Workbook

Sheet SL_PH
A1: NORKLE DATA | B1: REFERENCE ONLY
A3: targetData.version | B3: targetData.prodFmly1 | C3: targetData.prodFmly2 | D3: targetData.prodFmly3 | E3: targetData.segmentCode | F3: targetData.Cell_Name | G3: Subject Line | H3: Preheader | I3: Banner 1 Name | J3: Banner 1 - Image Path | K3: Banner 1 - Headline Copy | L3: Banner 1 - Subhead Copy | M3: Banner 1 - Subcopy | N3: Banner 1 - CTA Copy | O3: Banner 1 - CTA Link | P3: Banner 1 - CTA Deeplink | Q3: Banner 1 - CTA 2 Link | R3: Banner 1 - CTA 2 Deeplink | S3: Banner 2 Name | T3: Banner 2 - Image Path | U3: Banner 2 - Headline Copy | V3: Banner 2 - Subhead Copy | W3: Banner 2 - Subcopy | X3: Banner 2 - CTA Copy | Y3: Banner 2 - CTA Link | Z3: Banner 2 - CTA Deeplink | AA3: Banner 2 - CTA 2Copy | AB3: Banner 2 - CTA 2 Link | AC3: Banner 2 - CTA 2 Deeplink | AD3: Banner 3 Name | AE3: Banner 3 - Image Path | AF3: Banner 3 - Headline Copy | AG3: Banner 3 - Subhead Copy | AH3: Banner 3 - Subcopy | AI3: Banner 3 - CTA Copy | AJ3: Banner 3 - CTA Link | AK3: Banner 3 - CTA Deeplink | AL3: Banner 3 - CTA 2 Copy | AM3: Banner 3 - CTA 2 Link | AN3: Banner 3 - CTA 2 Deeplink | AO3: Banner 4 Name | AP3: Banner 4 - Image Path | AQ3: Banner 4 - Headline Copy | AR3: Banner 4 - Subhead Copy | AS3: Banner 4 - Subcopy | AT3: Banner 4 - CTA Copy | AU3: Banner 4 - CTA Link | AV3: Banner 4 - CTA Deeplink | AW3: Banner 4 - CTA 2 Copy | AX3: Banner 4 - CTA 2 Link | AY3: Banner 4 - CTA 2 Deeplink | AZ3: Banner 5 Name | BA3: Banner 5 - Image Path | BB3: Banner 5 - Headline Copy | BC3: Banner 5 - Subhead Copy | BD3: Banner 5 - Subcopy | BE3: Banner 5 - CTA Copy | BF3: Banner 5 - CTA Link | BG3: Banner 5 - CTA Deeplink | BH3: Banner 5 - CTA 2 Copy | BI3: Banner 5 - CTA 2 Link | BJ3: Banner 5- CTA 2 Deeplink | BK3: Banner 6 Name | BL3: Banner 6 - Image Path | BM3: Banner 6 - Headline Copy | BN3: Banner 6 - Subhead Copy | BO3: Banner 6 - Subcopy | BP3: Banner 6 - CTA Copy | BQ3: Banner 6 - CTA Link | BR3: Banner 6 - CTA Deeplink | BS3: Banner 6 - CTA 2 Copy | BT3: Banner 6 - CTA 2 Link | BU3: Banner 6 - CTA 2 Deeplink | BV3: Banner 7 Name | BW3: Banner 7 - Image Path | BX3: Banner 7 - Headline Copy | BY3: Banner 7 - Subhead Copy | BZ3: Banner 7 - Subcopy | CA3: Banner 7 - CTA Copy | CB3: Banner 7 - CTA Link | CC3: Banner 7 - CTA Deeplink | CD3: Banner 7 - CTA 2 Copy | CE3: Banner 7 - CTA 2 Link | CF3: Banner 7 - CTA 2 Deeplink | CG3: Banner 8 Name | CH3: Banner 8 - Image Path | CI3: Banner 8 - Headline Copy | CJ3: Banner 8 - Subhead Copy | CK3: Banner 8 - Subcopy | CL3: Banner 8 - CTA Copy | CM3: Banner 8 - CTA Link | CN3: Banner 8 - CTA Deeplink | CO3: Banner 8 - CTA 2 Copy | CP3: Banner 8 - CTA 2 Link | CQ3: Banner 8 - CTA 2 Deeplink | CR3: Banner 9 Name | CS3: Banner 9 - Image Path | CT3: Banner 9 - Headline Copy | CU3: Banner 9 - Subhead Copy | CV3: Banner 9 - Subcopy | CW3: Banner 9 - CTA Copy | CX3: Banner 9 - CTA Link | CY3: Banner 9 - CTA Deeplink | CZ3: Banner 9 - CTA 2 Copy | DA3: Banner 9 - CTA 2 Link | DB3: Banner 9 - CTA 2 Deeplink | DC3: Banner 10 Name | DD3: Banner 10 - Image Path | DE3: Banner 10 - Headline Copy | DF3: Banner 10 - Subhead Copy | DG3: Banner 10 - Subcopy | DH3: Banner 10 - CTA Copy | DI3: Banner 10 - CTA Link | DJ3: Banner 10 - CTA Deeplink | DK3: Banner 10 - CTA 2 Copy | DL3: Banner 10 - CTA 2 Link | DM3: Banner 10 - CTA 2 Deeplink | DN3: Banner 11 Name | DO3: Banner 11 - Image Path | DP3: Banner 11 - Headline Copy | DQ3: Banner 11 - Subhead Copy | DR3: Banner 11 - Subcopy | DS3: Banner 11 - CTA Copy | DT3: Banner 11 - CTA Link | DU3: Banner 11 - CTA Deeplink | DV3: Banner 11 - CTA 2 Copy | DW3: Banner 11 - CTA 2 Link | DX3: Banner 11 - CTA 2 Deeplink | DY3: Banner 12 Name | DZ3: Banner 12 - Image Path | EA3: Banner 12 - Headline Copy | EB3: Banner 12 - Subhead Copy | EC3: Banner 12 - Subcopy | ED3: Banner 12 - CTA Copy | EE3: Banner 12 - CTA Link | EF3: Banner 12 - CTA Deeplink | EG3: Banner 12 - CTA 2 Copy | EH3: Banner 12 - CTA 2 Link | EI3: Banner 12 - CTA 2 Deeplink | EJ3: Banner 13 Name | EK3: Banner 13 - Image Path | EL3: Banner 13 - Headline Copy | EM3: Banner 13 - Subhead Copy | EN3: Banner 13 - Subcopy | EO3: Banner 13 - CTA Copy | EP3: Banner 13 - CTA Link | EQ3: Banner 13 - CTA Deeplink | ER3: Banner 13 - CTA 2 Copy | ES3: Banner 13 - CTA 2 Link | ET3: Banner 13 - CTA 2 Deeplink | EU3: Banner 14 Name | EV3: Banner 14 - Image Path | EW3: Banner 14 - Headline Copy | EX3: Banner 14 - Subhead Copy | EY3: Banner 14 - Subcopy | EZ3: Banner 14 - CTA Copy | FA3: Banner 14 - CTA Link | FB3: Banner 14 - CTA Deeplink | FC3: Banner 14 - CTA 2 Copy | FD3: Banner 14 - CTA 2 Link | FE3: Banner 14 - CTA 2 Deeplink | FF3: Banner 15 Name | FG3: Banner 15 - Image Path | FH3: Banner 15 - Headline Copy | FI3: Banner 15 - Subhead Copy | FJ3: Banner 15 - Subcopy | FK3: Banner 15 - CTA Copy | FL3: Banner 15 - CTA Link | FM3: Banner 15 - CTA Deeplink | FN3: Banner 15 - CTA 2 Copy | FO3: Banner 15 - CTA 2 Link | FP3: Banner 15 - CTA 2 Deeplink
A4: DD | B4: MB_GALAXY MB_FOLD MB_NOTE MB_MID | C4: X | D4: X | E4: Reserver EPP_Reservers | G4: Cyber Monday is on. | H4: Act fast to save on showstopping gifts while supplies last. | I4: EPP Banner | J4: NULL | K4: NULL | L4: NULL | M4: NULL | N4: NULL | O4: NULL | P4: NULL | Q4: NULL | R4: NULL | S4: Hero & Countdown Timer Image | T4: ='Dynamic Banners'!$L$4 -> Cyber-monday-1.png | U4: ='Dynamic Banners'!$M$4 -> The clock is ticking away for Cyber Monday | V4: NULL | W4: ='Dynamic Banners'!$N$4 -> Shop amazing offers on showstopping products while supplies last. | X4: NULL | Y4: =[1]MiscBanners!$B$4 -> https://www.samsung.com/us/shop/all-deals/ | Z4: =[1]MiscBanners!$C$4 -> https://shopsamsung.page.link?link=https%3A%2F%2Fwww.samsung.com%2Fus%2Fshop%2Fall-deals%2F%3FofferCID%3DearlyAccess%26utm_source%3Dsamsung%26utm_medium%3Demail%26utm_campaign%3Dholiday_deals_t3_11172020%26marsLinkCategory%3D__MARSTRACKING__%26MKM_RID%3D__BPNUMBER__%26MKM_MID%3D__DELIVERNAME__%26cid%3D__CID____SEGMENTCODE__%26bpid%3D__BPNUMBER__%26iosparam%3Dsamsungestore%25253A%25252F%25252Fgototab%252523tab%25253D4%252523offerCID%25253DearlyAccess%252523utm_source%25253Dsamsung%252523utm_medium%25253Demail%252523utm_campaign%25253Dholiday_deals_t3_11172020%252523marsLinkCategory%25253D__MARSTRACKING__%252523MKM_RID%25253D__BPNUMBER__%252523MKM_MID%25253D__DELIVERNAME__%252523cid%25253D__CID____SEGMENTCODE__%252523bpid%25253D__BPNUMBER__&utm_source=samsung&utm_medium=email&utm_campaign=holiday_deals_t3_11172020&marsLinkCategory=__MARSTRACKING__&MKM_RID=__BPNUMBER__&MKM_MID=__DELIVERNAME__&cid=__CID____SEGMENTCODE__&bpid=__BPNUMBER__&apn=com.samsung.ecomm&al=samsungestore%3A%2F%2Fgototab%23tab%3D4%23offerCID%3DearlyAccess%23utm_source%3Dsamsung%23utm_medium%3Demail%23utm_campaign%3Dholiday_deals_t3_11172020%23marsLinkCategory%3D__MARSTRACKING__%23MKM_RID%3D__BPNUMBER__%23MKM_MID%3D__DELIVERNAME__%23cid%3D__CID____SEGMENTCODE__%23bpid%3D__BPNUMBER__&afl=https%3A%2F%2Fwww.samsung.com%2Fus%2Fshop%2Fall-deals%2F%3FofferCID%3DearlyAccess%26utm_source%3Dsamsung%26utm_medium%3Demail%26utm_campaign%3Dholiday_deals_t3_11172020%26marsLinkCategory%3D__MARSTRACKING__%26MKM_RID%3D__BPNUMBER__%26MKM_MID%3D__DELIVERNAME__%26cid%3D__CID____SEGMENTCODE__%26bpid%3D__BPNUMBER__&isi=1274679179&ibi=com.samsung.ShopSamsung&ius=samsungestore&ifl=https%3A%2F%2Fwww.samsung.com%2Fus%2Fshop%2Fall-deals%2F%3FofferCID%3DearlyAccess%26utm_source%3Dsamsung%26utm_medium%3Demail%26utm_campaign%3Dholiday_deals_t3_11172020%26marsLinkCategory%3D__MARSTRACKING__%26MKM_RID%3D__BPNUMBER__%26MKM_MID%3D__DELIVERNAME__%26cid%3D__CID____SEGMENTCODE__%26bpid%3D__BPNUMBER__&efr=1 | AA4: NULL | AB4: NULL | AC4: NULL | AD4: Hero & Countdown Timer Copy | AE4: NULL | AF4: NULL | AG4: While supplies last. | AH4: Today is your day to shop some of our greatest offers of the year. Plus, enjoy $30 or more instant credit§†, in addition to your exclusive $20 instant credit, with any smartphone purchase.‡ | AI4: NULL | AJ4: =[1]MiscBanners!$B$4 -> https://www.samsung.com/us/shop/all-deals/ | AK4: =[1]MiscBanners!$C$4 -> https://shopsamsung.page.link?link=https%3A%2F%2Fwww.samsung.com%2Fus%2Fshop%2Fall-deals%2F%3FofferCID%3DearlyAccess%26utm_source%3Dsamsung%26utm_medium%3Demail%26utm_campaign%3Dholiday_deals_t3_11172020%26marsLinkCategory%3D__MARSTRACKING__%26MKM_RID%3D__BPNUMBER__%26MKM_MID%3D__DELIVERNAME__%26cid%3D__CID____SEGMENTCODE__%26bpid%3D__BPNUMBER__%26iosparam%3Dsamsungestore%25253A%25252F%25252Fgototab%252523tab%25253D4%252523offerCID%25253DearlyAccess%252523utm_source%25253Dsamsung%252523utm_medium%25253Demail%252523utm_campaign%25253Dholiday_deals_t3_11172020%252523marsLinkCategory%25253D__MARSTRACKING__%252523MKM_RID%25253D__BPNUMBER__%252523MKM_MID%25253D__DELIVERNAME__%252523cid%25253D__CID____SEGMENTCODE__%252523bpid%25253D__BPNUMBER__&utm_source=samsung&utm_medium=email&utm_campaign=holiday_deals_t3_11172020&marsLinkCategory=__MARSTRACKING__&MKM_RID=__BPNUMBER__&MKM_MID=__DELIVERNAME__&cid=__CID____SEGMENTCODE__&bpid=__BPNUMBER__&apn=com.samsung.ecomm&al=samsungestore%3A%2F%2Fgototab%23tab%3D4%23offerCID%3DearlyAccess%23utm_source%3Dsamsung%23utm_medium%3Demail%23utm_campaign%3Dholiday_deals_t3_11172020%23marsLinkCategory%3D__MARSTRACKING__%23MKM_RID%3D__BPNUMBER__%23MKM_MID%3D__DELIVERNAME__%23cid%3D__CID____SEGMENTCODE__%23bpid%3D__BPNUMBER__&afl=https%3A%2F%2Fwww.samsung.com%2Fus%2Fshop%2Fall-deals%2F%3FofferCID%3DearlyAccess%26utm_source%3Dsamsung%26utm_medium%3Demail%26utm_campaign%3Dholiday_deals_t3_11172020%26marsLinkCategory%3D__MARSTRACKING__%26MKM_RID%3D__BPNUMBER__%26MKM_MID%3D__DELIVERNAME__%26cid%3D__CID____SEGMENTCODE__%26bpid%3D__BPNUMBER__&isi=1274679179&ibi=com.samsung.ShopSamsung&ius=samsungestore&ifl=https%3A%2F%2Fwww.samsung.com%2Fus%2Fshop%2Fall-deals%2F%3FofferCID%3DearlyAccess%26utm_source%3Dsamsung%26utm_medium%3Demail%26utm_campaign%3Dholiday_deals_t3_11172020%26marsLinkCategory%3D__MARSTRACKING__%26MKM_RID%3D__BPNUMBER__%26MKM_MID%3D__DELIVERNAME__%26cid%3D__CID____SEGMENTCODE__%26bpid%3D__BPNUMBER__&efr=1 | AL4: NULL | AM4: NULL | AN4: NULL | AO4: N20F (N20/N20U) | AP4: =DDOfferCopy!E4 -> 22_IM_HeadImage_MB_Note-500xV.jpg | AQ4: =DDOfferCopy!F4 -> Get up to 70% off Galaxy Note 20 5G or Note 20 Ultra 5G | AR4: =DDOfferCopy!G4 -> Now from only $8.34/mo for 36 mos⊕ or $299.99 with eligible trade-in.ᶿ | AS4: =DDOfferCopy!H4 -> Get $150 off instantly and up to $550 trade-in credit.ᶿ | AT4: =DDOfferCopy!I4 -> Buy now | AU4: =DDOfferCopy!J4 -> https://www.samsung.com/us/smartphones/galaxy-note20-5g/buy/ | AV4: =DDOfferCopy!K4 -> https://shopsamsung.page.link?link=https%3A%2F%2Fwww.samsung.com%2Fus%2Fsmartphones%2Fgalaxy-note20-5g%2Fbuy%2F%3FofferCID%3DearlyAccess%26utm_source%3Dsamsung%26utm_medium%3Demail%26utm_campaign%3Dholiday_deals_t3_11172020%26marsLinkCategory%3D__MARSTRACKING__%26MKM_RID%3D__BPNUMBER__%26MKM_MID%3D__DELIVERNAME__%26cid%3D__CID____SEGMENTCODE__%26bpid%3D__BPNUMBER__&utm_source=samsung&utm_medium=email&utm_campaign=holiday_deals_t3_11172020&marsLinkCategory=__MARSTRACKING__&MKM_RID=__BPNUMBER__&MKM_MID=__DELIVERNAME__&cid=__CID____SEGMENTCODE__&bpid=__BPNUMBER__&apn=com.samsung.ecomm&al=samsungestore%3A%2F%2Fopenwebview%23url%3Dhttps%3A%2F%2Fwww.samsung.com%2Fus%2Fbuy%2Fsmartphones%2Fgalaxy-note20-5g%2Findex.html%3FofferCID%3DearlyAccess%26segmentName%3DholidayReserve%23utm_source%3Dsamsung%23utm_medium%3Demail%23utm_campaign%3Dholiday_deals_t3_11172020%23marsLinkCategory%3D__MARSTRACKING__%23MKM_RID%3D__BPNUMBER__%23MKM_MID%3D__DELIVERNAME__%23cid%3D__CID____SEGMENTCODE__%23bpid%3D__BPNUMBER__&afl=https%3A%2F%2Fwww.samsung.com%2Fus%2Fsmartphones%2Fgalaxy-note20-5g%2Fbuy%2F%3FofferCID%3DearlyAccess%26utm_source%3Dsamsung%26utm_medium%3Demail%26utm_campaign%3Dholiday_deals_t3_11172020%26marsLinkCategory%3D__MARSTRACKING__%26MKM_RID%3D__BPNUMBER__%26MKM_MID%3D__DELIVERNAME__%26cid%3D__CID____SEGMENTCODE__%26bpid%3D__BPNUMBER__&efr=1 | AW4: =DDOfferCopy!L4 -> NULL | ... AY4: =DDOfferCopy!N4 -> NULL | AZ4: S20 Family (S20+, S20U, S20, S20FE) | BA4: =DDOfferCopy!E5 -> 21_IM_HeadImage_MB_Galaxy-500xV.jpg | BB4: =DDOfferCopy!F5 -> Get up to 73% off Galaxy S20 5G series devices | BC4: =DDOfferCopy!G5 -> Now from only $7.92/mo for 24 mos⊕ or $189.99 with eligible trade-in.ᶿ | BD4: =DDOfferCopy!H5 -> Get up to $150 off instantly and up to $460 trade-in credit.ᶿ | BE4: =DDOfferCopy!I5 -> Buy now | BF4: =DDOfferCopy!J5 -> https://www.samsung.com/us/mobile/galaxy-s20-5g/buy/ | BG4: =DDOfferCopy!K5 -> https://shopsamsung.page.link?link=https%3A%2F%2Fwww.samsung.com%2Fus%2Fmobile%2Fgalaxy-s20-5g%2Fbuy%2F%3FofferCID%3DearlyAccess%26utm_source%3Dsamsung%26utm_medium%3Demail%26utm_campaign%3Dholiday_deals_t3_11172020%26marsLinkCategory%3D__MARSTRACKING__%26MKM_RID%3D__BPNUMBER__%26MKM_MID%3D__DELIVERNAME__%26cid%3D__CID____SEGMENTCODE__%26bpid%3D__BPNUMBER__&utm_source=samsung&utm_medium=email&utm_campaign=holiday_deals_t3_11172020&marsLinkCategory=__MARSTRACKING__&MKM_RID=__BPNUMBER__&MKM_MID=__DELIVERNAME__&cid=__CID____SEGMENTCODE__&bpid=__BPNUMBER__&apn=com.samsung.ecomm&al=samsungestore%3A%2F%2Fopenwebview%23url%3Dhttps%3A%2F%2Fwww.samsung.com%2Fus%2Fbuy%2Fsmartphones%2Fgalaxy-s20-5g%2Findex.html%3FofferCID%3DearlyAccess%26segmentName%3DholidayReserve%23utm_source%3Dsamsung%23utm_medium%3Demail%23utm_campaign%3Dholiday_deals_t3_11172020%23marsLinkCategory%3D__MARSTRACKING__%23MKM_RID%3D__BPNUMBER__%23MKM_MID%3D__DELIVERNAME__%23cid%3D__CID____SEGMENTCODE__%23bpid%3D__BPNUMBER__&afl=https%3A%2F%2Fwww.samsung.com%2Fus%2Fmobile%2Fgalaxy-s20-5g%2Fbuy%2F%3FofferCID%3DearlyAccess%26utm_source%3Dsamsung%26utm_medium%3Demail%26utm_campaign%3Dholiday_deals_t3_11172020%26marsLinkCategory%3D__MARSTRACKING__%26MKM_RID%3D__BPNUMBER__%26MKM_MID%3D__DELIVERNAME__%26cid%3D__CID____SEGMENTCODE__%26bpid%3D__BPNUMBER__&efr=1 | BH4: =DDOfferCopy!L5 -> NULL | ... BJ4: =DDOfferCopy!N5 -> NULL | BK4: Fold2 | BL4: =DDOfferCopy!E6 -> 23_IM_HeadImage_MB_Fold-500xV.jpg | BM4: =DDOfferCopy!F6 -> Get up to 50% off Galaxy Z Fold2 5G | BN4: =DDOfferCopy!G6 -> Now from only $20.84/mo for 48 mos⊕ or $999.99 with eligible trade-in.ᶿ | BO4: =DDOfferCopy!H6 -> Our best Galaxy Z Fold2 5G offer of the year. Get up to $1000 trade-in credit.ᶿ Plus, get up to $120 instant credit toward accessories.§‡ | BP4: =DDOfferCopy!I6 -> Buy now | BQ4: =DDOfferCopy!J6 -> https://www.samsung.com/us/smartphones/galaxy-z-fold2-5g/buy/ | BR4: =DDOfferCopy!K6 -> https://shopsamsung.page.link?link=https%3A%2F%2Fwww.samsung.com%2Fus%2Fsmartphones%2Fgalaxy-z-fold2-5g%2Fbuy%2F%3FofferCID%3DearlyAccess%26utm_source%3Dsamsung%26utm_medium%3Demail%26utm_campaign%3Dholiday_deals_t3_11172020%26marsLinkCategory%3D__MARSTRACKING__%26MKM_RID%3D__BPNUMBER__%26MKM_MID%3D__DELIVERNAME__%26cid%3D__CID____SEGMENTCODE__%26bpid%3D__BPNUMBER__&utm_source=samsung&utm_medium=email&utm_campaign=holiday_deals_t3_11172020&marsLinkCategory=__MARSTRACKING__&MKM_RID=__BPNUMBER__&MKM_MID=__DELIVERNAME__&cid=__CID____SEGMENTCODE__&bpid=__BPNUMBER__&apn=com.samsung.ecomm&al=samsungestore%3A%2F%2Fopenwebview%23url%3Dhttps%3A%2F%2Fwww.samsung.com%2Fus%2Fbuy%2Fsmartphones%2Fgalaxy-z-fold2-5g%2Findex.html%3FofferCID%3DearlyAccess%26segmentName%3DholidayReserve%23utm_source%3Dsamsung%23utm_medium%3Demail%23utm_campaign%3Dholiday_deals_t3_11172020%23marsLinkCategory%3D__MARSTRACKING__%23MKM_RID%3D__BPNUMBER__%23MKM_MID%3D__DELIVERNAME__%23cid%3D__CID____SEGMENTCODE__%23bpid%3D__BPNUMBER__&afl=https%3A%2F%2Fwww.samsung.com%2Fus%2Fsmartphones%2Fgalaxy-z-fold2-5g%2Fbuy%2F%3FofferCID%3DearlyAccess%26utm_source%3Dsamsung%26utm_medium%3Demail%26utm_campaign%3Dholiday_deals_t3_11172020%26marsLinkCategory%3D__MARSTRACKING__%26MKM_RID%3D__BPNUMBER__%26MKM_MID%3D__DELIVERNAME__%26cid%3D__CID____SEGMENTCODE__%26bpid%3D__BPNUMBER__&efr=1 | BS4: =DDOfferCopy!L6 -> NULL | ... BU4: =DDOfferCopy!N6 -> NULL | BV4: A71 5G / A51 5G | BW4: =DDOfferCopy!E7 -> 24-IM-A71-A51-HeadImage-500xV.jpg | BX4: =DDOfferCopy!F7 -> Get 50% off Galaxy A71 5G with T-Mobile and Verizon | BY4: =DDOfferCopy!G7 -> Now from only only $8.34/mo for 36 mos⊕ or $299.99 with eligible trade-in.ᶿ | BZ4: =DDOfferCopy!H7 -> Save up to $250 instantly and get $75 or more trade-in credit. Treat yourself to blazing fast 5G speeds and incredible features at an amazing value. | CA4: =DDOfferCopy!I7 -> Buy now | CB4: =DDOfferCopy!J7 -> https://www.samsung.com/us/mobile/phones/galaxy-a/buy/?link=galaxy-a71-5g | CC4: =DDOfferCopy!K7 -> https://shopsamsung.page.link?link=https%3A%2F%2Fwww.samsung.com%2Fus%2Fmobile%2Fphones%2Fgalaxy-a%2Fbuy%2F%3Flink%3Dgalaxy-a71-5g%26offerCID%3DearlyAccess%26utm_source%3Dsamsung%26utm_medium%3Demail%26utm_campaign%3Dholiday_deals_t3_11172020%26marsLinkCategory%3D__MARSTRACKING__%26MKM_RID%3D__BPNUMBER__%26MKM_MID%3D__DELIVERNAME__%26cid%3D__CID____SEGMENTCODE__%26bpid%3D__BPNUMBER__&utm_source=samsung&utm_medium=email&utm_campaign=holiday_deals_t3_11172020&marsLinkCategory=__MARSTRACKING__&MKM_RID=__BPNUMBER__&MKM_MID=__DELIVERNAME__&cid=__CID____SEGMENTCODE__&bpid=__BPNUMBER__&apn=com.samsung.ecomm&al=samsungestore%3A%2F%2Fopenwebview%23url%3Dhttps%3A%2F%2Fwww.samsung.com%2Fus%2Fbuy%2Fsmartphones%2Fgalaxy-a50%2Findex.html%3Flink%3Dgalaxy-a71-5g%26offerCID%3DearlyAccess%26segmentName%3DholidayReserve%23utm_source%3Dsamsung%23utm_medium%3Demail%23utm_campaign%3Dholiday_deals_t3_11172020%23marsLinkCategory%3D__MARSTRACKING__%23MKM_RID%3D__BPNUMBER__%23MKM_MID%3D__DELIVERNAME__%23cid%3D__CID____SEGMENTCODE__%23bpid%3D__BPNUMBER__&afl=https%3A%2F%2Fwww.samsung.com%2Fus%2Fmobile%2Fphones%2Fgalaxy-a%2Fbuy%2F%3Flink%3Dgalaxy-a71-5g%26offerCID%3DearlyAccess%26utm_source%3Dsamsung%26utm_medium%3Demail%26utm_campaign%3Dholiday_deals_t3_11172020%26marsLinkCategory%3D__MARSTRACKING__%26MKM_RID%3D__BPNUMBER__%26MKM_MID%3D__DELIVERNAME__%26cid%3D__CID____SEGMENTCODE__%26bpid%3D__BPNUMBER__&efr=1 | CD4: =DDOfferCopy!L7 -> NULL | ... CF4: =DDOfferCopy!N7 -> NULL | CG4: GIFT GUIDE | CH4: =MiscBanners!$H$4 -> Give-wonder-500xV.jpg | CI4: =MiscBanners!$I$4 -> The gift that keeps on giving | CJ4: =MiscBanners!$J$4 -> NULL | CK4: =MiscBanners!$K$4 -> Discover even more exclusive offers on your favorite products and unlock the power of smart and savvy gifting. | CL4: =MiscBanners!$L$4 -> Shop now | CM4: =MiscBanners!$M$4 -> https://www.samsung.com/us/gift-ideas/ | CN4: =MiscBanners!$N$4 -> https://shopsamsung.page.link?link=https%3A%2F%2Fwww.samsung.com%2Fus%2Fgift-ideas%2F%3FofferCID%3DearlyAccess%26utm_source%3Dsamsung%26utm_medium%3Demail%26utm_campaign%3Dholiday_deals_t3_11172020%26marsLinkCategory%3D__MARSTRACKING__%26MKM_RID%3D__BPNUMBER__%26MKM_MID%3D__DELIVERNAME__%26cid%3D__CID____SEGMENTCODE__%26bpid%3D__BPNUMBER__%26iosparam%3Dsamsungestore%25253A%25252F%25252Fopenwebview%252523url%25253Dhttps%25253A%25252F%25252Fwww.samsung.com%25252Fus%25252Fapp%25252Fgift-ideas%25252F%25253FofferCID%25253DearlyAccess%252526segmentName%25253DholidayReserve%252523utm_source%25253Dsamsung%252523utm_medium%25253Demail%252523utm_campaign%25253Dholiday_deals_t3_11172020%252523marsLinkCategory%25253D__MARSTRACKING__%252523MKM_RID%25253D__BPNUMBER__%252523MKM_MID%25253D__DELIVERNAME__%252523cid%25253D__CID____SEGMENTCODE__%252523bpid%25253D__BPNUMBER__&utm_source=samsung&utm_medium=email&utm_campaign=holiday_deals_t3_11172020&marsLinkCategory=__MARSTRACKING__&MKM_RID=__BPNUMBER__&MKM_MID=__DELIVERNAME__&cid=__CID____SEGMENTCODE__&bpid=__BPNUMBER__&apn=com.samsung.ecomm&al=samsungestore%3A%2F%2Fopenwebview%23url%3Dhttps%3A%2F%2Fwww.samsung.com%2Fus%2Fapp%2Fgift-ideas%2F%3FofferCID%3DearlyAccess%26segmentName%3DholidayReserve%23utm_source%3Dsamsung%23utm_medium%3Demail%23utm_campaign%3Dholiday_deals_t3_11172020%23marsLinkCategory%3D__MARSTRACKING__%23MKM_RID%3D__BPNUMBER__%23MKM_MID%3D__DELIVERNAME__%23cid%3D__CID____SEGMENTCODE__%23bpid%3D__BPNUMBER__&afl=https%3A%2F%2Fwww.samsung.com%2Fus%2Fgift-ideas%2F%3FofferCID%3DearlyAccess%26utm_source%3Dsamsung%26utm_medium%3Demail%26utm_campaign%3Dholiday_deals_t3_11172020%26marsLinkCategory%3D__MARSTRACKING__%26MKM_RID%3D__BPNUMBER__%26MKM_MID%3D__DELIVERNAME__%26cid%3D__CID____SEGMENTCODE__%26bpid%3D__BPNUMBER__&isi=1274679179&ibi=com.samsung.ShopSamsung&ius=samsungestore&ifl=https%3A%2F%2Fwww.samsung.com%2Fus%2Fgift-ideas%2F%3FofferCID%3DearlyAccess%26utm_source%3Dsamsung%26utm_medium%3Demail%26utm_campaign%3Dholiday_deals_t3_11172020%26marsLinkCategory%3D__MARSTRACKING__%26MKM_RID%3D__BPNUMBER__%26MKM_MID%3D__DELIVERNAME__%26cid%3D__CID____SEGMENTCODE__%26bpid%3D__BPNUMBER__&efr=1 | CO4: =MiscBanners!$O$4 -> NULL | CP4: =MiscBanners!$P$4 -> NULL | CQ4: =MiscBanners!$Q$4 -> NULL | CR4: FOOTER | DC4: TC 1 | DD4: =TC!B2 -> NULL | DE4: =TC!C2 -> NULL | DF4: =TC!D2 -> NULL | DG4: =TC!E2 -> ᶿFor a limited time only, on Samsung.com/Shop Samsung App, pre-order or purchase a new qualifying Galaxy device (“Qualifying Purchase”), send in your qualifying trade-in device to Samsung through the Samsung Trade-In Program, and if Samsung determines your trade-in device meets all eligibility requirements, you will receive a trade-in credit specific to your qualifying trade-in device to apply toward your Qualifying Purchase. Device models that currently qualify for trade-in and trade-in credit amounts associated with those models are available on Samsung.com and the Shop Samsung App; eligible models and amounts may change at Samsung’s sole discretion. To be eligible for trade-in, your qualifying device must meet all Trade-In Program eligibility requirements, which include, but are not limited to, that the device powers on, holds a charge, and does not power off unexpectedly; has a functioning display; has no breaks or cracks in the screen (unless a cracked screen offer applies); has no breaks or cracks in the case; has no liquid damage (whether visible or not); has no other defects that go beyond normal wear and tear; is not on a black list; has a verified FCC ID; has been reset to factory settings; has all personal information removed; has all software locks disabled; and is owned by you (leased devices are not eligible). Anticipated trade-in value will be applied as a credit at time of purchase, but, if you do not send in your trade-in device within 15 days of receipt of your Qualifying Purchase, you will be charged back for the trade-in credit applied to your purchase, or if you send in your trade-in device within 15 days of receipt of your Qualifying Purchase but Samsung determines your device does not meet all eligibility requirements, you will be charged back for the trade-in credit applied to your purchase minus $25. Participation in this program does not excuse you from contracts with your carrier or retailer (or any related payments or fees) for the device that was traded in. Limit 1 trade-in per Qualifying Purchase. Samsung reserves the right to modify or discontinue this offer at any time. The Trade-In Program cannot be combined with any other Samsung, carrier or retailer promotions, discounts, or offers unless specifically provided for in the terms and conditions of such offers. Additional terms, including terms that govern the resolution of disputes, apply. Click here to learn more. | DH4: =TC!F2 -> NULL | DI4: =TC!G2 -> https://www.samsung.com/us/trade-in/terms-and-conditions/ | DJ4: =TC!H2 -> 0 | DK4: =TC!I2 -> NULL | ... DM4: =TC!K2 -> NULL | DN4: TC2 | DO4: =TC!B3 -> NULL | DP4: =TC!C3 -> NULL | DQ4: =TC!D3 -> NULL | DR4: =TC!E3 -> ⊕0% APR for 24, 36, 40 or 48 Months with Equal Payments: Available on purchases of select products charged to a Samsung Financing account. Minimum purchase: $50. 0% APR from date of eligible purchase until paid in full. Estimated monthly payment equals the eligible purchase amount multiplied by a repayment factor and rounded to the nearest penny (repayment factors: .04167 for 24 month, .02778 for 36 month, .02500 for 40 month, .02083 for 48 month). Last payment may vary due to rounding. Total amount of payments will not exceed eligible purchase amount. Other transactions and fees affect overall minimum payment amount. Advertised payment amount is an estimate and may change once taxes, delivery or other charges are added. Limited time offer. Regular account terms apply to non-promo purchases. Minimum interest charge: $1. Standard Purchase APR: 29.99%. Prior purchases excluded. Account must be in good standing. Subject to credit approval. Samsung Financing account issued by TD Bank, N.A. | DS4: =TC!F3 -> NULL | DT4: =TC!G3 -> 0 | DU4: =TC!H3 -> 0 | DV4: =TC!I3 -> NULL | ... DX4: =TC!K3 -> NULL | DY4: TC3 | DZ4: =TC!B4 -> NULL | EA4: =TC!C4 -> NULL | EB4: =TC!D4 -> NULL | EC4: =TC!E4 -> §18+ & 50 US/DC only. By 11/29/2020 11:59 PM EST, purchase a qualifying device on device installment plan, 2-year contract plan, lease or outright purchase at full retail price (“Qualifying Purchase”), & receive a Samsung Credit of $100 (“Gift”) instant credit from Samsung for use towards an eligible purchase including select wearables, tablets, PC’s and accessories when you purchase qualifying smartphone (“Qualifying Purchase”) before 01/15/21 at 11:59 PM EST. You must make a Qualifying Purchase on Samsung.com or the Shop Samsung App to receive an instant credit which may be applied instantly or deferred to a future eligible purchase. Gift valid for use on eligible purchases from 11/10/20- 01/15/21 or while supplies last, and is a one-time use certificate; when first used, any value not used is lost. Gift is non-transferrable and limited to 1 instant credit per registered customer. Samsung Credits are valid only at www.Samsung.com or in the App for use towards an eligible purchase. Void where prohibited or restricted by law. Additional restrictions apply. Offer subject to additional terms here. Samsung reserves the right to modify or discontinue offer at any time by posting notice on the app or website | ED4: =TC!F4 -> NULL | EE4: =TC!G4 -> https://www.samsung.com/us/ | EF4: =TC!H4 -> 0 | EG4: =TC!I4 -> NULL | ... EI4: =TC!K4 -> NULL | EJ4: TC4 | EK4: =TC!B5 -> NULL | EL4: =TC!C5 -> NULL | EM4: =TC!D5 -> NULL | EN4: =TC!E5 -> †18+ & 50 US/DC only. By 11/29/2020 11:59 PM EST, purchase a qualifying device on device installment plan, 2-year contract plan, lease or outright purchase at full retail price (“Qualifying Purchase”), & receive a Samsung Credit of $30 (“Gift”) instant credit from Samsung for use towards an eligible purchase including select wearables, tablets, PC’s and accessories when you purchase qualifying smartphone (“Qualifying Purchase”) before 01/15/21 at 11:59 PM EST. You must make a Qualifying Purchase on Samsung.com or the Shop Samsung App to receive an instant credit which may be applied instantly or deferred to a future eligible purchase. Gift valid for use on eligible purchases from 11/10/20- 01/15/21 or while supplies last, and is a one-time use certificate; when first used, any value not used is lost. Gift is non-transferrable and limited to 1 instant credit per registered customer. Samsung Credits are valid only at www.Samsung.com or in the App for use towards an eligible purchase. Void where prohibited or restricted by law. Additional restrictions apply. Offer subject to additional terms here. Samsung reserves the right to modify or discontinue offer at any time by posting notice on the app or website | EO4: =TC!F5 -> NULL | EP4: =TC!G5 -> https://www.samsung.com/us/ | EQ4: =TC!H5 -> 0 | ER4: =TC!I5 -> NULL | ... ET4: =TC!K5 -> NULL | EU4: TC5 | EV4: =TC!B6 -> NULL | EW4: =TC!C6 -> NULL | EX4: =TC!D6 -> NULL | EY4: =TC!E6 -> ‡18+ & 50 US/DC only. Between 10/26/20 at 12:01 AM EST and 11/18/20 at 11:59 PM EST (“Registration Period”), register for the Samsung Holiday instant credit promotion to receive a $20 instant credit from Samsung for use towards an eligible purchase including select wearables, tablets, PC’s and accessories when you purchase qualifying smartphone (“Qualifying Purchase”) before 01/15/21 at 11:59 PM EST. You must make a Qualifying Purchase on Samsung.com or the Shop Samsung App to receive an instant credit which may be applied instantly or deferred to a future eligible purchase. Gift valid for use on eligible purchases from 11/10/20- 01/15/21 or while supplies last, and is a one-time use certificate; when first used, any value not used is lost. Gift is non-transferrable and limited to 1 instant credit per registered customer. Samsung Credits are valid only at www.Samsung.com or in the App for use towards an eligible purchase. Void where prohibited or restricted by law. Additional restrictions apply. Offer subject to additional terms here. Samsung reserves the right to modify or discontinue offer at any time by posting notice on the app or website. | EZ4: =TC!F6 -> NULL | FA4: =TC!G6 -> https://www.samsung.com/us/ | FB4: =TC!H6 -> 0 | FC4: =TC!I6 -> NULL | ... FE4: =TC!K6 -> NULL
A5: DD | B5: MB_GALAXY MB_FOLD MB_NOTE MB_MID | C5: X | D5: X | E5: Non_Reservers EPP_NonReservers | G5: Cyber Monday is on. | H5: Act fast to save on showstopping gifts while supplies last. | I5: EPP Banner | J5: NULL | K5: NULL | L5: NULL | M5: NULL | N5: NULL | O5: NULL | P5: NULL | Q5: NULL | R5: NULL | S5: Hero & Countdown Timer Image | T5: ='Dynamic Banners'!$L$4 -> Cyber-monday-1.png | U5: ='Dynamic Banners'!$M$4 -> The clock is ticking away for Cyber Monday | V5: NULL | W5: ='Dynamic Banners'!$N$4 -> Shop amazing offers on showstopping products while supplies last. | X5: NULL | Y5: =[1]MiscBanners!$B$4 -> https://www.samsung.com/us/shop/all-deals/ | Z5: =[1]MiscBanners!$C$4 -> https://shopsamsung.page.link?link=https%3A%2F%2Fwww.samsung.com%2Fus%2Fshop%2Fall-deals%2F%3FofferCID%3DearlyAccess%26utm_source%3Dsamsung%26utm_medium%3Demail%26utm_campaign%3Dholiday_deals_t3_11172020%26marsLinkCategory%3D__MARSTRACKING__%26MKM_RID%3D__BPNUMBER__%26MKM_MID%3D__DELIVERNAME__%26cid%3D__CID____SEGMENTCODE__%26bpid%3D__BPNUMBER__%26iosparam%3Dsamsungestore%25253A%25252F%25252Fgototab%252523tab%25253D4%252523offerCID%25253DearlyAccess%252523utm_source%25253Dsamsung%252523utm_medium%25253Demail%252523utm_campaign%25253Dholiday_deals_t3_11172020%252523marsLinkCategory%25253D__MARSTRACKING__%252523MKM_RID%25253D__BPNUMBER__%252523MKM_MID%25253D__DELIVERNAME__%252523cid%25253D__CID____SEGMENTCODE__%252523bpid%25253D__BPNUMBER__&utm_source=samsung&utm_medium=email&utm_campaign=holiday_deals_t3_11172020&marsLinkCategory=__MARSTRACKING__&MKM_RID=__BPNUMBER__&MKM_MID=__DELIVERNAME__&cid=__CID____SEGMENTCODE__&bpid=__BPNUMBER__&apn=com.samsung.ecomm&al=samsungestore%3A%2F%2Fgototab%23tab%3D4%23offerCID%3DearlyAccess%23utm_source%3Dsamsung%23utm_medium%3Demail%23utm_campaign%3Dholiday_deals_t3_11172020%23marsLinkCategory%3D__MARSTRACKING__%23MKM_RID%3D__BPNUMBER__%23MKM_MID%3D__DELIVERNAME__%23cid%3D__CID____SEGMENTCODE__%23bpid%3D__BPNUMBER__&afl=https%3A%2F%2Fwww.samsung.com%2Fus%2Fshop%2Fall-deals%2F%3FofferCID%3DearlyAccess%26utm_source%3Dsamsung%26utm_medium%3Demail%26utm_campaign%3Dholiday_deals_t3_11172020%26marsLinkCategory%3D__MARSTRACKING__%26MKM_RID%3D__BPNUMBER__%26MKM_MID%3D__DELIVERNAME__%26cid%3D__CID____SEGMENTCODE__%26bpid%3D__BPNUMBER__&isi=1274679179&ibi=com.samsung.ShopSamsung&ius=samsungestore&ifl=https%3A%2F%2Fwww.samsung.com%2Fus%2Fshop%2Fall-deals%2F%3FofferCID%3DearlyAccess%26utm_source%3Dsamsung%26utm_medium%3Demail%26utm_campaign%3Dholiday_deals_t3_11172020%26marsLinkCategory%3D__MARSTRACKING__%26MKM_RID%3D__BPNUMBER__%26MKM_MID%3D__DELIVERNAME__%26cid%3D__CID____SEGMENTCODE__%26bpid%3D__BPNUMBER__&efr=1 | AA5: NULL | AB5: NULL | AC5: NULL | AD5: Hero & Countdown Timer Copy | AE5: NULL | AF5: NULL | AG5: While supplies last. | AH5: Today is your day to shop some of our greatest offers of the year. Plus, unlock $30 or more instant credit with any smartphone purchase.§† | AI5: NULL | AJ5: =[1]MiscBanners!$B$4 -> https://www.samsung.com/us/shop/all-deals/ | AK5: =[1]MiscBanners!$C$4 -> https://shopsamsung.page.link?link=https%3A%2F%2Fwww.samsung.com%2Fus%2Fshop%2Fall-deals%2F%3FofferCID%3DearlyAccess%26utm_source%3Dsamsung%26utm_medium%3Demail%26utm_campaign%3Dholiday_deals_t3_11172020%26marsLinkCategory%3D__MARSTRACKING__%26MKM_RID%3D__BPNUMBER__%26MKM_MID%3D__DELIVERNAME__%26cid%3D__CID____SEGMENTCODE__%26bpid%3D__BPNUMBER__%26iosparam%3Dsamsungestore%25253A%25252F%25252Fgototab%252523tab%25253D4%252523offerCID%25253DearlyAccess%252523utm_source%25253Dsamsung%252523utm_medium%25253Demail%252523utm_campaign%25253Dholiday_deals_t3_11172020%252523marsLinkCategory%25253D__MARSTRACKING__%252523MKM_RID%25253D__BPNUMBER__%252523MKM_MID%25253D__DELIVERNAME__%252523cid%25253D__CID____SEGMENTCODE__%252523bpid%25253D__BPNUMBER__&utm_source=samsung&utm_medium=email&utm_campaign=holiday_deals_t3_11172020&marsLinkCategory=__MARSTRACKING__&MKM_RID=__BPNUMBER__&MKM_MID=__DELIVERNAME__&cid=__CID____SEGMENTCODE__&bpid=__BPNUMBER__&apn=com.samsung.ecomm&al=samsungestore%3A%2F%2Fgototab%23tab%3D4%23offerCID%3DearlyAccess%23utm_source%3Dsamsung%23utm_medium%3Demail%23utm_campaign%3Dholiday_deals_t3_11172020%23marsLinkCategory%3D__MARSTRACKING__%23MKM_RID%3D__BPNUMBER__%23MKM_MID%3D__DELIVERNAME__%23cid%3D__CID____SEGMENTCODE__%23bpid%3D__BPNUMBER__&afl=https%3A%2F%2Fwww.samsung.com%2Fus%2Fshop%2Fall-deals%2F%3FofferCID%3DearlyAccess%26utm_source%3Dsamsung%26utm_medium%3Demail%26utm_campaign%3Dholiday_deals_t3_11172020%26marsLinkCategory%3D__MARSTRACKING__%26MKM_RID%3D__BPNUMBER__%26MKM_MID%3D__DELIVERNAME__%26cid%3D__CID____SEGMENTCODE__%26bpid%3D__BPNUMBER__&isi=1274679179&ibi=com.samsung.ShopSamsung&ius=samsungestore&ifl=https%3A%2F%2Fwww.samsung.com%2Fus%2Fshop%2Fall-deals%2F%3FofferCID%3DearlyAccess%26utm_source%3Dsamsung%26utm_medium%3Demail%26utm_campaign%3Dholiday_deals_t3_11172020%26marsLinkCategory%3D__MARSTRACKING__%26MKM_RID%3D__BPNUMBER__%26MKM_MID%3D__DELIVERNAME__%26cid%3D__CID____SEGMENTCODE__%26bpid%3D__BPNUMBER__&efr=1 | AL5: NULL | AM5: NULL | AN5: NULL | AO5: N20F (N20/N20U) | AP5: =DDOfferCopy!E4 -> 22_IM_HeadImage_MB_Note-500xV.jpg | AQ5: =DDOfferCopy!F4 -> Get up to 70% off Galaxy Note 20 5G or Note 20 Ultra 5G | AR5: =DDOfferCopy!G4 -> Now from only $8.34/mo for 36 mos⊕ or $299.99 with eligible trade-in.ᶿ | AS5: =DDOfferCopy!H4 -> Get $150 off instantly and up to $550 trade-in credit.ᶿ | AT5: =DDOfferCopy!I4 -> Buy now | AU5: =DDOfferCopy!P4 -> https://www.samsung.com/us/smartphones/galaxy-note20-5g/buy/ | AV5: =DDOfferCopy!$Q$4 -> https://shopsamsung.page.link?link=https%3A%2F%2Fwww.samsung.com%2Fus%2Fsmartphones%2Fgalaxy-note20-5g%2Fbuy%2F%3Futm_source%3Dsamsung%26utm_medium%3Demail%26utm_campaign%3Dholiday_deals_t3_11172020%26marsLinkCategory%3D__MARSTRACKING__%26MKM_RID%3D__BPNUMBER__%26MKM_MID%3D__DELIVERNAME__%26cid%3D__CID____SEGMENTCODE__%26bpid%3D__BPNUMBER__&utm_source=samsung&utm_medium=email&utm_campaign=holiday_deals_t3_11172020&marsLinkCategory=__MARSTRACKING__&MKM_RID=__BPNUMBER__&MKM_MID=__DELIVERNAME__&cid=__CID____SEGMENTCODE__&bpid=__BPNUMBER__&apn=com.samsung.ecomm&al=samsungestore%3A%2F%2Fopenwebview%23url%3Dhttps%3A%2F%2Fwww.samsung.com%2Fus%2Fbuy%2Fsmartphones%2Fgalaxy-note20-5g%2Findex.html%23utm_source%3Dsamsung%23utm_medium%3Demail%23utm_campaign%3Dholiday_deals_t3_11172020%23marsLinkCategory%3D__MARSTRACKING__%23MKM_RID%3D__BPNUMBER__%23MKM_MID%3D__DELIVERNAME__%23cid%3D__CID____SEGMENTCODE__%23bpid%3D__BPNUMBER__&afl=https%3A%2F%2Fwww.samsung.com%2Fus%2Fsmartphones%2Fgalaxy-note20-5g%2Fbuy%2F%3Futm_source%3Dsamsung%26utm_medium%3Demail%26utm_campaign%3Dholiday_deals_t3_11172020%26marsLinkCategory%3D__MARSTRACKING__%26MKM_RID%3D__BPNUMBER__%26MKM_MID%3D__DELIVERNAME__%26cid%3D__CID____SEGMENTCODE__%26bpid%3D__BPNUMBER__&efr=1 | AW5: =DDOfferCopy!R4 -> NULL | AX5: =DDOfferCopy!S4 -> NULL | AY5: =DDOfferCopy!T4 -> NULL | AZ5: S20 Family (S20+, S20U, S20, S20FE) | BA5: =DDOfferCopy!E5 -> 21_IM_HeadImage_MB_Galaxy-500xV.jpg | BB5: =DDOfferCopy!F5 -> Get up to 73% off Galaxy S20 5G series devices | BC5: =DDOfferCopy!G5 -> Now from only $7.92/mo for 24 mos⊕ or $189.99 with eligible trade-in.ᶿ | BD5: =DDOfferCopy!H5 -> Get up to $150 off instantly and up to $460 trade-in credit.ᶿ | BE5: =DDOfferCopy!I5 -> Buy now | BF5: =DDOfferCopy!J5 -> https://www.samsung.com/us/mobile/galaxy-s20-5g/buy/ | BG5: =DDOfferCopy!K5 -> https://shopsamsung.page.link?link=https%3A%2F%2Fwww.samsung.com%2Fus%2Fmobile%2Fgalaxy-s20-5g%2Fbuy%2F%3FofferCID%3DearlyAccess%26utm_source%3Dsamsung%26utm_medium%3Demail%26utm_campaign%3Dholiday_deals_t3_11172020%26marsLinkCategory%3D__MARSTRACKING__%26MKM_RID%3D__BPNUMBER__%26MKM_MID%3D__DELIVERNAME__%26cid%3D__CID____SEGMENTCODE__%26bpid%3D__BPNUMBER__&utm_source=samsung&utm_medium=email&utm_campaign=holiday_deals_t3_11172020&marsLinkCategory=__MARSTRACKING__&MKM_RID=__BPNUMBER__&MKM_MID=__DELIVERNAME__&cid=__CID____SEGMENTCODE__&bpid=__BPNUMBER__&apn=com.samsung.ecomm&al=samsungestore%3A%2F%2Fopenwebview%23url%3Dhttps%3A%2F%2Fwww.samsung.com%2Fus%2Fbuy%2Fsmartphones%2Fgalaxy-s20-5g%2Findex.html%3FofferCID%3DearlyAccess%26segmentName%3DholidayReserve%23utm_source%3Dsamsung%23utm_medium%3Demail%23utm_campaign%3Dholiday_deals_t3_11172020%23marsLinkCategory%3D__MARSTRACKING__%23MKM_RID%3D__BPNUMBER__%23MKM_MID%3D__DELIVERNAME__%23cid%3D__CID____SEGMENTCODE__%23bpid%3D__BPNUMBER__&afl=https%3A%2F%2Fwww.samsung.com%2Fus%2Fmobile%2Fgalaxy-s20-5g%2Fbuy%2F%3FofferCID%3DearlyAccess%26utm_source%3Dsamsung%26utm_medium%3Demail%26utm_campaign%3Dholiday_deals_t3_11172020%26marsLinkCategory%3D__MARSTRACKING__%26MKM_RID%3D__BPNUMBER__%26MKM_MID%3D__DELIVERNAME__%26cid%3D__CID____SEGMENTCODE__%26bpid%3D__BPNUMBER__&efr=1 | BH5: =DDOfferCopy!L5 -> NULL | ... BJ5: =DDOfferCopy!N5 -> NULL | BK5: Fold2 | BL5: =DDOfferCopy!E6 -> 23_IM_HeadImage_MB_Fold-500xV.jpg | BM5: =DDOfferCopy!F6 -> Get up to 50% off Galaxy Z Fold2 5G | BN5: =DDOfferCopy!G6 -> Now from only $20.84/mo for 48 mos⊕ or $999.99 with eligible trade-in.ᶿ | BO5: =DDOfferCopy!H6 -> Our best Galaxy Z Fold2 5G offer of the year. Get up to $1000 trade-in credit.ᶿ Plus, get up to $120 instant credit toward accessories.§‡ | BP5: =DDOfferCopy!I6 -> Buy now | BQ5: =DDOfferCopy!J6 -> https://www.samsung.com/us/smartphones/galaxy-z-fold2-5g/buy/ | BR5: =DDOfferCopy!K6 -> https://shopsamsung.page.link?link=https%3A%2F%2Fwww.samsung.com%2Fus%2Fsmartphones%2Fgalaxy-z-fold2-5g%2Fbuy%2F%3FofferCID%3DearlyAccess%26utm_source%3Dsamsung%26utm_medium%3Demail%26utm_campaign%3Dholiday_deals_t3_11172020%26marsLinkCategory%3D__MARSTRACKING__%26MKM_RID%3D__BPNUMBER__%26MKM_MID%3D__DELIVERNAME__%26cid%3D__CID____SEGMENTCODE__%26bpid%3D__BPNUMBER__&utm_source=samsung&utm_medium=email&utm_campaign=holiday_deals_t3_11172020&marsLinkCategory=__MARSTRACKING__&MKM_RID=__BPNUMBER__&MKM_MID=__DELIVERNAME__&cid=__CID____SEGMENTCODE__&bpid=__BPNUMBER__&apn=com.samsung.ecomm&al=samsungestore%3A%2F%2Fopenwebview%23url%3Dhttps%3A%2F%2Fwww.samsung.com%2Fus%2Fbuy%2Fsmartphones%2Fgalaxy-z-fold2-5g%2Findex.html%3FofferCID%3DearlyAccess%26segmentName%3DholidayReserve%23utm_source%3Dsamsung%23utm_medium%3Demail%23utm_campaign%3Dholiday_deals_t3_11172020%23marsLinkCategory%3D__MARSTRACKING__%23MKM_RID%3D__BPNUMBER__%23MKM_MID%3D__DELIVERNAME__%23cid%3D__CID____SEGMENTCODE__%23bpid%3D__BPNUMBER__&afl=https%3A%2F%2Fwww.samsung.com%2Fus%2Fsmartphones%2Fgalaxy-z-fold2-5g%2Fbuy%2F%3FofferCID%3DearlyAccess%26utm_source%3Dsamsung%26utm_medium%3Demail%26utm_campaign%3Dholiday_deals_t3_11172020%26marsLinkCategory%3D__MARSTRACKING__%26MKM_RID%3D__BPNUMBER__%26MKM_MID%3D__DELIVERNAME__%26cid%3D__CID____SEGMENTCODE__%26bpid%3D__BPNUMBER__&efr=1 | BS5: =DDOfferCopy!L6 -> NULL | ... BU5: =DDOfferCopy!N6 -> NULL | BV5: A71 5G / A51 5G | BW5: =DDOfferCopy!E7 -> 24-IM-A71-A51-HeadImage-500xV.jpg | BX5: =DDOfferCopy!F7 -> Get 50% off Galaxy A71 5G with T-Mobile and Verizon | BY5: =DDOfferCopy!G7 -> Now from only only $8.34/mo for 36 mos⊕ or $299.99 with eligible trade-in.ᶿ | BZ5: =DDOfferCopy!H7 -> Save up to $250 instantly and get $75 or more trade-in credit. Treat yourself to blazing fast 5G speeds and incredible features at an amazing value. | CA5: =DDOfferCopy!I7 -> Buy now | CB5: =DDOfferCopy!J7 -> https://www.samsung.com/us/mobile/phones/galaxy-a/buy/?link=galaxy-a71-5g | CC5: =DDOfferCopy!K7 -> https://shopsamsung.page.link?link=https%3A%2F%2Fwww.samsung.com%2Fus%2Fmobile%2Fphones%2Fgalaxy-a%2Fbuy%2F%3Flink%3Dgalaxy-a71-5g%26offerCID%3DearlyAccess%26utm_source%3Dsamsung%26utm_medium%3Demail%26utm_campaign%3Dholiday_deals_t3_11172020%26marsLinkCategory%3D__MARSTRACKING__%26MKM_RID%3D__BPNUMBER__%26MKM_MID%3D__DELIVERNAME__%26cid%3D__CID____SEGMENTCODE__%26bpid%3D__BPNUMBER__&utm_source=samsung&utm_medium=email&utm_campaign=holiday_deals_t3_11172020&marsLinkCategory=__MARSTRACKING__&MKM_RID=__BPNUMBER__&MKM_MID=__DELIVERNAME__&cid=__CID____SEGMENTCODE__&bpid=__BPNUMBER__&apn=com.samsung.ecomm&al=samsungestore%3A%2F%2Fopenwebview%23url%3Dhttps%3A%2F%2Fwww.samsung.com%2Fus%2Fbuy%2Fsmartphones%2Fgalaxy-a50%2Findex.html%3Flink%3Dgalaxy-a71-5g%26offerCID%3DearlyAccess%26segmentName%3DholidayReserve%23utm_source%3Dsamsung%23utm_medium%3Demail%23utm_campaign%3Dholiday_deals_t3_11172020%23marsLinkCategory%3D__MARSTRACKING__%23MKM_RID%3D__BPNUMBER__%23MKM_MID%3D__DELIVERNAME__%23cid%3D__CID____SEGMENTCODE__%23bpid%3D__BPNUMBER__&afl=https%3A%2F%2Fwww.samsung.com%2Fus%2Fmobile%2Fphones%2Fgalaxy-a%2Fbuy%2F%3Flink%3Dgalaxy-a71-5g%26offerCID%3DearlyAccess%26utm_source%3Dsamsung%26utm_medium%3Demail%26utm_campaign%3Dholiday_deals_t3_11172020%26marsLinkCategory%3D__MARSTRACKING__%26MKM_RID%3D__BPNUMBER__%26MKM_MID%3D__DELIVERNAME__%26cid%3D__CID____SEGMENTCODE__%26bpid%3D__BPNUMBER__&efr=1 | CD5: =DDOfferCopy!L7 -> NULL | ... CF5: =DDOfferCopy!N7 -> NULL | CG5: GIFT GUIDE | CH5: =MiscBanners!$H$4 -> Give-wonder-500xV.jpg | CI5: =MiscBanners!$I$4 -> The gift that keeps on giving | CJ5: =MiscBanners!$J$4 -> NULL | CK5: =MiscBanners!$K$4 -> Discover even more exclusive offers on your favorite products and unlock the power of smart and savvy gifting. | CL5: =MiscBanners!$L$4 -> Shop now | CM5: =MiscBanners!$M$4 -> https://www.samsung.com/us/gift-ideas/ | CN5: =MiscBanners!$N$4 -> https://shopsamsung.page.link?link=https%3A%2F%2Fwww.samsung.com%2Fus%2Fgift-ideas%2F%3FofferCID%3DearlyAccess%26utm_source%3Dsamsung%26utm_medium%3Demail%26utm_campaign%3Dholiday_deals_t3_11172020%26marsLinkCategory%3D__MARSTRACKING__%26MKM_RID%3D__BPNUMBER__%26MKM_MID%3D__DELIVERNAME__%26cid%3D__CID____SEGMENTCODE__%26bpid%3D__BPNUMBER__%26iosparam%3Dsamsungestore%25253A%25252F%25252Fopenwebview%252523url%25253Dhttps%25253A%25252F%25252Fwww.samsung.com%25252Fus%25252Fapp%25252Fgift-ideas%25252F%25253FofferCID%25253DearlyAccess%252526segmentName%25253DholidayReserve%252523utm_source%25253Dsamsung%252523utm_medium%25253Demail%252523utm_campaign%25253Dholiday_deals_t3_11172020%252523marsLinkCategory%25253D__MARSTRACKING__%252523MKM_RID%25253D__BPNUMBER__%252523MKM_MID%25253D__DELIVERNAME__%252523cid%25253D__CID____SEGMENTCODE__%252523bpid%25253D__BPNUMBER__&utm_source=samsung&utm_medium=email&utm_campaign=holiday_deals_t3_11172020&marsLinkCategory=__MARSTRACKING__&MKM_RID=__BPNUMBER__&MKM_MID=__DELIVERNAME__&cid=__CID____SEGMENTCODE__&bpid=__BPNUMBER__&apn=com.samsung.ecomm&al=samsungestore%3A%2F%2Fopenwebview%23url%3Dhttps%3A%2F%2Fwww.samsung.com%2Fus%2Fapp%2Fgift-ideas%2F%3FofferCID%3DearlyAccess%26segmentName%3DholidayReserve%23utm_source%3Dsamsung%23utm_medium%3Demail%23utm_campaign%3Dholiday_deals_t3_11172020%23marsLinkCategory%3D__MARSTRACKING__%23MKM_RID%3D__BPNUMBER__%23MKM_MID%3D__DELIVERNAME__%23cid%3D__CID____SEGMENTCODE__%23bpid%3D__BPNUMBER__&afl=https%3A%2F%2Fwww.samsung.com%2Fus%2Fgift-ideas%2F%3FofferCID%3DearlyAccess%26utm_source%3Dsamsung%26utm_medium%3Demail%26utm_campaign%3Dholiday_deals_t3_11172020%26marsLinkCategory%3D__MARSTRACKING__%26MKM_RID%3D__BPNUMBER__%26MKM_MID%3D__DELIVERNAME__%26cid%3D__CID____SEGMENTCODE__%26bpid%3D__BPNUMBER__&isi=1274679179&ibi=com.samsung.ShopSamsung&ius=samsungestore&ifl=https%3A%2F%2Fwww.samsung.com%2Fus%2Fgift-ideas%2F%3FofferCID%3DearlyAccess%26utm_source%3Dsamsung%26utm_medium%3Demail%26utm_campaign%3Dholiday_deals_t3_11172020%26marsLinkCategory%3D__MARSTRACKING__%26MKM_RID%3D__BPNUMBER__%26MKM_MID%3D__DELIVERNAME__%26cid%3D__CID____SEGMENTCODE__%26bpid%3D__BPNUMBER__&efr=1 | CO5: =MiscBanners!$O$4 -> NULL | CP5: =MiscBanners!$P$4 -> NULL | CQ5: =MiscBanners!$Q$4 -> NULL | CR5: FOOTER | DC5: TC 1 | DD5: NULL | DE5: NULL | DF5: NULL | DG5: ᶿFor a limited time only, on Samsung.com/Shop Samsung App, pre-order or purchase a new qualifying Galaxy device (“Qualifying Purchase”), send in your qualifying trade-in device to Samsung through the Samsung Trade-In Program, and if Samsung determines your trade-in device meets all eligibility requirements, you will receive a trade-in credit specific to your qualifying trade-in device to apply toward your Qualifying Purchase. Device models that currently qualify for trade-in and trade-in credit amounts associated with those models are available on Samsung.com and the Shop Samsung App; eligible models and amounts may change at Samsung’s sole discretion. To be eligible for trade-in, your qualifying device must meet all Trade-In Program eligibility requirements, which include, but are not limited to, that the device powers on, holds a charge, and does not power off unexpectedly; has a functioning display; has no breaks or cracks in the screen (unless a cracked screen offer applies); has no breaks or cracks in the case; has no liquid damage (whether visible or not); has no other defects that go beyond normal wear and tear; is not on a black list; has a verified FCC ID; has been reset to factory settings; has all personal information removed; has all software locks disabled; and is owned by you (leased devices are not eligible). Anticipated trade-in value will be applied as a credit at time of purchase, but, if you do not send in your trade-in device within 15 days of receipt of your Qualifying Purchase, you will be charged back for the trade-in credit applied to your purchase, or if you send in your trade-in device within 15 days of receipt of your Qualifying Purchase but Samsung determines your device does not meet all eligibility requirements, you will be charged back for the trade-in credit applied to your purchase minus $25. Participation in this program does not excuse you from contracts with your carrier or retailer (or any related payments or fees) for the device that was traded in. Limit 1 trade-in per Qualifying Purchase. Samsung reserves the right to modify or discontinue this offer at any time. The Trade-In Program cannot be combined with any other Samsung, carrier or retailer promotions, discounts, or offers unless specifically provided for in the terms and conditions of such offers. Additional terms, including terms that govern the resolution of disputes, apply. Click here to learn more. | DH5: NULL | DI5: https://www.samsung.com/us/trade-in/terms-and-conditions/ | DJ5: 0 | DK5: NULL | DL5: NULL | DM5: NULL | DN5: TC2 | DO5: NULL | DP5: NULL | DQ5: NULL | DR5: ⊕0% APR for 24, 36, 40 or 48 Months with Equal Payments: Available on purchases of select products charged to a Samsung Financing account. Minimum purchase: $50. 0% APR from date of eligible purchase until paid in full. Estimated monthly payment equals the eligible purchase amount multiplied by a repayment factor and rounded to the nearest penny (repayment factors: .04167 for 24 month, .02778 for 36 month, .02500 for 40 month, .02083 for 48 month). Last payment may vary due to rounding. Total amount of payments will not exceed eligible purchase amount. Other transactions and fees affect overall minimum payment amount. Advertised payment amount is an estimate and may change once taxes, delivery or other charges are added. Limited time offer. Regular account terms apply to non-promo purchases. Minimum interest charge: $1. Standard Purchase APR: 29.99%. Prior purchases excluded. Account must be in good standing. Subject to credit approval. Samsung Financing account issued by TD Bank, N.A. | DS5: NULL | DT5: 0 | DU5: 0 | DV5: NULL | DW5: NULL | DX5: NULL | DY5: TC3 | DZ5: NULL | EA5: NULL | EB5: NULL | EC5: §18+ & 50 US/DC only. By 11/29/2020 11:59 PM EST, purchase a qualifying device on device installment plan, 2-year contract plan, lease or outright purchase at full retail price (“Qualifying Purchase”), & receive a Samsung Credit of $100 (“Gift”) instant credit from Samsung for use towards an eligible purchase including select wearables, tablets, PC’s and accessories when you purchase qualifying smartphone (“Qualifying Purchase”) before 01/15/21 at 11:59 PM EST. You must make a Qualifying Purchase on Samsung.com or the Shop Samsung App to receive an instant credit which may be applied instantly or deferred to a future eligible purchase. Gift valid for use on eligible purchases from 11/10/20- 01/15/21 or while supplies last, and is a one-time use certificate; when first used, any value not used is lost. Gift is non-transferrable and limited to 1 instant credit per registered customer. Samsung Credits are valid only at www.Samsung.com or in the App for use towards an eligible purchase. Void where prohibited or restricted by law. Additional restrictions apply. Offer subject to additional terms here. Samsung reserves the right to modify or discontinue offer at any time by posting notice on the app or website | ED5: NULL | EE5: https://www.samsung.com/us/ | EF5: 0 | EG5: NULL | EH5: NULL | EI5: NULL | EJ5: TC4 | EK5: NULL | EL5: NULL | EM5: NULL | EN5: †18+ & 50 US/DC only. By 11/29/2020 11:59 PM EST, purchase a qualifying device on device installment plan, 2-year contract plan, lease or outright purchase at full retail price (“Qualifying Purchase”), & receive a Samsung Credit of $30 (“Gift”) instant credit from Samsung for use towards an eligible purchase including select wearables, tablets, PC’s and accessories when you purchase qualifying smartphone (“Qualifying Purchase”) before 01/15/21 at 11:59 PM EST. You must make a Qualifying Purchase on Samsung.com or the Shop Samsung App to receive an instant credit which may be applied instantly or deferred to a future eligible purchase. Gift valid for use on eligible purchases from 11/10/20- 01/15/21 or while supplies last, and is a one-time use certificate; when first used, any value not used is lost. Gift is non-transferrable and limited to 1 instant credit per registered customer. Samsung Credits are valid only at www.Samsung.com or in the App for use towards an eligible purchase. Void where prohibited or restricted by law. Additional restrictions apply. Offer subject to additional terms here. Samsung reserves the right to modify or discontinue offer at any time by posting notice on the app or website | EO5: NULL | EP5: https://www.samsung.com/us/ | EQ5: 0 | ER5: NULL | ES5: NULL | ET5: NULL
A6: CC | B6: MB_GALAXY MB_FOLD MB_NOTE MB_MID | C6: X | D6: X | E6: Reserver | G6: Cyber Monday is on. | H6: Act fast to save on showstopping gifts while supplies last. | I6: EPP Banner | J6: NULL | K6: NULL | L6: NULL | M6: NULL | N6: NULL | O6: NULL | P6: NULL | Q6: NULL | R6: NULL | S6: Hero & Countdown Timer Image | T6: ='Dynamic Banners'!$L$4 -> Cyber-monday-1.png | U6: ='Dynamic Banners'!$M$4 -> The clock is ticking away for Cyber Monday | V6: NULL | W6: ='Dynamic Banners'!$N$4 -> Shop amazing offers on showstopping products while supplies last. | X6: NULL | Y6: =[1]MiscBanners!$B$4 -> https://www.samsung.com/us/shop/all-deals/ | Z6: =[1]MiscBanners!$C$4 -> https://shopsamsung.page.link?link=https%3A%2F%2Fwww.samsung.com%2Fus%2Fshop%2Fall-deals%2F%3FofferCID%3DearlyAccess%26utm_source%3Dsamsung%26utm_medium%3Demail%26utm_campaign%3Dholiday_deals_t3_11172020%26marsLinkCategory%3D__MARSTRACKING__%26MKM_RID%3D__BPNUMBER__%26MKM_MID%3D__DELIVERNAME__%26cid%3D__CID____SEGMENTCODE__%26bpid%3D__BPNUMBER__%26iosparam%3Dsamsungestore%25253A%25252F%25252Fgototab%252523tab%25253D4%252523offerCID%25253DearlyAccess%252523utm_source%25253Dsamsung%252523utm_medium%25253Demail%252523utm_campaign%25253Dholiday_deals_t3_11172020%252523marsLinkCategory%25253D__MARSTRACKING__%252523MKM_RID%25253D__BPNUMBER__%252523MKM_MID%25253D__DELIVERNAME__%252523cid%25253D__CID____SEGMENTCODE__%252523bpid%25253D__BPNUMBER__&utm_source=samsung&utm_medium=email&utm_campaign=holiday_deals_t3_11172020&marsLinkCategory=__MARSTRACKING__&MKM_RID=__BPNUMBER__&MKM_MID=__DELIVERNAME__&cid=__CID____SEGMENTCODE__&bpid=__BPNUMBER__&apn=com.samsung.ecomm&al=samsungestore%3A%2F%2Fgototab%23tab%3D4%23offerCID%3DearlyAccess%23utm_source%3Dsamsung%23utm_medium%3Demail%23utm_campaign%3Dholiday_deals_t3_11172020%23marsLinkCategory%3D__MARSTRACKING__%23MKM_RID%3D__BPNUMBER__%23MKM_MID%3D__DELIVERNAME__%23cid%3D__CID____SEGMENTCODE__%23bpid%3D__BPNUMBER__&afl=https%3A%2F%2Fwww.samsung.com%2Fus%2Fshop%2Fall-deals%2F%3FofferCID%3DearlyAccess%26utm_source%3Dsamsung%26utm_medium%3Demail%26utm_campaign%3Dholiday_deals_t3_11172020%26marsLinkCategory%3D__MARSTRACKING__%26MKM_RID%3D__BPNUMBER__%26MKM_MID%3D__DELIVERNAME__%26cid%3D__CID____SEGMENTCODE__%26bpid%3D__BPNUMBER__&isi=1274679179&ibi=com.samsung.ShopSamsung&ius=samsungestore&ifl=https%3A%2F%2Fwww.samsung.com%2Fus%2Fshop%2Fall-deals%2F%3FofferCID%3DearlyAccess%26utm_source%3Dsamsung%26utm_medium%3Demail%26utm_campaign%3Dholiday_deals_t3_11172020%26marsLinkCategory%3D__MARSTRACKING__%26MKM_RID%3D__BPNUMBER__%26MKM_MID%3D__DELIVERNAME__%26cid%3D__CID____SEGMENTCODE__%26bpid%3D__BPNUMBER__&efr=1 | AA6: NULL | AB6: NULL | AC6: NULL | AD6: Hero & Countdown Timer Copy | AE6: NULL | AF6: NULL | AG6: While supplies last. | AH6: Today is the day to shop some of our greatest offers of the year. Plus, enjoy $30 or more instant credit§†, in addition to your exclusive $20 instant credit, with any smartphone purchase.‡ | AI6: NULL | AJ6: =[1]MiscBanners!$B$4 -> https://www.samsung.com/us/shop/all-deals/ | AK6: =[1]MiscBanners!$C$4 -> https://shopsamsung.page.link?link=https%3A%2F%2Fwww.samsung.com%2Fus%2Fshop%2Fall-deals%2F%3FofferCID%3DearlyAccess%26utm_source%3Dsamsung%26utm_medium%3Demail%26utm_campaign%3Dholiday_deals_t3_11172020%26marsLinkCategory%3D__MARSTRACKING__%26MKM_RID%3D__BPNUMBER__%26MKM_MID%3D__DELIVERNAME__%26cid%3D__CID____SEGMENTCODE__%26bpid%3D__BPNUMBER__%26iosparam%3Dsamsungestore%25253A%25252F%25252Fgototab%252523tab%25253D4%252523offerCID%25253DearlyAccess%252523utm_source%25253Dsamsung%252523utm_medium%25253Demail%252523utm_campaign%25253Dholiday_deals_t3_11172020%252523marsLinkCategory%25253D__MARSTRACKING__%252523MKM_RID%25253D__BPNUMBER__%252523MKM_MID%25253D__DELIVERNAME__%252523cid%25253D__CID____SEGMENTCODE__%252523bpid%25253D__BPNUMBER__&utm_source=samsung&utm_medium=email&utm_campaign=holiday_deals_t3_11172020&marsLinkCategory=__MARSTRACKING__&MKM_RID=__BPNUMBER__&MKM_MID=__DELIVERNAME__&cid=__CID____SEGMENTCODE__&bpid=__BPNUMBER__&apn=com.samsung.ecomm&al=samsungestore%3A%2F%2Fgototab%23tab%3D4%23offerCID%3DearlyAccess%23utm_source%3Dsamsung%23utm_medium%3Demail%23utm_campaign%3Dholiday_deals_t3_11172020%23marsLinkCategory%3D__MARSTRACKING__%23MKM_RID%3D__BPNUMBER__%23MKM_MID%3D__DELIVERNAME__%23cid%3D__CID____SEGMENTCODE__%23bpid%3D__BPNUMBER__&afl=https%3A%2F%2Fwww.samsung.com%2Fus%2Fshop%2Fall-deals%2F%3FofferCID%3DearlyAccess%26utm_source%3Dsamsung%26utm_medium%3Demail%26utm_campaign%3Dholiday_deals_t3_11172020%26marsLinkCategory%3D__MARSTRACKING__%26MKM_RID%3D__BPNUMBER__%26MKM_MID%3D__DELIVERNAME__%26cid%3D__CID____SEGMENTCODE__%26bpid%3D__BPNUMBER__&isi=1274679179&ibi=com.samsung.ShopSamsung&ius=samsungestore&ifl=https%3A%2F%2Fwww.samsung.com%2Fus%2Fshop%2Fall-deals%2F%3FofferCID%3DearlyAccess%26utm_source%3Dsamsung%26utm_medium%3Demail%26utm_campaign%3Dholiday_deals_t3_11172020%26marsLinkCategory%3D__MARSTRACKING__%26MKM_RID%3D__BPNUMBER__%26MKM_MID%3D__DELIVERNAME__%26cid%3D__CID____SEGMENTCODE__%26bpid%3D__BPNUMBER__&efr=1 | AL6: NULL | AM6: NULL | AN6: NULL | AO6: CC MOBILE RESERVER | AP6: =CCModuleCopy!$B$3 -> IM_HeadImage_Shop_Phones_500xV.jpg | AQ6: =CCModuleCopy!$C$3 -> Save up to $1000 instantly on the latest and greatest Galaxy smartphones | AR6: =CCModuleCopy!$D$3 -> NULL | AS6: =CCModuleCopy!$E$3 -> Whether you're here to improve the way you work or power up the way you play, shop some of our best offers of the year on Galaxy Note20 5G, S20 FE 5G, Z Fold2 5G and select A series devices. Plus, get $50 or more instant credit toward accessories with any smartphone purchase to complete your Galaxy Ecosystem.‡† | AT6: =CCModuleCopy!$F$3 -> Shop all | AU6: =CCModuleCopy!$G$3 -> https://www.samsung.com/us/shop/all-deals/cell-phone-deals/ | AV6: =CCModuleCopy!$H$3 -> https://shopsamsung.page.link?link=https%3A%2F%2Fwww.samsung.com%2Fus%2Fshop%2Fall-deals%2Fcell-phone-deals%2F%3FofferCID%3DearlyAccess%26utm_source%3Dsamsung%26utm_medium%3Demail%26utm_campaign%3Dholiday_deals_t3_11172020%26marsLinkCategory%3D__MARSTRACKING__%26MKM_RID%3D__BPNUMBER__%26MKM_MID%3D__DELIVERNAME__%26cid%3D__CID____SEGMENTCODE__%26bpid%3D__BPNUMBER__&utm_source=samsung&utm_medium=email&utm_campaign=holiday_deals_t3_11172020&marsLinkCategory=__MARSTRACKING__&MKM_RID=__BPNUMBER__&MKM_MID=__DELIVERNAME__&cid=__CID____SEGMENTCODE__&bpid=__BPNUMBER__&apn=com.samsung.ecomm&al=samsungestore%3A%2F%2Fgototab%23tab%3D4%23subtabid%3DMobile_Offers%23offerCID%3DearlyAccess%23segmentName%3DholidayReserve%23utm_source%3Dsamsung%23utm_medium%3Demail%23utm_campaign%3Dholiday_deals_t3_11172020%23marsLinkCategory%3D__MARSTRACKING__%23MKM_RID%3D__BPNUMBER__%23MKM_MID%3D__DELIVERNAME__%23cid%3D__CID____SEGMENTCODE__%23bpid%3D__BPNUMBER__&afl=https%3A%2F%2Fwww.samsung.com%2Fus%2Fshop%2Fall-deals%2Fcell-phone-deals%2F%3FofferCID%3DearlyAccess%26utm_source%3Dsamsung%26utm_medium%3Demail%26utm_campaign%3Dholiday_deals_t3_11172020%26marsLinkCategory%3D__MARSTRACKING__%26MKM_RID%3D__BPNUMBER__%26MKM_MID%3D__DELIVERNAME__%26cid%3D__CID____SEGMENTCODE__%26bpid%3D__BPNUMBER__&efr=1 | AW6: =CCModuleCopy!$I$3 -> NULL | AX6: =CCModuleCopy!$J$3 -> NULL | AY6: =CCModuleCopy!$K$3 -> NULL | AZ6: CC TV & ACCESSORIES | BA6: =CCModuleCopy!$B$7 -> HE_HeadImage_Shop_TVs_500xV.jpg | BB6: =CCModuleCopy!$C$7 -> Get up to $3000 off select 8K, 4K and Lifestyle TVs | BC6: =CCModuleCopy!$D$7 -> NULL | BD6: =CCModuleCopy!$E$7 -> Discover the mind-blowing, true-to-live resolution of QLED technology and create your ultimate home theater today. Save up to $3000 on 8K TVs, up to $1800 on select 4K TVs, up to $1300 on Lifestyle TVs and up to $400 on select soundbars and more. Plus, buy and try select Lifestyle TVs, soundbars and The Premiere Projector with our new 100-day, risk-free trial. | BE6: =CCModuleCopy!$F$7 -> Shop all | BF6: =CCModuleCopy!$G$7 -> https://www.samsung.com/us/shop/all-deals/tv-and-home-theater-deals/ | BG6: =CCModuleCopy!$H$7 -> https://shopsamsung.page.link?link=https%3A%2F%2Fwww.samsung.com%2Fus%2Fshop%2Fall-deals%2Ftv-and-home-theater-deals%2F%3FofferCID%3DearlyAccess%26utm_source%3Dsamsung%26utm_medium%3Demail%26utm_campaign%3Dholiday_deals_t3_11172020%26marsLinkCategory%3D__MARSTRACKING__%26MKM_RID%3D__BPNUMBER__%26MKM_MID%3D__DELIVERNAME__%26cid%3D__CID____SEGMENTCODE__%26bpid%3D__BPNUMBER__%26iosparam%3Dsamsungestore%25253A%25252F%25252Fgototab%252523tab%25253D4%252523subtabid%25253DTV_Home_Theater_Offers%252523offerCID%25253DearlyAccess%252523segmentName%25253DholidayReserve%252523utm_source%25253Dsamsung%252523utm_medium%25253Demail%252523utm_campaign%25253Dholiday_deals_t3_11172020%252523marsLinkCategory%25253D__MARSTRACKING__%252523MKM_RID%25253D__BPNUMBER__%252523MKM_MID%25253D__DELIVERNAME__%252523cid%25253D__CID____SEGMENTCODE__%252523bpid%25253D__BPNUMBER__&utm_source=samsung&utm_medium=email&utm_campaign=holiday_deals_t3_11172020&marsLinkCategory=__MARSTRACKING__&MKM_RID=__BPNUMBER__&MKM_MID=__DELIVERNAME__&cid=__CID____SEGMENTCODE__&bpid=__BPNUMBER__&apn=com.samsung.ecomm&al=samsungestore%3A%2F%2Fgototab%23tab%3D4%23subtabid%3DTV_Home_Theater_Offers%23offerCID%3DearlyAccess%23segmentName%3DholidayReserve%23utm_source%3Dsamsung%23utm_medium%3Demail%23utm_campaign%3Dholiday_deals_t3_11172020%23marsLinkCategory%3D__MARSTRACKING__%23MKM_RID%3D__BPNUMBER__%23MKM_MID%3D__DELIVERNAME__%23cid%3D__CID____SEGMENTCODE__%23bpid%3D__BPNUMBER__&afl=https%3A%2F%2Fwww.samsung.com%2Fus%2Fshop%2Fall-deals%2Ftv-and-home-theater-deals%2F%3FofferCID%3DearlyAccess%26utm_source%3Dsamsung%26utm_medium%3Demail%26utm_campaign%3Dholiday_deals_t3_11172020%26marsLinkCategory%3D__MARSTRACKING__%26MKM_RID%3D__BPNUMBER__%26MKM_MID%3D__DELIVERNAME__%26cid%3D__CID____SEGMENTCODE__%26bpid%3D__BPNUMBER__&isi=1274679179&ibi=com.samsung.ShopSamsung&ius=samsungestore&ifl=https%3A%2F%2Fwww.samsung.com%2Fus%2Fshop%2Fall-deals%2Ftv-and-home-theater-deals%2F%3FofferCID%3DearlyAccess%26utm_source%3Dsamsung%26utm_medium%3Demail%26utm_campaign%3Dholiday_deals_t3_11172020%26marsLinkCategory%3D__MARSTRACKING__%26MKM_RID%3D__BPNUMBER__%26MKM_MID%3D__DELIVERNAME__%26cid%3D__CID____SEGMENTCODE__%26bpid%3D__BPNUMBER__&efr=1 | BH6: =CCModuleCopy!$I$7 -> NULL | BI6: =CCModuleCopy!$J$7 -> NULL | BJ6: =CCModuleCopy!$K$7 -> NULL | BK6: CC TABLET | BL6: =CCModuleCopy!$B$15 -> Tablet-HeadImage-500xV.jpg | BM6: =CCModuleCopy!$C$15 -> Save up to $150 on select tablets | BN6: =CCModuleCopy!$D$15 -> NULL | BO6: =CCModuleCopy!$E$15 -> Empower how you create, learn, game and more with our powerful line of tablets. Shop offers on must-have products from the new Galaxy Tab S7+ to the Galaxy Tab S6 Lite. | BP6: =CCModuleCopy!$F$15 -> Shop all | BQ6: =CCModuleCopy!$G$15 -> https://www.samsung.com/us/shop/all-deals/tablets-laptops-computers-deals/ | BR6: =CCModuleCopy!$H$15 -> https://shopsamsung.page.link?link=https%3A%2F%2Fwww.samsung.com%2Fus%2Fshop%2Fall-deals%2Ftablets-laptops-computers-deals%2F%3FofferCID%3DearlyAccess%26utm_source%3Dsamsung%26utm_medium%3Demail%26utm_campaign%3Dholiday_deals_rev_11182020%26marsLinkCategory%3D__MARSTRACKING__%26MKM_RID%3D__BPNUMBER__%26MKM_MID%3D__DELIVERNAME__%26cid%3D__CID____SEGMENTCODE__%26bpid%3D__BPNUMBER__%26iosparam%3Dsamsungestore%25253A%25252F%25252Fgototab%252523tab%25253D4%252523subtabid%25253DTablets%252526Computing_Offers%252523offerCID%25253DearlyAccess%252523utm_source%25253Dsamsung%252523utm_medium%25253Demail%252523utm_campaign%25253Dholiday_deals_rev_11182020%252523marsLinkCategory%25253D__MARSTRACKING__%252523MKM_RID%25253D__BPNUMBER__%252523MKM_MID%25253D__DELIVERNAME__%252523cid%25253D__CID____SEGMENTCODE__%252523bpid%25253D__BPNUMBER__&utm_source=samsung&utm_medium=email&utm_campaign=holiday_deals_rev_11182020&marsLinkCategory=__MARSTRACKING__&MKM_RID=__BPNUMBER__&MKM_MID=__DELIVERNAME__&cid=__CID____SEGMENTCODE__&bpid=__BPNUMBER__&apn=com.samsung.ecomm&al=samsungestore%3A%2F%2Fgototab%23tab%3D4%23subtabid%3DTablets%26Computing_Offers%23offerCID%3DearlyAccess%23utm_source%3Dsamsung%23utm_medium%3Demail%23utm_campaign%3Dholiday_deals_rev_11182020%23marsLinkCategory%3D__MARSTRACKING__%23MKM_RID%3D__BPNUMBER__%23MKM_MID%3D__DELIVERNAME__%23cid%3D__CID____SEGMENTCODE__%23bpid%3D__BPNUMBER__&afl=https%3A%2F%2Fwww.samsung.com%2Fus%2Fshop%2Fall-deals%2Ftablets-laptops-computers-deals%2F%3FofferCID%3DearlyAccess%26utm_source%3Dsamsung%26utm_medium%3Demail%26utm_campaign%3Dholiday_deals_rev_11182020%26marsLinkCategory%3D__MARSTRACKING__%26MKM_RID%3D__BPNUMBER__%26MKM_MID%3D__DELIVERNAME__%26cid%3D__CID____SEGMENTCODE__%26bpid%3D__BPNUMBER__&isi=1274679179&ibi=com.samsung.ShopSamsung&ius=samsungestore&ifl=https%3A%2F%2Fwww.samsung.com%2Fus%2Fshop%2Fall-deals%2Ftablets-laptops-computers-deals%2F%3FofferCID%3DearlyAccess%26utm_source%3Dsamsung%26utm_medium%3Demail%26utm_campaign%3Dholiday_deals_rev_11182020%26marsLinkCategory%3D__MARSTRACKING__%26MKM_RID%3D__BPNUMBER__%26MKM_MID%3D__DELIVERNAME__%26cid%3D__CID____SEGMENTCODE__%26bpid%3D__BPNUMBER__&efr=1 | BS6: =CCModuleCopy!$I$15 -> NULL | BT6: =CCModuleCopy!$J$15 -> NULL | BU6: =CCModuleCopy!$K$15 -> NULL | BV6: CC WEAR | BW6: =CCModuleCopy!$B$11 -> ME_HeadImage_Wearables_500xV.jpg | BX6: =CCModuleCopy!$C$11 -> Get up to $100 off select watches and earbuds | BY6: =CCModuleCopy!$D$11 -> NULL | BZ6: =CCModuleCopy!$E$11 -> Treat yourself (or someone special) to Galaxy Watch3 Titanium, Watch3, Buds+ and more, suited for every lifestyle and every holiday shopping budget. Plus, now you can flex your fashion muscles with the new Samsung Design Studio. Create a Galaxy Watch as unique as you, today. | CA6: =CCModuleCopy!$F$11 -> Shop all | CB6: =CCModuleCopy!$G$11 -> https://www.samsung.com/us/shop/all-deals/watches-audio-accessories-deals/ | CC6: =CCModuleCopy!$H$11 -> https://shopsamsung.page.link?link=https%3A%2F%2Fwww.samsung.com%2Fus%2Fshop%2Fall-deals%2Ftablets-wearables-cell-phone-accessories-deals%2F%3FofferCID%3DearlyAccess%26utm_source%3Dsamsung%26utm_medium%3Demail%26utm_campaign%3Dholiday_deals_t3_11172020%26marsLinkCategory%3D__MARSTRACKING__%26MKM_RID%3D__BPNUMBER__%26MKM_MID%3D__DELIVERNAME__%26cid%3D__CID____SEGMENTCODE__%26bpid%3D__BPNUMBER__&utm_source=samsung&utm_medium=email&utm_campaign=holiday_deals_t3_11172020&marsLinkCategory=__MARSTRACKING__&MKM_RID=__BPNUMBER__&MKM_MID=__DELIVERNAME__&cid=__CID____SEGMENTCODE__&bpid=__BPNUMBER__&apn=com.samsung.ecomm&al=samsungestore%3A%2F%2Fgototab%23tab%3D4%23subtabid%3DTablets_Wearables_Offers%23offerCID%3DearlyAccess%23utm_source%3Dsamsung%23utm_medium%3Demail%23utm_campaign%3Dholiday_deals_t3_11172020%23marsLinkCategory%3D__MARSTRACKING__%23MKM_RID%3D__BPNUMBER__%23MKM_MID%3D__DELIVERNAME__%23cid%3D__CID____SEGMENTCODE__%23bpid%3D__BPNUMBER__&afl=https%3A%2F%2Fwww.samsung.com%2Fus%2Fshop%2Fall-deals%2Ftablets-wearables-cell-phone-accessories-deals%2F%3FofferCID%3DearlyAccess%26utm_source%3Dsamsung%26utm_medium%3Demail%26utm_campaign%3Dholiday_deals_t3_11172020%26marsLinkCategory%3D__MARSTRACKING__%26MKM_RID%3D__BPNUMBER__%26MKM_MID%3D__DELIVERNAME__%26cid%3D__CID____SEGMENTCODE__%26bpid%3D__BPNUMBER__&efr=1 | CD6: =CCModuleCopy!$I$11 -> NULL | CE6: =CCModuleCopy!$J$11 -> NULL | CF6: =CCModuleCopy!$K$11 -> NULL | CG6: CC COMPUTER | CH6: =CCModuleCopy!$B$13 -> CE_HeadImage_Computing_500xV.jpg | CI6: =CCModuleCopy!$C$13 -> Get up to 60% off memory cards, SSD, monitors and more | CJ6: =CCModuleCopy!$D$13 -> NULL | CK6: =CCModuleCopy!$E$13 -> Expand the way you play, store and create and get up to 30% off monitors, up to 60% off memory cards, up to 35% off SSD and more. Work and game smarter, not harder with these must-have computing offers. | CL6: =CCModuleCopy!$F$13 -> Shop all | CM6: =CCModuleCopy!$G$13 -> https://www.samsung.com/us/shop/all-deals/tablets-laptops-computers-deals/ | CN6: =CCModuleCopy!$H$13 -> https://shopsamsung.page.link?link=https%3A%2F%2Fwww.samsung.com%2Fus%2Fshop%2Fall-deals%2Flaptop-and-computer-deals%2F%3FofferCID%3DearlyAccess%26utm_source%3Dsamsung%26utm_medium%3Demail%26utm_campaign%3Dholiday_deals_t3_11172020%26marsLinkCategory%3D__MARSTRACKING__%26MKM_RID%3D__BPNUMBER__%26MKM_MID%3D__DELIVERNAME__%26cid%3D__CID____SEGMENTCODE__%26bpid%3D__BPNUMBER__%26iosparam%3Dsamsungestore%25253A%25252F%25252Fgototab%252523tab%25253D4%252523subtabid%25253DComputing_Offers%252523offerCID%25253DearlyAccess%252523segmentName%25253DholidayReserve%252523utm_source%25253Dsamsung%252523utm_medium%25253Demail%252523utm_campaign%25253Dholiday_deals_t3_11172020%252523marsLinkCategory%25253D__MARSTRACKING__%252523MKM_RID%25253D__BPNUMBER__%252523MKM_MID%25253D__DELIVERNAME__%252523cid%25253D__CID____SEGMENTCODE__%252523bpid%25253D__BPNUMBER__&utm_source=samsung&utm_medium=email&utm_campaign=holiday_deals_t3_11172020&marsLinkCategory=__MARSTRACKING__&MKM_RID=__BPNUMBER__&MKM_MID=__DELIVERNAME__&cid=__CID____SEGMENTCODE__&bpid=__BPNUMBER__&apn=com.samsung.ecomm&al=samsungestore%3A%2F%2Fgototab%23tab%3D4%23subtabid%3DComputing_Offers%23offerCID%3DearlyAccess%23segmentName%3DholidayReserve%23utm_source%3Dsamsung%23utm_medium%3Demail%23utm_campaign%3Dholiday_deals_t3_11172020%23marsLinkCategory%3D__MARSTRACKING__%23MKM_RID%3D__BPNUMBER__%23MKM_MID%3D__DELIVERNAME__%23cid%3D__CID____SEGMENTCODE__%23bpid%3D__BPNUMBER__&afl=https%3A%2F%2Fwww.samsung.com%2Fus%2Fshop%2Fall-deals%2Flaptop-and-computer-deals%2F%3FofferCID%3DearlyAccess%26utm_source%3Dsamsung%26utm_medium%3Demail%26utm_campaign%3Dholiday_deals_t3_11172020%26marsLinkCategory%3D__MARSTRACKING__%26MKM_RID%3D__BPNUMBER__%26MKM_MID%3D__DELIVERNAME__%26cid%3D__CID____SEGMENTCODE__%26bpid%3D__BPNUMBER__&isi=1274679179&ibi=com.samsung.ShopSamsung&ius=samsungestore&ifl=https%3A%2F%2Fwww.samsung.com%2Fus%2Fshop%2Fall-deals%2Flaptop-and-computer-deals%2F%3FofferCID%3DearlyAccess%26utm_source%3Dsamsung%26utm_medium%3Demail%26utm_campaign%3Dholiday_deals_t3_11172020%26marsLinkCategory%3D__MARSTRACKING__%26MKM_RID%3D__BPNUMBER__%26MKM_MID%3D__DELIVERNAME__%26cid%3D__CID____SEGMENTCODE__%26bpid%3D__BPNUMBER__&efr=1 | CO6: =CCModuleCopy!$I$13 -> NULL | CP6: =CCModuleCopy!$J$13 -> NULL | CQ6: =CCModuleCopy!$K$13 -> NULL | CR6: CC HA | CS6: =CCModuleCopy!$B$9 -> HA_HeadImage_Shop_HA_500xV.jpg | CT6: =CCModuleCopy!$C$9 -> Save up to 50% on everything you need to upgrade your home and home care | CU6: =CCModuleCopy!$D$9 -> NULL | CV6: =CCModuleCopy!$E$9 -> Get an additional 10% off when you buy 4 or more eligible kitchen appliances. Save even more with early Black Friday prices for select categories.α Plus, shop our time and cost-saving laundry and floor care products, and buy and try a Jet Stick Cordless Vacuum with our new 100-day, risk-free trial. | CW6: =CCModuleCopy!$F$9 -> Shop all | CX6: =CCModuleCopy!$G$9 -> https://www.samsung.com/us/shop/all-deals/home-appliance-and-smart-home-sales/ | CY6: =CCModuleCopy!$H$9 -> https://shopsamsung.page.link?link=https%3A%2F%2Fwww.samsung.com%2Fus%2Fshop%2Fall-deals%2Fhome-appliance-and-smart-home-sales%2F%3FofferCID%3DearlyAccess%26utm_source%3Dsamsung%26utm_medium%3Demail%26utm_campaign%3Dholiday_deals_t3_11172020%26marsLinkCategory%3D__MARSTRACKING__%26MKM_RID%3D__BPNUMBER__%26MKM_MID%3D__DELIVERNAME__%26cid%3D__CID____SEGMENTCODE__%26bpid%3D__BPNUMBER__%26iosparam%3Dsamsungestore%25253A%25252F%25252Fgototab%252523tab%25253D4%252523subtabid%25253DHome_Appliances_SmartHome_Offers%252523offerCID%25253DearlyAccess%252523segmentName%25253DholidayReserve%252523utm_source%25253Dsamsung%252523utm_medium%25253Demail%252523utm_campaign%25253Dholiday_deals_t3_11172020%252523marsLinkCategory%25253D__MARSTRACKING__%252523MKM_RID%25253D__BPNUMBER__%252523MKM_MID%25253D__DELIVERNAME__%252523cid%25253D__CID____SEGMENTCODE__%252523bpid%25253D__BPNUMBER__&utm_source=samsung&utm_medium=email&utm_campaign=holiday_deals_t3_11172020&marsLinkCategory=__MARSTRACKING__&MKM_RID=__BPNUMBER__&MKM_MID=__DELIVERNAME__&cid=__CID____SEGMENTCODE__&bpid=__BPNUMBER__&apn=com.samsung.ecomm&al=samsungestore%3A%2F%2Fgototab%23tab%3D4%23subtabid%3DHome_Appliances_SmartHome_Offers%23offerCID%3DearlyAccess%23segmentName%3DholidayReserve%23utm_source%3Dsamsung%23utm_medium%3Demail%23utm_campaign%3Dholiday_deals_t3_11172020%23marsLinkCategory%3D__MARSTRACKING__%23MKM_RID%3D__BPNUMBER__%23MKM_MID%3D__DELIVERNAME__%23cid%3D__CID____SEGMENTCODE__%23bpid%3D__BPNUMBER__&afl=https%3A%2F%2Fwww.samsung.com%2Fus%2Fshop%2Fall-deals%2Fhome-appliance-and-smart-home-sales%2F%3FofferCID%3DearlyAccess%26utm_source%3Dsamsung%26utm_medium%3Demail%26utm_campaign%3Dholiday_deals_t3_11172020%26marsLinkCategory%3D__MARSTRACKING__%26MKM_RID%3D__BPNUMBER__%26MKM_MID%3D__DELIVERNAME__%26cid%3D__CID____SEGMENTCODE__%26bpid%3D__BPNUMBER__&isi=1274679179&ibi=com.samsung.ShopSamsung&ius=samsungestore&ifl=https%3A%2F%2Fwww.samsung.com%2Fus%2Fshop%2Fall-deals%2Fhome-appliance-and-smart-home-sales%2F%3FofferCID%3DearlyAccess%26utm_source%3Dsamsung%26utm_medium%3Demail%26utm_campaign%3Dholiday_deals_t3_11172020%26marsLinkCategory%3D__MARSTRACKING__%26MKM_RID%3D__BPNUMBER__%26MKM_MID%3D__DELIVERNAME__%26cid%3D__CID____SEGMENTCODE__%26bpid%3D__BPNUMBER__&efr=1 | CZ6: =CCModuleCopy!$I$9 -> NULL | DA6: =CCModuleCopy!$J$9 -> NULL | DB6: =CCModuleCopy!$K$9 -> NULL | DC6: GIFT GUIDE | DD6: =MiscBanners!$H$4 -> Give-wonder-500xV.jpg | DE6: =MiscBanners!$I$4 -> The gift that keeps on giving | DF6: =MiscBanners!$J$4 -> NULL | DG6: =MiscBanners!$K$4 -> Discover even more exclusive offers on your favorite products and unlock the power of smart and savvy gifting. | DH6: =MiscBanners!$L$4 -> Shop now | DI6: =MiscBanners!$M$4 -> https://www.samsung.com/us/gift-ideas/ | DJ6: =MiscBanners!$N$4 -> https://shopsamsung.page.link?link=https%3A%2F%2Fwww.samsung.com%2Fus%2Fgift-ideas%2F%3FofferCID%3DearlyAccess%26utm_source%3Dsamsung%26utm_medium%3Demail%26utm_campaign%3Dholiday_deals_t3_11172020%26marsLinkCategory%3D__MARSTRACKING__%26MKM_RID%3D__BPNUMBER__%26MKM_MID%3D__DELIVERNAME__%26cid%3D__CID____SEGMENTCODE__%26bpid%3D__BPNUMBER__%26iosparam%3Dsamsungestore%25253A%25252F%25252Fopenwebview%252523url%25253Dhttps%25253A%25252F%25252Fwww.samsung.com%25252Fus%25252Fapp%25252Fgift-ideas%25252F%25253FofferCID%25253DearlyAccess%252526segmentName%25253DholidayReserve%252523utm_source%25253Dsamsung%252523utm_medium%25253Demail%252523utm_campaign%25253Dholiday_deals_t3_11172020%252523marsLinkCategory%25253D__MARSTRACKING__%252523MKM_RID%25253D__BPNUMBER__%252523MKM_MID%25253D__DELIVERNAME__%252523cid%25253D__CID____SEGMENTCODE__%252523bpid%25253D__BPNUMBER__&utm_source=samsung&utm_medium=email&utm_campaign=holiday_deals_t3_11172020&marsLinkCategory=__MARSTRACKING__&MKM_RID=__BPNUMBER__&MKM_MID=__DELIVERNAME__&cid=__CID____SEGMENTCODE__&bpid=__BPNUMBER__&apn=com.samsung.ecomm&al=samsungestore%3A%2F%2Fopenwebview%23url%3Dhttps%3A%2F%2Fwww.samsung.com%2Fus%2Fapp%2Fgift-ideas%2F%3FofferCID%3DearlyAccess%26segmentName%3DholidayReserve%23utm_source%3Dsamsung%23utm_medium%3Demail%23utm_campaign%3Dholiday_deals_t3_11172020%23marsLinkCategory%3D__MARSTRACKING__%23MKM_RID%3D__BPNUMBER__%23MKM_MID%3D__DELIVERNAME__%23cid%3D__CID____SEGMENTCODE__%23bpid%3D__BPNUMBER__&afl=https%3A%2F%2Fwww.samsung.com%2Fus%2Fgift-ideas%2F%3FofferCID%3DearlyAccess%26utm_source%3Dsamsung%26utm_medium%3Demail%26utm_campaign%3Dholiday_deals_t3_11172020%26marsLinkCategory%3D__MARSTRACKING__%26MKM_RID%3D__BPNUMBER__%26MKM_MID%3D__DELIVERNAME__%26cid%3D__CID____SEGMENTCODE__%26bpid%3D__BPNUMBER__&isi=1274679179&ibi=com.samsung.ShopSamsung&ius=samsungestore&ifl=https%3A%2F%2Fwww.samsung.com%2Fus%2Fgift-ideas%2F%3FofferCID%3DearlyAccess%26utm_source%3Dsamsung%26utm_medium%3Demail%26utm_campaign%3Dholiday_deals_t3_11172020%26marsLinkCategory%3D__MARSTRACKING__%26MKM_RID%3D__BPNUMBER__%26MKM_MID%3D__DELIVERNAME__%26cid%3D__CID____SEGMENTCODE__%26bpid%3D__BPNUMBER__&efr=1 | DK6: =MiscBanners!$O$4 -> NULL | DL6: =MiscBanners!$P$4 -> NULL | DM6: =MiscBanners!$Q$4 -> NULL | DN6: FOOTER | DY6: TC1 | DZ6: =TC!B4 -> NULL | EA6: =TC!C4 -> NULL | EB6: =TC!D4 -> NULL | EC6: =TC!E4 -> §18+ & 50 US/DC only. By 11/29/2020 11:59 PM EST, purchase a qualifying device on device installment plan, 2-year contract plan, lease or outright purchase at full retail price (“Qualifying Purchase”), & receive a Samsung Credit of $100 (“Gift”) instant credit from Samsung for use towards an eligible purchase including select wearables, tablets, PC’s and accessories when you purchase qualifying smartphone (“Qualifying Purchase”) before 01/15/21 at 11:59 PM EST. You must make a Qualifying Purchase on Samsung.com or the Shop Samsung App to receive an instant credit which may be applied instantly or deferred to a future eligible purchase. Gift valid for use on eligible purchases from 11/10/20- 01/15/21 or while supplies last, and is a one-time use certificate; when first used, any value not used is lost. Gift is non-transferrable and limited to 1 instant credit per registered customer. Samsung Credits are valid only at www.Samsung.com or in the App for use towards an eligible purchase. Void where prohibited or restricted by law. Additional restrictions apply. Offer subject to additional terms here. Samsung reserves the right to modify or discontinue offer at any time by posting notice on the app or website | ED6: =TC!F4 -> NULL | EE6: =TC!G4 -> https://www.samsung.com/us/ | EF6: =TC!H4 -> 0 | EG6: =TC!I4 -> NULL | ... EI6: =TC!K4 -> NULL | EJ6: TC2 | EK6: =TC!B5 -> NULL | EL6: =TC!C5 -> NULL | EM6: =TC!D5 -> NULL | EN6: =TC!E5 -> †18+ & 50 US/DC only. By 11/29/2020 11:59 PM EST, purchase a qualifying device on device installment plan, 2-year contract plan, lease or outright purchase at full retail price (“Qualifying Purchase”), & receive a Samsung Credit of $30 (“Gift”) instant credit from Samsung for use towards an eligible purchase including select wearables, tablets, PC’s and accessories when you purchase qualifying smartphone (“Qualifying Purchase”) before 01/15/21 at 11:59 PM EST. You must make a Qualifying Purchase on Samsung.com or the Shop Samsung App to receive an instant credit which may be applied instantly or deferred to a future eligible purchase. Gift valid for use on eligible purchases from 11/10/20- 01/15/21 or while supplies last, and is a one-time use certificate; when first used, any value not used is lost. Gift is non-transferrable and limited to 1 instant credit per registered customer. Samsung Credits are valid only at www.Samsung.com or in the App for use towards an eligible purchase. Void where prohibited or restricted by law. Additional restrictions apply. Offer subject to additional terms here. Samsung reserves the right to modify or discontinue offer at any time by posting notice on the app or website | EO6: =TC!F5 -> NULL | EP6: =TC!G5 -> https://www.samsung.com/us/ | EQ6: =TC!H5 -> 0 | ER6: =TC!I5 -> NULL | ... ET6: =TC!K5 -> NULL | EU6: TC3 | EV6: =TC!B6 -> NULL | EW6: =TC!C6 -> NULL | EX6: =TC!D6 -> NULL | EY6: =TC!E6 -> ‡18+ & 50 US/DC only. Between 10/26/20 at 12:01 AM EST and 11/18/20 at 11:59 PM EST (“Registration Period”), register for the Samsung Holiday instant credit promotion to receive a $20 instant credit from Samsung for use towards an eligible purchase including select wearables, tablets, PC’s and accessories when you purchase qualifying smartphone (“Qualifying Purchase”) before 01/15/21 at 11:59 PM EST. You must make a Qualifying Purchase on Samsung.com or the Shop Samsung App to receive an instant credit which may be applied instantly or deferred to a future eligible purchase. Gift valid for use on eligible purchases from 11/10/20- 01/15/21 or while supplies last, and is a one-time use certificate; when first used, any value not used is lost. Gift is non-transferrable and limited to 1 instant credit per registered customer. Samsung Credits are valid only at www.Samsung.com or in the App for use towards an eligible purchase. Void where prohibited or restricted by law. Additional restrictions apply. Offer subject to additional terms here. Samsung reserves the right to modify or discontinue offer at any time by posting notice on the app or website. | EZ6: =TC!F6 -> NULL | FA6: =TC!G6 -> https://www.samsung.com/us/ | FB6: =TC!H6 -> 0 | FC6: =TC!I6 -> NULL | ... FE6: =TC!K6 -> NULL | FF6: TC4 | FG6: =TC!B7 -> NULL | FH6: =TC!C7 -> NULL | FI6: =TC!D7 -> NULL | FJ6: =TC!E7 -> αMust be an eligible legal resident of the 50 US/DC & at least 18 years old to participate. Purchase at least 4 eligible Samsung Home Appliance products in the same transaction (Refrigerators, Ranges, Countertop Microwaves, Over-the-Range Microwave Ovens, Dishwashers, Wall Ovens, Cooktops, or Range Hoods) (“a Qualifying Purchase”) between 11/04/20 and 12/02/20 on Samsung.com, and you will receive a 10% instant rebate off of the pre-tax purchase price of your Qualifying Purchase (“Gift”). Purchases must include products from different product categories. If more than 4 eligible products are purchased, the additional products purchased are eligible for the discount as long as the eligibility requirements listed above and below are met. Eligible categories are Refrigerators, Ranges, Countertop Microwaves, Over-the-Range Microwave Ovens, Dishwashers, Wall Ovens, Cooktops, or Range Hoods. Samsung Chef Collection, Washers, Dryers, Pedestals, Vacuums, Air Purifiers, AirDresser, Wine Cooler, and all accessories are not eligible. Quantities limited; offer valid while supplies last. One claim per household. This Offer and instant rebate Gift redemption applies to Samsung.com only. Offer cannot be combined with other Samsung offers, rebates, programs, or promotions unless otherwise stated. | FK6: =TC!F7 -> NULL | FL6: =TC!G7 -> 0 | FM6: =TC!H7 -> 0 | FN6: =TC!I7 -> NULL | ... FP6: =TC!K7 -> NULL
A7: CC | B7: TV_QLED TV_UHD TV_FRAME | C7: X | D7: X | E7: Reserver | G7: Cyber Monday is on. | H7: Act fast to save on showstopping gifts while supplies last. | I7: EPP Banner | J7: NULL | K7: NULL | L7: NULL | M7: NULL | N7: NULL | O7: NULL | P7: NULL | Q7: NULL | R7: NULL | S7: Hero & Countdown Timer Image | T7: ='Dynamic Banners'!$L$4 -> Cyber-monday-1.png | U7: ='Dynamic Banners'!$M$4 -> The clock is ticking away for Cyber Monday | V7: NULL | W7: ='Dynamic Banners'!$N$4 -> Shop amazing offers on showstopping products while supplies last. | X7: NULL | Y7: =[1]MiscBanners!$B$4 -> https://www.samsung.com/us/shop/all-deals/ | Z7: =[1]MiscBanners!$C$4 -> https://shopsamsung.page.link?link=https%3A%2F%2Fwww.samsung.com%2Fus%2Fshop%2Fall-deals%2F%3FofferCID%3DearlyAccess%26utm_source%3Dsamsung%26utm_medium%3Demail%26utm_campaign%3Dholiday_deals_t3_11172020%26marsLinkCategory%3D__MARSTRACKING__%26MKM_RID%3D__BPNUMBER__%26MKM_MID%3D__DELIVERNAME__%26cid%3D__CID____SEGMENTCODE__%26bpid%3D__BPNUMBER__%26iosparam%3Dsamsungestore%25253A%25252F%25252Fgototab%252523tab%25253D4%252523offerCID%25253DearlyAccess%252523utm_source%25253Dsamsung%252523utm_medium%25253Demail%252523utm_campaign%25253Dholiday_deals_t3_11172020%252523marsLinkCategory%25253D__MARSTRACKING__%252523MKM_RID%25253D__BPNUMBER__%252523MKM_MID%25253D__DELIVERNAME__%252523cid%25253D__CID____SEGMENTCODE__%252523bpid%25253D__BPNUMBER__&utm_source=samsung&utm_medium=email&utm_campaign=holiday_deals_t3_11172020&marsLinkCategory=__MARSTRACKING__&MKM_RID=__BPNUMBER__&MKM_MID=__DELIVERNAME__&cid=__CID____SEGMENTCODE__&bpid=__BPNUMBER__&apn=com.samsung.ecomm&al=samsungestore%3A%2F%2Fgototab%23tab%3D4%23offerCID%3DearlyAccess%23utm_source%3Dsamsung%23utm_medium%3Demail%23utm_campaign%3Dholiday_deals_t3_11172020%23marsLinkCategory%3D__MARSTRACKING__%23MKM_RID%3D__BPNUMBER__%23MKM_MID%3D__DELIVERNAME__%23cid%3D__CID____SEGMENTCODE__%23bpid%3D__BPNUMBER__&afl=https%3A%2F%2Fwww.samsung.com%2Fus%2Fshop%2Fall-deals%2F%3FofferCID%3DearlyAccess%26utm_source%3Dsamsung%26utm_medium%3Demail%26utm_campaign%3Dholiday_deals_t3_11172020%26marsLinkCategory%3D__MARSTRACKING__%26MKM_RID%3D__BPNUMBER__%26MKM_MID%3D__DELIVERNAME__%26cid%3D__CID____SEGMENTCODE__%26bpid%3D__BPNUMBER__&isi=1274679179&ibi=com.samsung.ShopSamsung&ius=samsungestore&ifl=https%3A%2F%2Fwww.samsung.com%2Fus%2Fshop%2Fall-deals%2F%3FofferCID%3DearlyAccess%26utm_source%3Dsamsung%26utm_medium%3Demail%26utm_campaign%3Dholiday_deals_t3_11172020%26marsLinkCategory%3D__MARSTRACKING__%26MKM_RID%3D__BPNUMBER__%26MKM_MID%3D__DELIVERNAME__%26cid%3D__CID____SEGMENTCODE__%26bpid%3D__BPNUMBER__&efr=1 | AA7: NULL | AB7: NULL | AC7: NULL | AD7: Hero & Countdown Timer Copy | AE7: NULL | AF7: NULL | AG7: While supplies last. | AH7: Today is your day to shop some of our greatest offers of the year. | AI7: NULL | AJ7: =[1]MiscBanners!$B$4 -> https://www.samsung.com/us/shop/all-deals/ | AK7: =[1]MiscBanners!$C$4 -> https://shopsamsung.page.link?link=https%3A%2F%2Fwww.samsung.com%2Fus%2Fshop%2Fall-deals%2F%3FofferCID%3DearlyAccess%26utm_source%3Dsamsung%26utm_medium%3Demail%26utm_campaign%3Dholiday_deals_t3_11172020%26marsLinkCategory%3D__MARSTRACKING__%26MKM_RID%3D__BPNUMBER__%26MKM_MID%3D__DELIVERNAME__%26cid%3D__CID____SEGMENTCODE__%26bpid%3D__BPNUMBER__%26iosparam%3Dsamsungestore%25253A%25252F%25252Fgototab%252523tab%25253D4%252523offerCID%25253DearlyAccess%252523utm_source%25253Dsamsung%252523utm_medium%25253Demail%252523utm_campaign%25253Dholiday_deals_t3_11172020%252523marsLinkCategory%25253D__MARSTRACKING__%252523MKM_RID%25253D__BPNUMBER__%252523MKM_MID%25253D__DELIVERNAME__%252523cid%25253D__CID____SEGMENTCODE__%252523bpid%25253D__BPNUMBER__&utm_source=samsung&utm_medium=email&utm_campaign=holiday_deals_t3_11172020&marsLinkCategory=__MARSTRACKING__&MKM_RID=__BPNUMBER__&MKM_MID=__DELIVERNAME__&cid=__CID____SEGMENTCODE__&bpid=__BPNUMBER__&apn=com.samsung.ecomm&al=samsungestore%3A%2F%2Fgototab%23tab%3D4%23offerCID%3DearlyAccess%23utm_source%3Dsamsung%23utm_medium%3Demail%23utm_campaign%3Dholiday_deals_t3_11172020%23marsLinkCategory%3D__MARSTRACKING__%23MKM_RID%3D__BPNUMBER__%23MKM_MID%3D__DELIVERNAME__%23cid%3D__CID____SEGMENTCODE__%23bpid%3D__BPNUMBER__&afl=https%3A%2F%2Fwww.samsung.com%2Fus%2Fshop%2Fall-deals%2F%3FofferCID%3DearlyAccess%26utm_source%3Dsamsung%26utm_medium%3Demail%26utm_campaign%3Dholiday_deals_t3_11172020%26marsLinkCategory%3D__MARSTRACKING__%26MKM_RID%3D__BPNUMBER__%26MKM_MID%3D__DELIVERNAME__%26cid%3D__CID____SEGMENTCODE__%26bpid%3D__BPNUMBER__&isi=1274679179&ibi=com.samsung.ShopSamsung&ius=samsungestore&ifl=https%3A%2F%2Fwww.samsung.com%2Fus%2Fshop%2Fall-deals%2F%3FofferCID%3DearlyAccess%26utm_source%3Dsamsung%26utm_medium%3Demail%26utm_campaign%3Dholiday_deals_t3_11172020%26marsLinkCategory%3D__MARSTRACKING__%26MKM_RID%3D__BPNUMBER__%26MKM_MID%3D__DELIVERNAME__%26cid%3D__CID____SEGMENTCODE__%26bpid%3D__BPNUMBER__&efr=1 | AL7: NULL | AM7: NULL | AN7: NULL | AO7: CC TV & ACCESSORIES | AP7: =CCModuleCopy!$B$7 -> HE_HeadImage_Shop_TVs_500xV.jpg | AQ7: =CCModuleCopy!$C$7 -> Get up to $3000 off select 8K, 4K and Lifestyle TVs | AR7: =CCModuleCopy!$D$7 -> NULL | AS7: =CCModuleCopy!$E$7 -> Discover the mind-blowing, true-to-live resolution of QLED technology and create your ultimate home theater today. Save up to $3000 on 8K TVs, up to $1800 on select 4K TVs, up to $1300 on Lifestyle TVs and up to $400 on select soundbars and more. Plus, buy and try select Lifestyle TVs, soundbars and The Premiere Projector with our new 100-day, risk-free trial. | AT7: =CCModuleCopy!$F$7 -> Shop all | AU7: =CCModuleCopy!$G$7 -> https://www.samsung.com/us/shop/all-deals/tv-and-home-theater-deals/ | AV7: =CCModuleCopy!$H$7 -> https://shopsamsung.page.link?link=https%3A%2F%2Fwww.samsung.com%2Fus%2Fshop%2Fall-deals%2Ftv-and-home-theater-deals%2F%3FofferCID%3DearlyAccess%26utm_source%3Dsamsung%26utm_medium%3Demail%26utm_campaign%3Dholiday_deals_t3_11172020%26marsLinkCategory%3D__MARSTRACKING__%26MKM_RID%3D__BPNUMBER__%26MKM_MID%3D__DELIVERNAME__%26cid%3D__CID____SEGMENTCODE__%26bpid%3D__BPNUMBER__%26iosparam%3Dsamsungestore%25253A%25252F%25252Fgototab%252523tab%25253D4%252523subtabid%25253DTV_Home_Theater_Offers%252523offerCID%25253DearlyAccess%252523segmentName%25253DholidayReserve%252523utm_source%25253Dsamsung%252523utm_medium%25253Demail%252523utm_campaign%25253Dholiday_deals_t3_11172020%252523marsLinkCategory%25253D__MARSTRACKING__%252523MKM_RID%25253D__BPNUMBER__%252523MKM_MID%25253D__DELIVERNAME__%252523cid%25253D__CID____SEGMENTCODE__%252523bpid%25253D__BPNUMBER__&utm_source=samsung&utm_medium=email&utm_campaign=holiday_deals_t3_11172020&marsLinkCategory=__MARSTRACKING__&MKM_RID=__BPNUMBER__&MKM_MID=__DELIVERNAME__&cid=__CID____SEGMENTCODE__&bpid=__BPNUMBER__&apn=com.samsung.ecomm&al=samsungestore%3A%2F%2Fgototab%23tab%3D4%23subtabid%3DTV_Home_Theater_Offers%23offerCID%3DearlyAccess%23segmentName%3DholidayReserve%23utm_source%3Dsamsung%23utm_medium%3Demail%23utm_campaign%3Dholiday_deals_t3_11172020%23marsLinkCategory%3D__MARSTRACKING__%23MKM_RID%3D__BPNUMBER__%23MKM_MID%3D__DELIVERNAME__%23cid%3D__CID____SEGMENTCODE__%23bpid%3D__BPNUMBER__&afl=https%3A%2F%2Fwww.samsung.com%2Fus%2Fshop%2Fall-deals%2Ftv-and-home-theater-deals%2F%3FofferCID%3DearlyAccess%26utm_source%3Dsamsung%26utm_medium%3Demail%26utm_campaign%3Dholiday_deals_t3_11172020%26marsLinkCategory%3D__MARSTRACKING__%26MKM_RID%3D__BPNUMBER__%26MKM_MID%3D__DELIVERNAME__%26cid%3D__CID____SEGMENTCODE__%26bpid%3D__BPNUMBER__&isi=1274679179&ibi=com.samsung.ShopSamsung&ius=samsungestore&ifl=https%3A%2F%2Fwww.samsung.com%2Fus%2Fshop%2Fall-deals%2Ftv-and-home-theater-deals%2F%3FofferCID%3DearlyAccess%26utm_source%3Dsamsung%26utm_medium%3Demail%26utm_campaign%3Dholiday_deals_t3_11172020%26marsLinkCategory%3D__MARSTRACKING__%26MKM_RID%3D__BPNUMBER__%26MKM_MID%3D__DELIVERNAME__%26cid%3D__CID____SEGMENTCODE__%26bpid%3D__BPNUMBER__&efr=1 | AW7: =CCModuleCopy!$I$7 -> NULL | AX7: =CCModuleCopy!$J$7 -> NULL | AY7: =CCModuleCopy!$K$7 -> NULL | AZ7: CC MOBILE RESERVER | BA7: =CCModuleCopy!$B$3 -> IM_HeadImage_Shop_Phones_500xV.jpg | BB7: =CCModuleCopy!$C$3 -> Save up to $1000 instantly on the latest and greatest Galaxy smartphones | BC7: =CCModuleCopy!$D$3 -> NULL | BD7: =CCModuleCopy!$E$3 -> Whether you're here to improve the way you work or power up the way you play, shop some of our best offers of the year on Galaxy Note20 5G, S20 FE 5G, Z Fold2 5G and select A series devices. Plus, get $50 or more instant credit toward accessories with any smartphone purchase to complete your Galaxy Ecosystem.‡† | BE7: =CCModuleCopy!$F$3 -> Shop all | BF7: =CCModuleCopy!$G$3 -> https://www.samsung.com/us/shop/all-deals/cell-phone-deals/ | BG7: =CCModuleCopy!$H$3 -> https://shopsamsung.page.link?link=https%3A%2F%2Fwww.samsung.com%2Fus%2Fshop%2Fall-deals%2Fcell-phone-deals%2F%3FofferCID%3DearlyAccess%26utm_source%3Dsamsung%26utm_medium%3Demail%26utm_campaign%3Dholiday_deals_t3_11172020%26marsLinkCategory%3D__MARSTRACKING__%26MKM_RID%3D__BPNUMBER__%26MKM_MID%3D__DELIVERNAME__%26cid%3D__CID____SEGMENTCODE__%26bpid%3D__BPNUMBER__&utm_source=samsung&utm_medium=email&utm_campaign=holiday_deals_t3_11172020&marsLinkCategory=__MARSTRACKING__&MKM_RID=__BPNUMBER__&MKM_MID=__DELIVERNAME__&cid=__CID____SEGMENTCODE__&bpid=__BPNUMBER__&apn=com.samsung.ecomm&al=samsungestore%3A%2F%2Fgototab%23tab%3D4%23subtabid%3DMobile_Offers%23offerCID%3DearlyAccess%23segmentName%3DholidayReserve%23utm_source%3Dsamsung%23utm_medium%3Demail%23utm_campaign%3Dholiday_deals_t3_11172020%23marsLinkCategory%3D__MARSTRACKING__%23MKM_RID%3D__BPNUMBER__%23MKM_MID%3D__DELIVERNAME__%23cid%3D__CID____SEGMENTCODE__%23bpid%3D__BPNUMBER__&afl=https%3A%2F%2Fwww.samsung.com%2Fus%2Fshop%2Fall-deals%2Fcell-phone-deals%2F%3FofferCID%3DearlyAccess%26utm_source%3Dsamsung%26utm_medium%3Demail%26utm_campaign%3Dholiday_deals_t3_11172020%26marsLinkCategory%3D__MARSTRACKING__%26MKM_RID%3D__BPNUMBER__%26MKM_MID%3D__DELIVERNAME__%26cid%3D__CID____SEGMENTCODE__%26bpid%3D__BPNUMBER__&efr=1 | BH7: =CCModuleCopy!$I$3 -> NULL | BI7: =CCModuleCopy!$J$3 -> NULL | BJ7: =CCModuleCopy!$K$3 -> NULL | BK7: CC TABLET | BL7: 0 | BM7: Save up to $150 on select tablets | BN7: NULL | BO7: Empower how you create, work, learn, game and more with our powerful line of tablets. Shop our offers on great products from the new Galaxy Tab S7+ to the Galaxy Tab S6 Lite. | BP7: Shop all | BQ7: 0 | BR7: 0 | BS7: NULL | BT7: NULL | BU7: NULL | BV7: CC WEAR | BW7: =CCModuleCopy!$B$11 -> ME_HeadImage_Wearables_500xV.jpg | BX7: =CCModuleCopy!$C$11 -> Get up to $100 off select watches and earbuds | BY7: =CCModuleCopy!$D$11 -> NULL | BZ7: =CCModuleCopy!$E$11 -> Treat yourself (or someone special) to Galaxy Watch3 Titanium, Watch3, Buds+ and more, suited for every lifestyle and every holiday shopping budget. Plus, now you can flex your fashion muscles with the new Samsung Design Studio. Create a Galaxy Watch as unique as you, today. | CA7: =CCModuleCopy!$F$11 -> Shop all | CB7: =CCModuleCopy!$G$11 -> https://www.samsung.com/us/shop/all-deals/watches-audio-accessories-deals/ | CC7: =CCModuleCopy!$H$11 -> https://shopsamsung.page.link?link=https%3A%2F%2Fwww.samsung.com%2Fus%2Fshop%2Fall-deals%2Ftablets-wearables-cell-phone-accessories-deals%2F%3FofferCID%3DearlyAccess%26utm_source%3Dsamsung%26utm_medium%3Demail%26utm_campaign%3Dholiday_deals_t3_11172020%26marsLinkCategory%3D__MARSTRACKING__%26MKM_RID%3D__BPNUMBER__%26MKM_MID%3D__DELIVERNAME__%26cid%3D__CID____SEGMENTCODE__%26bpid%3D__BPNUMBER__&utm_source=samsung&utm_medium=email&utm_campaign=holiday_deals_t3_11172020&marsLinkCategory=__MARSTRACKING__&MKM_RID=__BPNUMBER__&MKM_MID=__DELIVERNAME__&cid=__CID____SEGMENTCODE__&bpid=__BPNUMBER__&apn=com.samsung.ecomm&al=samsungestore%3A%2F%2Fgototab%23tab%3D4%23subtabid%3DTablets_Wearables_Offers%23offerCID%3DearlyAccess%23utm_source%3Dsamsung%23utm_medium%3Demail%23utm_campaign%3Dholiday_deals_t3_11172020%23marsLinkCategory%3D__MARSTRACKING__%23MKM_RID%3D__BPNUMBER__%23MKM_MID%3D__DELIVERNAME__%23cid%3D__CID____SEGMENTCODE__%23bpid%3D__BPNUMBER__&afl=https%3A%2F%2Fwww.samsung.com%2Fus%2Fshop%2Fall-deals%2Ftablets-wearables-cell-phone-accessories-deals%2F%3FofferCID%3DearlyAccess%26utm_source%3Dsamsung%26utm_medium%3Demail%26utm_campaign%3Dholiday_deals_t3_11172020%26marsLinkCategory%3D__MARSTRACKING__%26MKM_RID%3D__BPNUMBER__%26MKM_MID%3D__DELIVERNAME__%26cid%3D__CID____SEGMENTCODE__%26bpid%3D__BPNUMBER__&efr=1 | CD7: =CCModuleCopy!$I$11 -> NULL | CE7: =CCModuleCopy!$J$11 -> NULL | CF7: =CCModuleCopy!$K$11 -> NULL | CG7: CC COMPUTER | CH7: =CCModuleCopy!$B$13 -> CE_HeadImage_Computing_500xV.jpg | CI7: =CCModuleCopy!$C$13 -> Get up to 60% off memory cards, SSD, monitors and more | CJ7: =CCModuleCopy!$D$13 -> NULL | CK7: =CCModuleCopy!$E$13 -> Expand the way you play, store and create and get up to 30% off monitors, up to 60% off memory cards, up to 35% off SSD and more. Work and game smarter, not harder with these must-have computing offers. | CL7: =CCModuleCopy!$F$13 -> Shop all | CM7: =CCModuleCopy!$G$13 -> https://www.samsung.com/us/shop/all-deals/tablets-laptops-computers-deals/ | CN7: =CCModuleCopy!$H$13 -> https://shopsamsung.page.link?link=https%3A%2F%2Fwww.samsung.com%2Fus%2Fshop%2Fall-deals%2Flaptop-and-computer-deals%2F%3FofferCID%3DearlyAccess%26utm_source%3Dsamsung%26utm_medium%3Demail%26utm_campaign%3Dholiday_deals_t3_11172020%26marsLinkCategory%3D__MARSTRACKING__%26MKM_RID%3D__BPNUMBER__%26MKM_MID%3D__DELIVERNAME__%26cid%3D__CID____SEGMENTCODE__%26bpid%3D__BPNUMBER__%26iosparam%3Dsamsungestore%25253A%25252F%25252Fgototab%252523tab%25253D4%252523subtabid%25253DComputing_Offers%252523offerCID%25253DearlyAccess%252523segmentName%25253DholidayReserve%252523utm_source%25253Dsamsung%252523utm_medium%25253Demail%252523utm_campaign%25253Dholiday_deals_t3_11172020%252523marsLinkCategory%25253D__MARSTRACKING__%252523MKM_RID%25253D__BPNUMBER__%252523MKM_MID%25253D__DELIVERNAME__%252523cid%25253D__CID____SEGMENTCODE__%252523bpid%25253D__BPNUMBER__&utm_source=samsung&utm_medium=email&utm_campaign=holiday_deals_t3_11172020&marsLinkCategory=__MARSTRACKING__&MKM_RID=__BPNUMBER__&MKM_MID=__DELIVERNAME__&cid=__CID____SEGMENTCODE__&bpid=__BPNUMBER__&apn=com.samsung.ecomm&al=samsungestore%3A%2F%2Fgototab%23tab%3D4%23subtabid%3DComputing_Offers%23offerCID%3DearlyAccess%23segmentName%3DholidayReserve%23utm_source%3Dsamsung%23utm_medium%3Demail%23utm_campaign%3Dholiday_deals_t3_11172020%23marsLinkCategory%3D__MARSTRACKING__%23MKM_RID%3D__BPNUMBER__%23MKM_MID%3D__DELIVERNAME__%23cid%3D__CID____SEGMENTCODE__%23bpid%3D__BPNUMBER__&afl=https%3A%2F%2Fwww.samsung.com%2Fus%2Fshop%2Fall-deals%2Flaptop-and-computer-deals%2F%3FofferCID%3DearlyAccess%26utm_source%3Dsamsung%26utm_medium%3Demail%26utm_campaign%3Dholiday_deals_t3_11172020%26marsLinkCategory%3D__MARSTRACKING__%26MKM_RID%3D__BPNUMBER__%26MKM_MID%3D__DELIVERNAME__%26cid%3D__CID____SEGMENTCODE__%26bpid%3D__BPNUMBER__&isi=1274679179&ibi=com.samsung.ShopSamsung&ius=samsungestore&ifl=https%3A%2F%2Fwww.samsung.com%2Fus%2Fshop%2Fall-deals%2Flaptop-and-computer-deals%2F%3FofferCID%3DearlyAccess%26utm_source%3Dsamsung%26utm_medium%3Demail%26utm_campaign%3Dholiday_deals_t3_11172020%26marsLinkCategory%3D__MARSTRACKING__%26MKM_RID%3D__BPNUMBER__%26MKM_MID%3D__DELIVERNAME__%26cid%3D__CID____SEGMENTCODE__%26bpid%3D__BPNUMBER__&efr=1 | CO7: =CCModuleCopy!$I$13 -> NULL | CP7: =CCModuleCopy!$J$13 -> NULL | CQ7: =CCModuleCopy!$K$13 -> NULL | CR7: CC HA | CS7: =CCModuleCopy!$B$9 -> HA_HeadImage_Shop_HA_500xV.jpg | CT7: =CCModuleCopy!$C$9 -> Save up to 50% on everything you need to upgrade your home and home care | CU7: =CCModuleCopy!$D$9 -> NULL | CV7: =CCModuleCopy!$E$9 -> Get an additional 10% off when you buy 4 or more eligible kitchen appliances. Save even more with early Black Friday prices for select categories.α Plus, shop our time and cost-saving laundry and floor care products, and buy and try a Jet Stick Cordless Vacuum with our new 100-day, risk-free trial. | CW7: =CCModuleCopy!$F$9 -> Shop all | CX7: =CCModuleCopy!$G$9 -> https://www.samsung.com/us/shop/all-deals/home-appliance-and-smart-home-sales/ | CY7: =CCModuleCopy!$H$9 -> https://shopsamsung.page.link?link=https%3A%2F%2Fwww.samsung.com%2Fus%2Fshop%2Fall-deals%2Fhome-appliance-and-smart-home-sales%2F%3FofferCID%3DearlyAccess%26utm_source%3Dsamsung%26utm_medium%3Demail%26utm_campaign%3Dholiday_deals_t3_11172020%26marsLinkCategory%3D__MARSTRACKING__%26MKM_RID%3D__BPNUMBER__%26MKM_MID%3D__DELIVERNAME__%26cid%3D__CID____SEGMENTCODE__%26bpid%3D__BPNUMBER__%26iosparam%3Dsamsungestore%25253A%25252F%25252Fgototab%252523tab%25253D4%252523subtabid%25253DHome_Appliances_SmartHome_Offers%252523offerCID%25253DearlyAccess%252523segmentName%25253DholidayReserve%252523utm_source%25253Dsamsung%252523utm_medium%25253Demail%252523utm_campaign%25253Dholiday_deals_t3_11172020%252523marsLinkCategory%25253D__MARSTRACKING__%252523MKM_RID%25253D__BPNUMBER__%252523MKM_MID%25253D__DELIVERNAME__%252523cid%25253D__CID____SEGMENTCODE__%252523bpid%25253D__BPNUMBER__&utm_source=samsung&utm_medium=email&utm_campaign=holiday_deals_t3_11172020&marsLinkCategory=__MARSTRACKING__&MKM_RID=__BPNUMBER__&MKM_MID=__DELIVERNAME__&cid=__CID____SEGMENTCODE__&bpid=__BPNUMBER__&apn=com.samsung.ecomm&al=samsungestore%3A%2F%2Fgototab%23tab%3D4%23subtabid%3DHome_Appliances_SmartHome_Offers%23offerCID%3DearlyAccess%23segmentName%3DholidayReserve%23utm_source%3Dsamsung%23utm_medium%3Demail%23utm_campaign%3Dholiday_deals_t3_11172020%23marsLinkCategory%3D__MARSTRACKING__%23MKM_RID%3D__BPNUMBER__%23MKM_MID%3D__DELIVERNAME__%23cid%3D__CID____SEGMENTCODE__%23bpid%3D__BPNUMBER__&afl=https%3A%2F%2Fwww.samsung.com%2Fus%2Fshop%2Fall-deals%2Fhome-appliance-and-smart-home-sales%2F%3FofferCID%3DearlyAccess%26utm_source%3Dsamsung%26utm_medium%3Demail%26utm_campaign%3Dholiday_deals_t3_11172020%26marsLinkCategory%3D__MARSTRACKING__%26MKM_RID%3D__BPNUMBER__%26MKM_MID%3D__DELIVERNAME__%26cid%3D__CID____SEGMENTCODE__%26bpid%3D__BPNUMBER__&isi=1274679179&ibi=com.samsung.ShopSamsung&ius=samsungestore&ifl=https%3A%2F%2Fwww.samsung.com%2Fus%2Fshop%2Fall-deals%2Fhome-appliance-and-smart-home-sales%2F%3FofferCID%3DearlyAccess%26utm_source%3Dsamsung%26utm_medium%3Demail%26utm_campaign%3Dholiday_deals_t3_11172020%26marsLinkCategory%3D__MARSTRACKING__%26MKM_RID%3D__BPNUMBER__%26MKM_MID%3D__DELIVERNAME__%26cid%3D__CID____SEGMENTCODE__%26bpid%3D__BPNUMBER__&efr=1 | CZ7: =CCModuleCopy!$I$9 -> NULL | DA7: =CCModuleCopy!$J$9 -> NULL | DB7: =CCModuleCopy!$K$9 -> NULL | DC7: GIFT GUIDE | DD7: =MiscBanners!$H$4 -> Give-wonder-500xV.jpg | DE7: =MiscBanners!$I$4 -> The gift that keeps on giving | DF7: =MiscBanners!$J$4 -> NULL | DG7: =MiscBanners!$K$4 -> Discover even more exclusive offers on your favorite products and unlock the power of smart and savvy gifting. | DH7: =MiscBanners!$L$4 -> Shop now | DI7: =MiscBanners!$M$4 -> https://www.samsung.com/us/gift-ideas/ | DJ7: =MiscBanners!$N$4 -> https://shopsamsung.page.link?link=https%3A%2F%2Fwww.samsung.com%2Fus%2Fgift-ideas%2F%3FofferCID%3DearlyAccess%26utm_source%3Dsamsung%26utm_medium%3Demail%26utm_campaign%3Dholiday_deals_t3_11172020%26marsLinkCategory%3D__MARSTRACKING__%26MKM_RID%3D__BPNUMBER__%26MKM_MID%3D__DELIVERNAME__%26cid%3D__CID____SEGMENTCODE__%26bpid%3D__BPNUMBER__%26iosparam%3Dsamsungestore%25253A%25252F%25252Fopenwebview%252523url%25253Dhttps%25253A%25252F%25252Fwww.samsung.com%25252Fus%25252Fapp%25252Fgift-ideas%25252F%25253FofferCID%25253DearlyAccess%252526segmentName%25253DholidayReserve%252523utm_source%25253Dsamsung%252523utm_medium%25253Demail%252523utm_campaign%25253Dholiday_deals_t3_11172020%252523marsLinkCategory%25253D__MARSTRACKING__%252523MKM_RID%25253D__BPNUMBER__%252523MKM_MID%25253D__DELIVERNAME__%252523cid%25253D__CID____SEGMENTCODE__%252523bpid%25253D__BPNUMBER__&utm_source=samsung&utm_medium=email&utm_campaign=holiday_deals_t3_11172020&marsLinkCategory=__MARSTRACKING__&MKM_RID=__BPNUMBER__&MKM_MID=__DELIVERNAME__&cid=__CID____SEGMENTCODE__&bpid=__BPNUMBER__&apn=com.samsung.ecomm&al=samsungestore%3A%2F%2Fopenwebview%23url%3Dhttps%3A%2F%2Fwww.samsung.com%2Fus%2Fapp%2Fgift-ideas%2F%3FofferCID%3DearlyAccess%26segmentName%3DholidayReserve%23utm_source%3Dsamsung%23utm_medium%3Demail%23utm_campaign%3Dholiday_deals_t3_11172020%23marsLinkCategory%3D__MARSTRACKING__%23MKM_RID%3D__BPNUMBER__%23MKM_MID%3D__DELIVERNAME__%23cid%3D__CID____SEGMENTCODE__%23bpid%3D__BPNUMBER__&afl=https%3A%2F%2Fwww.samsung.com%2Fus%2Fgift-ideas%2F%3FofferCID%3DearlyAccess%26utm_source%3Dsamsung%26utm_medium%3Demail%26utm_campaign%3Dholiday_deals_t3_11172020%26marsLinkCategory%3D__MARSTRACKING__%26MKM_RID%3D__BPNUMBER__%26MKM_MID%3D__DELIVERNAME__%26cid%3D__CID____SEGMENTCODE__%26bpid%3D__BPNUMBER__&isi=1274679179&ibi=com.samsung.ShopSamsung&ius=samsungestore&ifl=https%3A%2F%2Fwww.samsung.com%2Fus%2Fgift-ideas%2F%3FofferCID%3DearlyAccess%26utm_source%3Dsamsung%26utm_medium%3Demail%26utm_campaign%3Dholiday_deals_t3_11172020%26marsLinkCategory%3D__MARSTRACKING__%26MKM_RID%3D__BPNUMBER__%26MKM_MID%3D__DELIVERNAME__%26cid%3D__CID____SEGMENTCODE__%26bpid%3D__BPNUMBER__&efr=1 | DK7: =MiscBanners!$O$4 -> NULL | DL7: =MiscBanners!$P$4 -> NULL | DM7: =MiscBanners!$Q$4 -> NULL | DN7: FOOTER | DY7: TC1 | DZ7: =TC!B5 -> NULL | EA7: =TC!C5 -> NULL | EB7: =TC!D5 -> NULL | EC7: =TC!E5 -> †18+ & 50 US/DC only. By 11/29/2020 11:59 PM EST, purchase a qualifying device on device installment plan, 2-year contract plan, lease or outright purchase at full retail price (“Qualifying Purchase”), & receive a Samsung Credit of $30 (“Gift”) instant credit from Samsung for use towards an eligible purchase including select wearables, tablets, PC’s and accessories when you purchase qualifying smartphone (“Qualifying Purchase”) before 01/15/21 at 11:59 PM EST. You must make a Qualifying Purchase on Samsung.com or the Shop Samsung App to receive an instant credit which may be applied instantly or deferred to a future eligible purchase. Gift valid for use on eligible purchases from 11/10/20- 01/15/21 or while supplies last, and is a one-time use certificate; when first used, any value not used is lost. Gift is non-transferrable and limited to 1 instant credit per registered customer. Samsung Credits are valid only at www.Samsung.com or in the App for use towards an eligible purchase. Void where prohibited or restricted by law. Additional restrictions apply. Offer subject to additional terms here. Samsung reserves the right to modify or discontinue offer at any time by posting notice on the app or website | ED7: =TC!F5 -> NULL | EE7: =TC!G5 -> https://www.samsung.com/us/ | EF7: =TC!H5 -> 0 | EG7: =TC!I5 -> NULL | ... EI7: =TC!K5 -> NULL | EJ7: TC2 | EK7: =TC!B6 -> NULL | EL7: =TC!C6 -> NULL | EM7: =TC!D6 -> NULL | EN7: =TC!E6 -> ‡18+ & 50 US/DC only. Between 10/26/20 at 12:01 AM EST and 11/18/20 at 11:59 PM EST (“Registration Period”), register for the Samsung Holiday instant credit promotion to receive a $20 instant credit from Samsung for use towards an eligible purchase including select wearables, tablets, PC’s and accessories when you purchase qualifying smartphone (“Qualifying Purchase”) before 01/15/21 at 11:59 PM EST. You must make a Qualifying Purchase on Samsung.com or the Shop Samsung App to receive an instant credit which may be applied instantly or deferred to a future eligible purchase. Gift valid for use on eligible purchases from 11/10/20- 01/15/21 or while supplies last, and is a one-time use certificate; when first used, any value not used is lost. Gift is non-transferrable and limited to 1 instant credit per registered customer. Samsung Credits are valid only at www.Samsung.com or in the App for use towards an eligible purchase. Void where prohibited or restricted by law. Additional restrictions apply. Offer subject to additional terms here. Samsung reserves the right to modify or discontinue offer at any time by posting notice on the app or website. | EO7: =TC!F6 -> NULL | EP7: =TC!G6 -> https://www.samsung.com/us/ | EQ7: =TC!H6 -> 0 | ER7: =TC!I6 -> NULL | ... ET7: =TC!K6 -> NULL | EU7: TC3 | EV7: =TC!B7 -> NULL | EW7: =TC!C7 -> NULL | EX7: =TC!D7 -> NULL | EY7: =TC!E7 -> αMust be an eligible legal resident of the 50 US/DC & at least 18 years old to participate. Purchase at least 4 eligible Samsung Home Appliance products in the same transaction (Refrigerators, Ranges, Countertop Microwaves, Over-the-Range Microwave Ovens, Dishwashers, Wall Ovens, Cooktops, or Range Hoods) (“a Qualifying Purchase”) between 11/04/20 and 12/02/20 on Samsung.com, and you will receive a 10% instant rebate off of the pre-tax purchase price of your Qualifying Purchase (“Gift”). Purchases must include products from different product categories. If more than 4 eligible products are purchased, the additional products purchased are eligible for the discount as long as the eligibility requirements listed above and below are met. Eligible categories are Refrigerators, Ranges, Countertop Microwaves, Over-the-Range Microwave Ovens, Dishwashers, Wall Ovens, Cooktops, or Range Hoods. Samsung Chef Collection, Washers, Dryers, Pedestals, Vacuums, Air Purifiers, AirDresser, Wine Cooler, and all accessories are not eligible. Quantities limited; offer valid while supplies last. One claim per household. This Offer and instant rebate Gift redemption applies to Samsung.com only. Offer cannot be combined with other Samsung offers, rebates, programs, or promotions unless otherwise stated. | EZ7: =TC!F7 -> NULL | FA7: =TC!G7 -> 0 | FB7: =TC!H7 -> 0 | FC7: =TC!I7 -> NULL | ... FE7: =TC!K7 -> NULL | FF7: TC4 | FG7: =TC!B8 -> 0 | FH7: =TC!C8 -> 0 | FI7: =TC!D8 -> 0 | FJ7: =TC!E8 -> 0 | FK7: =TC!F8 -> 0 | FL7: =TC!G8 -> 0 | FM7: =TC!H8 -> 0 | FN7: =TC!I8 -> 0 | ... FP7: =TC!K8 -> 0
A8: CC | B8: MB_TABLET | C8: X | D8: X | E8: Reserver | G8: Cyber Monday is on. | H8: Act fast to save on showstopping gifts while supplies last. | I8: EPP Banner | J8: NULL | K8: NULL | L8: NULL | M8: NULL | N8: NULL | O8: NULL | P8: NULL | Q8: NULL | R8: NULL | S8: Hero & Countdown Timer Image | T8: ='Dynamic Banners'!$L$4 -> Cyber-monday-1.png | U8: ='Dynamic Banners'!$M$4 -> The clock is ticking away for Cyber Monday | V8: NULL | W8: ='Dynamic Banners'!$N$4 -> Shop amazing offers on showstopping products while supplies last. | X8: NULL | Y8: =[1]MiscBanners!$B$4 -> https://www.samsung.com/us/shop/all-deals/ | Z8: =[1]MiscBanners!$C$4 -> https://shopsamsung.page.link?link=https%3A%2F%2Fwww.samsung.com%2Fus%2Fshop%2Fall-deals%2F%3FofferCID%3DearlyAccess%26utm_source%3Dsamsung%26utm_medium%3Demail%26utm_campaign%3Dholiday_deals_t3_11172020%26marsLinkCategory%3D__MARSTRACKING__%26MKM_RID%3D__BPNUMBER__%26MKM_MID%3D__DELIVERNAME__%26cid%3D__CID____SEGMENTCODE__%26bpid%3D__BPNUMBER__%26iosparam%3Dsamsungestore%25253A%25252F%25252Fgototab%252523tab%25253D4%252523offerCID%25253DearlyAccess%252523utm_source%25253Dsamsung%252523utm_medium%25253Demail%252523utm_campaign%25253Dholiday_deals_t3_11172020%252523marsLinkCategory%25253D__MARSTRACKING__%252523MKM_RID%25253D__BPNUMBER__%252523MKM_MID%25253D__DELIVERNAME__%252523cid%25253D__CID____SEGMENTCODE__%252523bpid%25253D__BPNUMBER__&utm_source=samsung&utm_medium=email&utm_campaign=holiday_deals_t3_11172020&marsLinkCategory=__MARSTRACKING__&MKM_RID=__BPNUMBER__&MKM_MID=__DELIVERNAME__&cid=__CID____SEGMENTCODE__&bpid=__BPNUMBER__&apn=com.samsung.ecomm&al=samsungestore%3A%2F%2Fgototab%23tab%3D4%23offerCID%3DearlyAccess%23utm_source%3Dsamsung%23utm_medium%3Demail%23utm_campaign%3Dholiday_deals_t3_11172020%23marsLinkCategory%3D__MARSTRACKING__%23MKM_RID%3D__BPNUMBER__%23MKM_MID%3D__DELIVERNAME__%23cid%3D__CID____SEGMENTCODE__%23bpid%3D__BPNUMBER__&afl=https%3A%2F%2Fwww.samsung.com%2Fus%2Fshop%2Fall-deals%2F%3FofferCID%3DearlyAccess%26utm_source%3Dsamsung%26utm_medium%3Demail%26utm_campaign%3Dholiday_deals_t3_11172020%26marsLinkCategory%3D__MARSTRACKING__%26MKM_RID%3D__BPNUMBER__%26MKM_MID%3D__DELIVERNAME__%26cid%3D__CID____SEGMENTCODE__%26bpid%3D__BPNUMBER__&isi=1274679179&ibi=com.samsung.ShopSamsung&ius=samsungestore&ifl=https%3A%2F%2Fwww.samsung.com%2Fus%2Fshop%2Fall-deals%2F%3FofferCID%3DearlyAccess%26utm_source%3Dsamsung%26utm_medium%3Demail%26utm_campaign%3Dholiday_deals_t3_11172020%26marsLinkCategory%3D__MARSTRACKING__%26MKM_RID%3D__BPNUMBER__%26MKM_MID%3D__DELIVERNAME__%26cid%3D__CID____SEGMENTCODE__%26bpid%3D__BPNUMBER__&efr=1 | AA8: NULL | AB8: NULL | AC8: NULL | AD8: Hero & Countdown Timer Copy | AE8: NULL | AF8: NULL | AG8: While supplies last. | AH8: Today is your day to shop some of our greatest offers of the year. | AI8: NULL | AJ8: =[1]MiscBanners!$B$4 -> https://www.samsung.com/us/shop/all-deals/ | AK8: =[1]MiscBanners!$C$4 -> https://shopsamsung.page.link?link=https%3A%2F%2Fwww.samsung.com%2Fus%2Fshop%2Fall-deals%2F%3FofferCID%3DearlyAccess%26utm_source%3Dsamsung%26utm_medium%3Demail%26utm_campaign%3Dholiday_deals_t3_11172020%26marsLinkCategory%3D__MARSTRACKING__%26MKM_RID%3D__BPNUMBER__%26MKM_MID%3D__DELIVERNAME__%26cid%3D__CID____SEGMENTCODE__%26bpid%3D__BPNUMBER__%26iosparam%3Dsamsungestore%25253A%25252F%25252Fgototab%252523tab%25253D4%252523offerCID%25253DearlyAccess%252523utm_source%25253Dsamsung%252523utm_medium%25253Demail%252523utm_campaign%25253Dholiday_deals_t3_11172020%252523marsLinkCategory%25253D__MARSTRACKING__%252523MKM_RID%25253D__BPNUMBER__%252523MKM_MID%25253D__DELIVERNAME__%252523cid%25253D__CID____SEGMENTCODE__%252523bpid%25253D__BPNUMBER__&utm_source=samsung&utm_medium=email&utm_campaign=holiday_deals_t3_11172020&marsLinkCategory=__MARSTRACKING__&MKM_RID=__BPNUMBER__&MKM_MID=__DELIVERNAME__&cid=__CID____SEGMENTCODE__&bpid=__BPNUMBER__&apn=com.samsung.ecomm&al=samsungestore%3A%2F%2Fgototab%23tab%3D4%23offerCID%3DearlyAccess%23utm_source%3Dsamsung%23utm_medium%3Demail%23utm_campaign%3Dholiday_deals_t3_11172020%23marsLinkCategory%3D__MARSTRACKING__%23MKM_RID%3D__BPNUMBER__%23MKM_MID%3D__DELIVERNAME__%23cid%3D__CID____SEGMENTCODE__%23bpid%3D__BPNUMBER__&afl=https%3A%2F%2Fwww.samsung.com%2Fus%2Fshop%2Fall-deals%2F%3FofferCID%3DearlyAccess%26utm_source%3Dsamsung%26utm_medium%3Demail%26utm_campaign%3Dholiday_deals_t3_11172020%26marsLinkCategory%3D__MARSTRACKING__%26MKM_RID%3D__BPNUMBER__%26MKM_MID%3D__DELIVERNAME__%26cid%3D__CID____SEGMENTCODE__%26bpid%3D__BPNUMBER__&isi=1274679179&ibi=com.samsung.ShopSamsung&ius=samsungestore&ifl=https%3A%2F%2Fwww.samsung.com%2Fus%2Fshop%2Fall-deals%2F%3FofferCID%3DearlyAccess%26utm_source%3Dsamsung%26utm_medium%3Demail%26utm_campaign%3Dholiday_deals_t3_11172020%26marsLinkCategory%3D__MARSTRACKING__%26MKM_RID%3D__BPNUMBER__%26MKM_MID%3D__DELIVERNAME__%26cid%3D__CID____SEGMENTCODE__%26bpid%3D__BPNUMBER__&efr=1 | AL8: NULL | AM8: NULL | AN8: NULL | AO8: CC TABLET | AP8: =CCModuleCopy!$B$15 -> Tablet-HeadImage-500xV.jpg | AQ8: =CCModuleCopy!$C$15 -> Save up to $150 on select tablets | AR8: =CCModuleCopy!$D$15 -> NULL | AS8: =CCModuleCopy!$E$15 -> Empower how you create, learn, game and more with our powerful line of tablets. Shop offers on must-have products from the new Galaxy Tab S7+ to the Galaxy Tab S6 Lite. | AT8: =CCModuleCopy!$F$15 -> Shop all | AU8: =CCModuleCopy!$G$15 -> https://www.samsung.com/us/shop/all-deals/tablets-laptops-computers-deals/ | AV8: =CCModuleCopy!$H$15 -> https://shopsamsung.page.link?link=https%3A%2F%2Fwww.samsung.com%2Fus%2Fshop%2Fall-deals%2Ftablets-laptops-computers-deals%2F%3FofferCID%3DearlyAccess%26utm_source%3Dsamsung%26utm_medium%3Demail%26utm_campaign%3Dholiday_deals_rev_11182020%26marsLinkCategory%3D__MARSTRACKING__%26MKM_RID%3D__BPNUMBER__%26MKM_MID%3D__DELIVERNAME__%26cid%3D__CID____SEGMENTCODE__%26bpid%3D__BPNUMBER__%26iosparam%3Dsamsungestore%25253A%25252F%25252Fgototab%252523tab%25253D4%252523subtabid%25253DTablets%252526Computing_Offers%252523offerCID%25253DearlyAccess%252523utm_source%25253Dsamsung%252523utm_medium%25253Demail%252523utm_campaign%25253Dholiday_deals_rev_11182020%252523marsLinkCategory%25253D__MARSTRACKING__%252523MKM_RID%25253D__BPNUMBER__%252523MKM_MID%25253D__DELIVERNAME__%252523cid%25253D__CID____SEGMENTCODE__%252523bpid%25253D__BPNUMBER__&utm_source=samsung&utm_medium=email&utm_campaign=holiday_deals_rev_11182020&marsLinkCategory=__MARSTRACKING__&MKM_RID=__BPNUMBER__&MKM_MID=__DELIVERNAME__&cid=__CID____SEGMENTCODE__&bpid=__BPNUMBER__&apn=com.samsung.ecomm&al=samsungestore%3A%2F%2Fgototab%23tab%3D4%23subtabid%3DTablets%26Computing_Offers%23offerCID%3DearlyAccess%23utm_source%3Dsamsung%23utm_medium%3Demail%23utm_campaign%3Dholiday_deals_rev_11182020%23marsLinkCategory%3D__MARSTRACKING__%23MKM_RID%3D__BPNUMBER__%23MKM_MID%3D__DELIVERNAME__%23cid%3D__CID____SEGMENTCODE__%23bpid%3D__BPNUMBER__&afl=https%3A%2F%2Fwww.samsung.com%2Fus%2Fshop%2Fall-deals%2Ftablets-laptops-computers-deals%2F%3FofferCID%3DearlyAccess%26utm_source%3Dsamsung%26utm_medium%3Demail%26utm_campaign%3Dholiday_deals_rev_11182020%26marsLinkCategory%3D__MARSTRACKING__%26MKM_RID%3D__BPNUMBER__%26MKM_MID%3D__DELIVERNAME__%26cid%3D__CID____SEGMENTCODE__%26bpid%3D__BPNUMBER__&isi=1274679179&ibi=com.samsung.ShopSamsung&ius=samsungestore&ifl=https%3A%2F%2Fwww.samsung.com%2Fus%2Fshop%2Fall-deals%2Ftablets-laptops-computers-deals%2F%3FofferCID%3DearlyAccess%26utm_source%3Dsamsung%26utm_medium%3Demail%26utm_campaign%3Dholiday_deals_rev_11182020%26marsLinkCategory%3D__MARSTRACKING__%26MKM_RID%3D__BPNUMBER__%26MKM_MID%3D__DELIVERNAME__%26cid%3D__CID____SEGMENTCODE__%26bpid%3D__BPNUMBER__&efr=1 | AW8: =CCModuleCopy!$I$15 -> NULL | AX8: =CCModuleCopy!$J$15 -> NULL | AY8: =CCModuleCopy!$K$15 -> NULL | AZ8: CC MOBILE RESERVER | BA8: =CCModuleCopy!$B$3 -> IM_HeadImage_Shop_Phones_500xV.jpg | BB8: =CCModuleCopy!$C$3 -> Save up to $1000 instantly on the latest and greatest Galaxy smartphones | BC8: =CCModuleCopy!$D$3 -> NULL | BD8: =CCModuleCopy!$E$3 -> Whether you're here to improve the way you work or power up the way you play, shop some of our best offers of the year on Galaxy Note20 5G, S20 FE 5G, Z Fold2 5G and select A series devices. Plus, get $50 or more instant credit toward accessories with any smartphone purchase to complete your Galaxy Ecosystem.‡† | BE8: =CCModuleCopy!$F$3 -> Shop all | BF8: =CCModuleCopy!$G$3 -> https://www.samsung.com/us/shop/all-deals/cell-phone-deals/ | BG8: =CCModuleCopy!$H$3 -> https://shopsamsung.page.link?link=https%3A%2F%2Fwww.samsung.com%2Fus%2Fshop%2Fall-deals%2Fcell-phone-deals%2F%3FofferCID%3DearlyAccess%26utm_source%3Dsamsung%26utm_medium%3Demail%26utm_campaign%3Dholiday_deals_t3_11172020%26marsLinkCategory%3D__MARSTRACKING__%26MKM_RID%3D__BPNUMBER__%26MKM_MID%3D__DELIVERNAME__%26cid%3D__CID____SEGMENTCODE__%26bpid%3D__BPNUMBER__&utm_source=samsung&utm_medium=email&utm_campaign=holiday_deals_t3_11172020&marsLinkCategory=__MARSTRACKING__&MKM_RID=__BPNUMBER__&MKM_MID=__DELIVERNAME__&cid=__CID____SEGMENTCODE__&bpid=__BPNUMBER__&apn=com.samsung.ecomm&al=samsungestore%3A%2F%2Fgototab%23tab%3D4%23subtabid%3DMobile_Offers%23offerCID%3DearlyAccess%23segmentName%3DholidayReserve%23utm_source%3Dsamsung%23utm_medium%3Demail%23utm_campaign%3Dholiday_deals_t3_11172020%23marsLinkCategory%3D__MARSTRACKING__%23MKM_RID%3D__BPNUMBER__%23MKM_MID%3D__DELIVERNAME__%23cid%3D__CID____SEGMENTCODE__%23bpid%3D__BPNUMBER__&afl=https%3A%2F%2Fwww.samsung.com%2Fus%2Fshop%2Fall-deals%2Fcell-phone-deals%2F%3FofferCID%3DearlyAccess%26utm_source%3Dsamsung%26utm_medium%3Demail%26utm_campaign%3Dholiday_deals_t3_11172020%26marsLinkCategory%3D__MARSTRACKING__%26MKM_RID%3D__BPNUMBER__%26MKM_MID%3D__DELIVERNAME__%26cid%3D__CID____SEGMENTCODE__%26bpid%3D__BPNUMBER__&efr=1 | BH8: =CCModuleCopy!$I$3 -> NULL | BI8: =CCModuleCopy!$J$3 -> NULL | BJ8: =CCModuleCopy!$K$3 -> NULL | BK8: CC TV & ACCESSORIES | BL8: =CCModuleCopy!$B$7 -> HE_HeadImage_Shop_TVs_500xV.jpg | BM8: =CCModuleCopy!$C$7 -> Get up to $3000 off select 8K, 4K and Lifestyle TVs | BN8: =CCModuleCopy!$D$7 -> NULL | BO8: =CCModuleCopy!$E$7 -> Discover the mind-blowing, true-to-live resolution of QLED technology and create your ultimate home theater today. Save up to $3000 on 8K TVs, up to $1800 on select 4K TVs, up to $1300 on Lifestyle TVs and up to $400 on select soundbars and more. Plus, buy and try select Lifestyle TVs, soundbars and The Premiere Projector with our new 100-day, risk-free trial. | BP8: =CCModuleCopy!$F$7 -> Shop all | BQ8: =CCModuleCopy!$G$7 -> https://www.samsung.com/us/shop/all-deals/tv-and-home-theater-deals/ | BR8: =CCModuleCopy!$H$7 -> https://shopsamsung.page.link?link=https%3A%2F%2Fwww.samsung.com%2Fus%2Fshop%2Fall-deals%2Ftv-and-home-theater-deals%2F%3FofferCID%3DearlyAccess%26utm_source%3Dsamsung%26utm_medium%3Demail%26utm_campaign%3Dholiday_deals_t3_11172020%26marsLinkCategory%3D__MARSTRACKING__%26MKM_RID%3D__BPNUMBER__%26MKM_MID%3D__DELIVERNAME__%26cid%3D__CID____SEGMENTCODE__%26bpid%3D__BPNUMBER__%26iosparam%3Dsamsungestore%25253A%25252F%25252Fgototab%252523tab%25253D4%252523subtabid%25253DTV_Home_Theater_Offers%252523offerCID%25253DearlyAccess%252523segmentName%25253DholidayReserve%252523utm_source%25253Dsamsung%252523utm_medium%25253Demail%252523utm_campaign%25253Dholiday_deals_t3_11172020%252523marsLinkCategory%25253D__MARSTRACKING__%252523MKM_RID%25253D__BPNUMBER__%252523MKM_MID%25253D__DELIVERNAME__%252523cid%25253D__CID____SEGMENTCODE__%252523bpid%25253D__BPNUMBER__&utm_source=samsung&utm_medium=email&utm_campaign=holiday_deals_t3_11172020&marsLinkCategory=__MARSTRACKING__&MKM_RID=__BPNUMBER__&MKM_MID=__DELIVERNAME__&cid=__CID____SEGMENTCODE__&bpid=__BPNUMBER__&apn=com.samsung.ecomm&al=samsungestore%3A%2F%2Fgototab%23tab%3D4%23subtabid%3DTV_Home_Theater_Offers%23offerCID%3DearlyAccess%23segmentName%3DholidayReserve%23utm_source%3Dsamsung%23utm_medium%3Demail%23utm_campaign%3Dholiday_deals_t3_11172020%23marsLinkCategory%3D__MARSTRACKING__%23MKM_RID%3D__BPNUMBER__%23MKM_MID%3D__DELIVERNAME__%23cid%3D__CID____SEGMENTCODE__%23bpid%3D__BPNUMBER__&afl=https%3A%2F%2Fwww.samsung.com%2Fus%2Fshop%2Fall-deals%2Ftv-and-home-theater-deals%2F%3FofferCID%3DearlyAccess%26utm_source%3Dsamsung%26utm_medium%3Demail%26utm_campaign%3Dholiday_deals_t3_11172020%26marsLinkCategory%3D__MARSTRACKING__%26MKM_RID%3D__BPNUMBER__%26MKM_MID%3D__DELIVERNAME__%26cid%3D__CID____SEGMENTCODE__%26bpid%3D__BPNUMBER__&isi=1274679179&ibi=com.samsung.ShopSamsung&ius=samsungestore&ifl=https%3A%2F%2Fwww.samsung.com%2Fus%2Fshop%2Fall-deals%2Ftv-and-home-theater-deals%2F%3FofferCID%3DearlyAccess%26utm_source%3Dsamsung%26utm_medium%3Demail%26utm_campaign%3Dholiday_deals_t3_11172020%26marsLinkCategory%3D__MARSTRACKING__%26MKM_RID%3D__BPNUMBER__%26MKM_MID%3D__DELIVERNAME__%26cid%3D__CID____SEGMENTCODE__%26bpid%3D__BPNUMBER__&efr=1 | BS8: =CCModuleCopy!$I$7 -> NULL | BT8: =CCModuleCopy!$J$7 -> NULL | BU8: =CCModuleCopy!$K$7 -> NULL | BV8: CC WEAR | BW8: =CCModuleCopy!$B$11 -> ME_HeadImage_Wearables_500xV.jpg | BX8: =CCModuleCopy!$C$11 -> Get up to $100 off select watches and earbuds | BY8: =CCModuleCopy!$D$11 -> NULL | BZ8: =CCModuleCopy!$E$11 -> Treat yourself (or someone special) to Galaxy Watch3 Titanium, Watch3, Buds+ and more, suited for every lifestyle and every holiday shopping budget. Plus, now you can flex your fashion muscles with the new Samsung Design Studio. Create a Galaxy Watch as unique as you, today. | CA8: =CCModuleCopy!$F$11 -> Shop all | CB8: =CCModuleCopy!$G$11 -> https://www.samsung.com/us/shop/all-deals/watches-audio-accessories-deals/ | CC8: =CCModuleCopy!$H$11 -> https://shopsamsung.page.link?link=https%3A%2F%2Fwww.samsung.com%2Fus%2Fshop%2Fall-deals%2Ftablets-wearables-cell-phone-accessories-deals%2F%3FofferCID%3DearlyAccess%26utm_source%3Dsamsung%26utm_medium%3Demail%26utm_campaign%3Dholiday_deals_t3_11172020%26marsLinkCategory%3D__MARSTRACKING__%26MKM_RID%3D__BPNUMBER__%26MKM_MID%3D__DELIVERNAME__%26cid%3D__CID____SEGMENTCODE__%26bpid%3D__BPNUMBER__&utm_source=samsung&utm_medium=email&utm_campaign=holiday_deals_t3_11172020&marsLinkCategory=__MARSTRACKING__&MKM_RID=__BPNUMBER__&MKM_MID=__DELIVERNAME__&cid=__CID____SEGMENTCODE__&bpid=__BPNUMBER__&apn=com.samsung.ecomm&al=samsungestore%3A%2F%2Fgototab%23tab%3D4%23subtabid%3DTablets_Wearables_Offers%23offerCID%3DearlyAccess%23utm_source%3Dsamsung%23utm_medium%3Demail%23utm_campaign%3Dholiday_deals_t3_11172020%23marsLinkCategory%3D__MARSTRACKING__%23MKM_RID%3D__BPNUMBER__%23MKM_MID%3D__DELIVERNAME__%23cid%3D__CID____SEGMENTCODE__%23bpid%3D__BPNUMBER__&afl=https%3A%2F%2Fwww.samsung.com%2Fus%2Fshop%2Fall-deals%2Ftablets-wearables-cell-phone-accessories-deals%2F%3FofferCID%3DearlyAccess%26utm_source%3Dsamsung%26utm_medium%3Demail%26utm_campaign%3Dholiday_deals_t3_11172020%26marsLinkCategory%3D__MARSTRACKING__%26MKM_RID%3D__BPNUMBER__%26MKM_MID%3D__DELIVERNAME__%26cid%3D__CID____SEGMENTCODE__%26bpid%3D__BPNUMBER__&efr=1 | CD8: =CCModuleCopy!$I$11 -> NULL | CE8: =CCModuleCopy!$J$11 -> NULL | CF8: =CCModuleCopy!$K$11 -> NULL | CG8: CC COMPUTER | CH8: =CCModuleCopy!$B$13 -> CE_HeadImage_Computing_500xV.jpg | CI8: =CCModuleCopy!$C$13 -> Get up to 60% off memory cards, SSD, monitors and more | CJ8: =CCModuleCopy!$D$13 -> NULL | CK8: =CCModuleCopy!$E$13 -> Expand the way you play, store and create and get up to 30% off monitors, up to 60% off memory cards, up to 35% off SSD and more. Work and game smarter, not harder with these must-have computing offers. | CL8: =CCModuleCopy!$F$13 -> Shop all | CM8: =CCModuleCopy!$G$13 -> https://www.samsung.com/us/shop/all-deals/tablets-laptops-computers-deals/ | CN8: =CCModuleCopy!$H$13 -> https://shopsamsung.page.link?link=https%3A%2F%2Fwww.samsung.com%2Fus%2Fshop%2Fall-deals%2Flaptop-and-computer-deals%2F%3FofferCID%3DearlyAccess%26utm_source%3Dsamsung%26utm_medium%3Demail%26utm_campaign%3Dholiday_deals_t3_11172020%26marsLinkCategory%3D__MARSTRACKING__%26MKM_RID%3D__BPNUMBER__%26MKM_MID%3D__DELIVERNAME__%26cid%3D__CID____SEGMENTCODE__%26bpid%3D__BPNUMBER__%26iosparam%3Dsamsungestore%25253A%25252F%25252Fgototab%252523tab%25253D4%252523subtabid%25253DComputing_Offers%252523offerCID%25253DearlyAccess%252523segmentName%25253DholidayReserve%252523utm_source%25253Dsamsung%252523utm_medium%25253Demail%252523utm_campaign%25253Dholiday_deals_t3_11172020%252523marsLinkCategory%25253D__MARSTRACKING__%252523MKM_RID%25253D__BPNUMBER__%252523MKM_MID%25253D__DELIVERNAME__%252523cid%25253D__CID____SEGMENTCODE__%252523bpid%25253D__BPNUMBER__&utm_source=samsung&utm_medium=email&utm_campaign=holiday_deals_t3_11172020&marsLinkCategory=__MARSTRACKING__&MKM_RID=__BPNUMBER__&MKM_MID=__DELIVERNAME__&cid=__CID____SEGMENTCODE__&bpid=__BPNUMBER__&apn=com.samsung.ecomm&al=samsungestore%3A%2F%2Fgototab%23tab%3D4%23subtabid%3DComputing_Offers%23offerCID%3DearlyAccess%23segmentName%3DholidayReserve%23utm_source%3Dsamsung%23utm_medium%3Demail%23utm_campaign%3Dholiday_deals_t3_11172020%23marsLinkCategory%3D__MARSTRACKING__%23MKM_RID%3D__BPNUMBER__%23MKM_MID%3D__DELIVERNAME__%23cid%3D__CID____SEGMENTCODE__%23bpid%3D__BPNUMBER__&afl=https%3A%2F%2Fwww.samsung.com%2Fus%2Fshop%2Fall-deals%2Flaptop-and-computer-deals%2F%3FofferCID%3DearlyAccess%26utm_source%3Dsamsung%26utm_medium%3Demail%26utm_campaign%3Dholiday_deals_t3_11172020%26marsLinkCategory%3D__MARSTRACKING__%26MKM_RID%3D__BPNUMBER__%26MKM_MID%3D__DELIVERNAME__%26cid%3D__CID____SEGMENTCODE__%26bpid%3D__BPNUMBER__&isi=1274679179&ibi=com.samsung.ShopSamsung&ius=samsungestore&ifl=https%3A%2F%2Fwww.samsung.com%2Fus%2Fshop%2Fall-deals%2Flaptop-and-computer-deals%2F%3FofferCID%3DearlyAccess%26utm_source%3Dsamsung%26utm_medium%3Demail%26utm_campaign%3Dholiday_deals_t3_11172020%26marsLinkCategory%3D__MARSTRACKING__%26MKM_RID%3D__BPNUMBER__%26MKM_MID%3D__DELIVERNAME__%26cid%3D__CID____SEGMENTCODE__%26bpid%3D__BPNUMBER__&efr=1 | CO8: =CCModuleCopy!$I$13 -> NULL | CP8: =CCModuleCopy!$J$13 -> NULL | CQ8: =CCModuleCopy!$K$13 -> NULL | CR8: CC HA | CS8: =CCModuleCopy!$B$9 -> HA_HeadImage_Shop_HA_500xV.jpg | CT8: =CCModuleCopy!$C$9 -> Save up to 50% on everything you need to upgrade your home and home care | CU8: =CCModuleCopy!$D$9 -> NULL | CV8: =CCModuleCopy!$E$9 -> Get an additional 10% off when you buy 4 or more eligible kitchen appliances. Save even more with early Black Friday prices for select categories.α Plus, shop our time and cost-saving laundry and floor care products, and buy and try a Jet Stick Cordless Vacuum with our new 100-day, risk-free trial. | CW8: =CCModuleCopy!$F$9 -> Shop all | CX8: =CCModuleCopy!$G$9 -> https://www.samsung.com/us/shop/all-deals/home-appliance-and-smart-home-sales/ | CY8: =CCModuleCopy!$H$9 -> https://shopsamsung.page.link?link=https%3A%2F%2Fwww.samsung.com%2Fus%2Fshop%2Fall-deals%2Fhome-appliance-and-smart-home-sales%2F%3FofferCID%3DearlyAccess%26utm_source%3Dsamsung%26utm_medium%3Demail%26utm_campaign%3Dholiday_deals_t3_11172020%26marsLinkCategory%3D__MARSTRACKING__%26MKM_RID%3D__BPNUMBER__%26MKM_MID%3D__DELIVERNAME__%26cid%3D__CID____SEGMENTCODE__%26bpid%3D__BPNUMBER__%26iosparam%3Dsamsungestore%25253A%25252F%25252Fgototab%252523tab%25253D4%252523subtabid%25253DHome_Appliances_SmartHome_Offers%252523offerCID%25253DearlyAccess%252523segmentName%25253DholidayReserve%252523utm_source%25253Dsamsung%252523utm_medium%25253Demail%252523utm_campaign%25253Dholiday_deals_t3_11172020%252523marsLinkCategory%25253D__MARSTRACKING__%252523MKM_RID%25253D__BPNUMBER__%252523MKM_MID%25253D__DELIVERNAME__%252523cid%25253D__CID____SEGMENTCODE__%252523bpid%25253D__BPNUMBER__&utm_source=samsung&utm_medium=email&utm_campaign=holiday_deals_t3_11172020&marsLinkCategory=__MARSTRACKING__&MKM_RID=__BPNUMBER__&MKM_MID=__DELIVERNAME__&cid=__CID____SEGMENTCODE__&bpid=__BPNUMBER__&apn=com.samsung.ecomm&al=samsungestore%3A%2F%2Fgototab%23tab%3D4%23subtabid%3DHome_Appliances_SmartHome_Offers%23offerCID%3DearlyAccess%23segmentName%3DholidayReserve%23utm_source%3Dsamsung%23utm_medium%3Demail%23utm_campaign%3Dholiday_deals_t3_11172020%23marsLinkCategory%3D__MARSTRACKING__%23MKM_RID%3D__BPNUMBER__%23MKM_MID%3D__DELIVERNAME__%23cid%3D__CID____SEGMENTCODE__%23bpid%3D__BPNUMBER__&afl=https%3A%2F%2Fwww.samsung.com%2Fus%2Fshop%2Fall-deals%2Fhome-appliance-and-smart-home-sales%2F%3FofferCID%3DearlyAccess%26utm_source%3Dsamsung%26utm_medium%3Demail%26utm_campaign%3Dholiday_deals_t3_11172020%26marsLinkCategory%3D__MARSTRACKING__%26MKM_RID%3D__BPNUMBER__%26MKM_MID%3D__DELIVERNAME__%26cid%3D__CID____SEGMENTCODE__%26bpid%3D__BPNUMBER__&isi=1274679179&ibi=com.samsung.ShopSamsung&ius=samsungestore&ifl=https%3A%2F%2Fwww.samsung.com%2Fus%2Fshop%2Fall-deals%2Fhome-appliance-and-smart-home-sales%2F%3FofferCID%3DearlyAccess%26utm_source%3Dsamsung%26utm_medium%3Demail%26utm_campaign%3Dholiday_deals_t3_11172020%26marsLinkCategory%3D__MARSTRACKING__%26MKM_RID%3D__BPNUMBER__%26MKM_MID%3D__DELIVERNAME__%26cid%3D__CID____SEGMENTCODE__%26bpid%3D__BPNUMBER__&efr=1 | CZ8: =CCModuleCopy!$I$9 -> NULL | DA8: =CCModuleCopy!$J$9 -> NULL | DB8: =CCModuleCopy!$K$9 -> NULL | DC8: GIFT GUIDE | DD8: =MiscBanners!$H$4 -> Give-wonder-500xV.jpg | DE8: =MiscBanners!$I$4 -> The gift that keeps on giving | DF8: =MiscBanners!$J$4 -> NULL | DG8: =MiscBanners!$K$4 -> Discover even more exclusive offers on your favorite products and unlock the power of smart and savvy gifting. | DH8: =MiscBanners!$L$4 -> Shop now | DI8: =MiscBanners!$M$4 -> https://www.samsung.com/us/gift-ideas/ | DJ8: =MiscBanners!$N$4 -> https://shopsamsung.page.link?link=https%3A%2F%2Fwww.samsung.com%2Fus%2Fgift-ideas%2F%3FofferCID%3DearlyAccess%26utm_source%3Dsamsung%26utm_medium%3Demail%26utm_campaign%3Dholiday_deals_t3_11172020%26marsLinkCategory%3D__MARSTRACKING__%26MKM_RID%3D__BPNUMBER__%26MKM_MID%3D__DELIVERNAME__%26cid%3D__CID____SEGMENTCODE__%26bpid%3D__BPNUMBER__%26iosparam%3Dsamsungestore%25253A%25252F%25252Fopenwebview%252523url%25253Dhttps%25253A%25252F%25252Fwww.samsung.com%25252Fus%25252Fapp%25252Fgift-ideas%25252F%25253FofferCID%25253DearlyAccess%252526segmentName%25253DholidayReserve%252523utm_source%25253Dsamsung%252523utm_medium%25253Demail%252523utm_campaign%25253Dholiday_deals_t3_11172020%252523marsLinkCategory%25253D__MARSTRACKING__%252523MKM_RID%25253D__BPNUMBER__%252523MKM_MID%25253D__DELIVERNAME__%252523cid%25253D__CID____SEGMENTCODE__%252523bpid%25253D__BPNUMBER__&utm_source=samsung&utm_medium=email&utm_campaign=holiday_deals_t3_11172020&marsLinkCategory=__MARSTRACKING__&MKM_RID=__BPNUMBER__&MKM_MID=__DELIVERNAME__&cid=__CID____SEGMENTCODE__&bpid=__BPNUMBER__&apn=com.samsung.ecomm&al=samsungestore%3A%2F%2Fopenwebview%23url%3Dhttps%3A%2F%2Fwww.samsung.com%2Fus%2Fapp%2Fgift-ideas%2F%3FofferCID%3DearlyAccess%26segmentName%3DholidayReserve%23utm_source%3Dsamsung%23utm_medium%3Demail%23utm_campaign%3Dholiday_deals_t3_11172020%23marsLinkCategory%3D__MARSTRACKING__%23MKM_RID%3D__BPNUMBER__%23MKM_MID%3D__DELIVERNAME__%23cid%3D__CID____SEGMENTCODE__%23bpid%3D__BPNUMBER__&afl=https%3A%2F%2Fwww.samsung.com%2Fus%2Fgift-ideas%2F%3FofferCID%3DearlyAccess%26utm_source%3Dsamsung%26utm_medium%3Demail%26utm_campaign%3Dholiday_deals_t3_11172020%26marsLinkCategory%3D__MARSTRACKING__%26MKM_RID%3D__BPNUMBER__%26MKM_MID%3D__DELIVERNAME__%26cid%3D__CID____SEGMENTCODE__%26bpid%3D__BPNUMBER__&isi=1274679179&ibi=com.samsung.ShopSamsung&ius=samsungestore&ifl=https%3A%2F%2Fwww.samsung.com%2Fus%2Fgift-ideas%2F%3FofferCID%3DearlyAccess%26utm_source%3Dsamsung%26utm_medium%3Demail%26utm_campaign%3Dholiday_deals_t3_11172020%26marsLinkCategory%3D__MARSTRACKING__%26MKM_RID%3D__BPNUMBER__%26MKM_MID%3D__DELIVERNAME__%26cid%3D__CID____SEGMENTCODE__%26bpid%3D__BPNUMBER__&efr=1 | DK8: =MiscBanners!$O$4 -> NULL | DL8: =MiscBanners!$P$4 -> NULL | DM8: =MiscBanners!$Q$4 -> NULL | DN8: FOOTER | DY8: TC1 | DZ8: NULL | EA8: NULL | EB8: NULL | EC8: §18+ & 50 US/DC only. By 11/29/2020 11:59 PM EST, purchase a qualifying device on device installment plan, 2-year contract plan, lease or outright purchase at full retail price (“Qualifying Purchase”), & receive a Samsung Credit of $100 (“Gift”) instant credit from Samsung for use towards an eligible purchase including select wearables, tablets, PC’s and accessories when you purchase qualifying smartphone (“Qualifying Purchase”) before 01/15/21 at 11:59 PM EST. You must make a Qualifying Purchase on Samsung.com or the Shop Samsung App to receive an instant credit which may be applied instantly or deferred to a future eligible purchase. Gift valid for use on eligible purchases from 11/10/20- 01/15/21 or while supplies last, and is a one-time use certificate; when first used, any value not used is lost. Gift is non-transferrable and limited to 1 instant credit per registered customer. Samsung Credits are valid only at www.Samsung.com or in the App for use towards an eligible purchase. Void where prohibited or restricted by law. Additional restrictions apply. Offer subject to additional terms here. Samsung reserves the right to modify or discontinue offer at any time by posting notice on the app or website | ED8: NULL | EE8: https://www.samsung.com/us/ | EF8: 0 | EG8: NULL | EH8: NULL | EI8: NULL | EJ8: TC2 | EK8: NULL | EL8: NULL | EM8: NULL | EN8: †18+ & 50 US/DC only. By 11/29/2020 11:59 PM EST, purchase a qualifying device on device installment plan, 2-year contract plan, lease or outright purchase at full retail price (“Qualifying Purchase”), & receive a Samsung Credit of $30 (“Gift”) instant credit from Samsung for use towards an eligible purchase including select wearables, tablets, PC’s and accessories when you purchase qualifying smartphone (“Qualifying Purchase”) before 01/15/21 at 11:59 PM EST. You must make a Qualifying Purchase on Samsung.com or the Shop Samsung App to receive an instant credit which may be applied instantly or deferred to a future eligible purchase. Gift valid for use on eligible purchases from 11/10/20- 01/15/21 or while supplies last, and is a one-time use certificate; when first used, any value not used is lost. Gift is non-transferrable and limited to 1 instant credit per registered customer. Samsung Credits are valid only at www.Samsung.com or in the App for use towards an eligible purchase. Void where prohibited or restricted by law. Additional restrictions apply. Offer subject to additional terms here. Samsung reserves the right to modify or discontinue offer at any time by posting notice on the app or website | EO8: NULL | EP8: https://www.samsung.com/us/ | EQ8: 0 | ER8: NULL | ES8: NULL | ET8: NULL | EU8: TC3 | EV8: NULL | EW8: NULL | EX8: NULL | EY8: ‡18+ & 50 US/DC only. Between 10/26/20 at 12:01 AM EST and 11/18/20 at 11:59 PM EST (“Registration Period”), register for the Samsung Holiday instant credit promotion to receive a $20 instant credit from Samsung for use towards an eligible purchase including select wearables, tablets, PC’s and accessories when you purchase qualifying smartphone (“Qualifying Purchase”) before 01/15/21 at 11:59 PM EST. You must make a Qualifying Purchase on Samsung.com or the Shop Samsung App to receive an instant credit which may be applied instantly or deferred to a future eligible purchase. Gift valid for use on eligible purchases from 11/10/20- 01/15/21 or while supplies last, and is a one-time use certificate; when first used, any value not used is lost. Gift is non-transferrable and limited to 1 instant credit per registered customer. Samsung Credits are valid only at www.Samsung.com or in the App for use towards an eligible purchase. Void where prohibited or restricted by law. Additional restrictions apply. Offer subject to additional terms here. Samsung reserves the right to modify or discontinue offer at any time by posting notice on the app or website. | EZ8: NULL | FA8: https://www.samsung.com/us/ | FB8: 0 | FC8: NULL | FD8: NULL | FE8: NULL | FF8: TC4 | FG8: NULL | FH8: NULL | FI8: NULL | FJ8: αMust be an eligible legal resident of the 50 US/DC & at least 18 years old to participate. Purchase at least 4 eligible Samsung Home Appliance products in the same transaction (Refrigerators, Ranges, Countertop Microwaves, Over-the-Range Microwave Ovens, Dishwashers, Wall Ovens, Cooktops, or Range Hoods) (“a Qualifying Purchase”) between 11/04/20 and 12/02/20 on Samsung.com, and you will receive a 10% instant rebate off of the pre-tax purchase price of your Qualifying Purchase (“Gift”). Purchases must include products from different product categories. If more than 4 eligible products are purchased, the additional products purchased are eligible for the discount as long as the eligibility requirements listed above and below are met. Eligible categories are Refrigerators, Ranges, Countertop Microwaves, Over-the-Range Microwave Ovens, Dishwashers, Wall Ovens, Cooktops, or Range Hoods. Samsung Chef Collection, Washers, Dryers, Pedestals, Vacuums, Air Purifiers, AirDresser, Wine Cooler, and all accessories are not eligible. Quantities limited; offer valid while supplies last. One claim per household. This Offer and instant rebate Gift redemption applies to Samsung.com only. Offer cannot be combined with other Samsung offers, rebates, programs, or promotions unless otherwise stated. | FK8: NULL | FL8: 0 | FM8: 0 | FN8: NULL | FO8: NULL | FP8: NULL
A9: CC | B9: MB_WEAR | C9: X | D9: X | E9: Reserver | G9: Cyber Monday is on. | H9: Act fast to save on showstopping gifts while supplies last. | I9: EPP Banner | J9: NULL | K9: NULL | L9: NULL | M9: NULL | N9: NULL | O9: NULL | P9: NULL | Q9: NULL | R9: NULL | S9: Hero & Countdown Timer Image | T9: ='Dynamic Banners'!$L$4 -> Cyber-monday-1.png | U9: ='Dynamic Banners'!$M$4 -> The clock is ticking away for Cyber Monday | V9: NULL | W9: ='Dynamic Banners'!$N$4 -> Shop amazing offers on showstopping products while supplies last. | X9: NULL | Y9: =[1]MiscBanners!$B$4 -> https://www.samsung.com/us/shop/all-deals/ | Z9: =[1]MiscBanners!$C$4 -> https://shopsamsung.page.link?link=https%3A%2F%2Fwww.samsung.com%2Fus%2Fshop%2Fall-deals%2F%3FofferCID%3DearlyAccess%26utm_source%3Dsamsung%26utm_medium%3Demail%26utm_campaign%3Dholiday_deals_t3_11172020%26marsLinkCategory%3D__MARSTRACKING__%26MKM_RID%3D__BPNUMBER__%26MKM_MID%3D__DELIVERNAME__%26cid%3D__CID____SEGMENTCODE__%26bpid%3D__BPNUMBER__%26iosparam%3Dsamsungestore%25253A%25252F%25252Fgototab%252523tab%25253D4%252523offerCID%25253DearlyAccess%252523utm_source%25253Dsamsung%252523utm_medium%25253Demail%252523utm_campaign%25253Dholiday_deals_t3_11172020%252523marsLinkCategory%25253D__MARSTRACKING__%252523MKM_RID%25253D__BPNUMBER__%252523MKM_MID%25253D__DELIVERNAME__%252523cid%25253D__CID____SEGMENTCODE__%252523bpid%25253D__BPNUMBER__&utm_source=samsung&utm_medium=email&utm_campaign=holiday_deals_t3_11172020&marsLinkCategory=__MARSTRACKING__&MKM_RID=__BPNUMBER__&MKM_MID=__DELIVERNAME__&cid=__CID____SEGMENTCODE__&bpid=__BPNUMBER__&apn=com.samsung.ecomm&al=samsungestore%3A%2F%2Fgototab%23tab%3D4%23offerCID%3DearlyAccess%23utm_source%3Dsamsung%23utm_medium%3Demail%23utm_campaign%3Dholiday_deals_t3_11172020%23marsLinkCategory%3D__MARSTRACKING__%23MKM_RID%3D__BPNUMBER__%23MKM_MID%3D__DELIVERNAME__%23cid%3D__CID____SEGMENTCODE__%23bpid%3D__BPNUMBER__&afl=https%3A%2F%2Fwww.samsung.com%2Fus%2Fshop%2Fall-deals%2F%3FofferCID%3DearlyAccess%26utm_source%3Dsamsung%26utm_medium%3Demail%26utm_campaign%3Dholiday_deals_t3_11172020%26marsLinkCategory%3D__MARSTRACKING__%26MKM_RID%3D__BPNUMBER__%26MKM_MID%3D__DELIVERNAME__%26cid%3D__CID____SEGMENTCODE__%26bpid%3D__BPNUMBER__&isi=1274679179&ibi=com.samsung.ShopSamsung&ius=samsungestore&ifl=https%3A%2F%2Fwww.samsung.com%2Fus%2Fshop%2Fall-deals%2F%3FofferCID%3DearlyAccess%26utm_source%3Dsamsung%26utm_medium%3Demail%26utm_campaign%3Dholiday_deals_t3_11172020%26marsLinkCategory%3D__MARSTRACKING__%26MKM_RID%3D__BPNUMBER__%26MKM_MID%3D__DELIVERNAME__%26cid%3D__CID____SEGMENTCODE__%26bpid%3D__BPNUMBER__&efr=1 | AA9: NULL | AB9: NULL | AC9: NULL | AD9: Hero & Countdown Timer Copy | AE9: NULL | AF9: NULL | AG9: While supplies last. | AH9: Today is your day to shop some of our greatest offers of the year. | AI9: NULL | AJ9: =[1]MiscBanners!$B$4 -> https://www.samsung.com/us/shop/all-deals/ | AK9: =[1]MiscBanners!$C$4 -> https://shopsamsung.page.link?link=https%3A%2F%2Fwww.samsung.com%2Fus%2Fshop%2Fall-deals%2F%3FofferCID%3DearlyAccess%26utm_source%3Dsamsung%26utm_medium%3Demail%26utm_campaign%3Dholiday_deals_t3_11172020%26marsLinkCategory%3D__MARSTRACKING__%26MKM_RID%3D__BPNUMBER__%26MKM_MID%3D__DELIVERNAME__%26cid%3D__CID____SEGMENTCODE__%26bpid%3D__BPNUMBER__%26iosparam%3Dsamsungestore%25253A%25252F%25252Fgototab%252523tab%25253D4%252523offerCID%25253DearlyAccess%252523utm_source%25253Dsamsung%252523utm_medium%25253Demail%252523utm_campaign%25253Dholiday_deals_t3_11172020%252523marsLinkCategory%25253D__MARSTRACKING__%252523MKM_RID%25253D__BPNUMBER__%252523MKM_MID%25253D__DELIVERNAME__%252523cid%25253D__CID____SEGMENTCODE__%252523bpid%25253D__BPNUMBER__&utm_source=samsung&utm_medium=email&utm_campaign=holiday_deals_t3_11172020&marsLinkCategory=__MARSTRACKING__&MKM_RID=__BPNUMBER__&MKM_MID=__DELIVERNAME__&cid=__CID____SEGMENTCODE__&bpid=__BPNUMBER__&apn=com.samsung.ecomm&al=samsungestore%3A%2F%2Fgototab%23tab%3D4%23offerCID%3DearlyAccess%23utm_source%3Dsamsung%23utm_medium%3Demail%23utm_campaign%3Dholiday_deals_t3_11172020%23marsLinkCategory%3D__MARSTRACKING__%23MKM_RID%3D__BPNUMBER__%23MKM_MID%3D__DELIVERNAME__%23cid%3D__CID____SEGMENTCODE__%23bpid%3D__BPNUMBER__&afl=https%3A%2F%2Fwww.samsung.com%2Fus%2Fshop%2Fall-deals%2F%3FofferCID%3DearlyAccess%26utm_source%3Dsamsung%26utm_medium%3Demail%26utm_campaign%3Dholiday_deals_t3_11172020%26marsLinkCategory%3D__MARSTRACKING__%26MKM_RID%3D__BPNUMBER__%26MKM_MID%3D__DELIVERNAME__%26cid%3D__CID____SEGMENTCODE__%26bpid%3D__BPNUMBER__&isi=1274679179&ibi=com.samsung.ShopSamsung&ius=samsungestore&ifl=https%3A%2F%2Fwww.samsung.com%2Fus%2Fshop%2Fall-deals%2F%3FofferCID%3DearlyAccess%26utm_source%3Dsamsung%26utm_medium%3Demail%26utm_campaign%3Dholiday_deals_t3_11172020%26marsLinkCategory%3D__MARSTRACKING__%26MKM_RID%3D__BPNUMBER__%26MKM_MID%3D__DELIVERNAME__%26cid%3D__CID____SEGMENTCODE__%26bpid%3D__BPNUMBER__&efr=1 | AL9: NULL | AM9: NULL | AN9: NULL | AO9: CC WEAR | AP9: =CCModuleCopy!$B$11 -> ME_HeadImage_Wearables_500xV.jpg | AQ9: =CCModuleCopy!$C$11 -> Get up to $100 off select watches and earbuds | AR9: =CCModuleCopy!$D$11 -> NULL | AS9: =CCModuleCopy!$E$11 -> Treat yourself (or someone special) to Galaxy Watch3 Titanium, Watch3, Buds+ and more, suited for every lifestyle and every holiday shopping budget. Plus, now you can flex your fashion muscles with the new Samsung Design Studio. Create a Galaxy Watch as unique as you, today. | AT9: =CCModuleCopy!$F$11 -> Shop all | AU9: =CCModuleCopy!$G$11 -> https://www.samsung.com/us/shop/all-deals/watches-audio-accessories-deals/ | AV9: =CCModuleCopy!$H$11 -> https://shopsamsung.page.link?link=https%3A%2F%2Fwww.samsung.com%2Fus%2Fshop%2Fall-deals%2Ftablets-wearables-cell-phone-accessories-deals%2F%3FofferCID%3DearlyAccess%26utm_source%3Dsamsung%26utm_medium%3Demail%26utm_campaign%3Dholiday_deals_t3_11172020%26marsLinkCategory%3D__MARSTRACKING__%26MKM_RID%3D__BPNUMBER__%26MKM_MID%3D__DELIVERNAME__%26cid%3D__CID____SEGMENTCODE__%26bpid%3D__BPNUMBER__&utm_source=samsung&utm_medium=email&utm_campaign=holiday_deals_t3_11172020&marsLinkCategory=__MARSTRACKING__&MKM_RID=__BPNUMBER__&MKM_MID=__DELIVERNAME__&cid=__CID____SEGMENTCODE__&bpid=__BPNUMBER__&apn=com.samsung.ecomm&al=samsungestore%3A%2F%2Fgototab%23tab%3D4%23subtabid%3DTablets_Wearables_Offers%23offerCID%3DearlyAccess%23utm_source%3Dsamsung%23utm_medium%3Demail%23utm_campaign%3Dholiday_deals_t3_11172020%23marsLinkCategory%3D__MARSTRACKING__%23MKM_RID%3D__BPNUMBER__%23MKM_MID%3D__DELIVERNAME__%23cid%3D__CID____SEGMENTCODE__%23bpid%3D__BPNUMBER__&afl=https%3A%2F%2Fwww.samsung.com%2Fus%2Fshop%2Fall-deals%2Ftablets-wearables-cell-phone-accessories-deals%2F%3FofferCID%3DearlyAccess%26utm_source%3Dsamsung%26utm_medium%3Demail%26utm_campaign%3Dholiday_deals_t3_11172020%26marsLinkCategory%3D__MARSTRACKING__%26MKM_RID%3D__BPNUMBER__%26MKM_MID%3D__DELIVERNAME__%26cid%3D__CID____SEGMENTCODE__%26bpid%3D__BPNUMBER__&efr=1 | AW9: =CCModuleCopy!$I$11 -> NULL | AX9: =CCModuleCopy!$J$11 -> NULL | AY9: =CCModuleCopy!$K$11 -> NULL | AZ9: CC MOBILE RESERVER | BA9: =CCModuleCopy!$B$3 -> IM_HeadImage_Shop_Phones_500xV.jpg | BB9: =CCModuleCopy!$C$3 -> Save up to $1000 instantly on the latest and greatest Galaxy smartphones | BC9: =CCModuleCopy!$D$3 -> NULL | BD9: =CCModuleCopy!$E$3 -> Whether you're here to improve the way you work or power up the way you play, shop some of our best offers of the year on Galaxy Note20 5G, S20 FE 5G, Z Fold2 5G and select A series devices. Plus, get $50 or more instant credit toward accessories with any smartphone purchase to complete your Galaxy Ecosystem.‡† | BE9: =CCModuleCopy!$F$3 -> Shop all | BF9: =CCModuleCopy!$G$3 -> https://www.samsung.com/us/shop/all-deals/cell-phone-deals/ | BG9: =CCModuleCopy!$H$3 -> https://shopsamsung.page.link?link=https%3A%2F%2Fwww.samsung.com%2Fus%2Fshop%2Fall-deals%2Fcell-phone-deals%2F%3FofferCID%3DearlyAccess%26utm_source%3Dsamsung%26utm_medium%3Demail%26utm_campaign%3Dholiday_deals_t3_11172020%26marsLinkCategory%3D__MARSTRACKING__%26MKM_RID%3D__BPNUMBER__%26MKM_MID%3D__DELIVERNAME__%26cid%3D__CID____SEGMENTCODE__%26bpid%3D__BPNUMBER__&utm_source=samsung&utm_medium=email&utm_campaign=holiday_deals_t3_11172020&marsLinkCategory=__MARSTRACKING__&MKM_RID=__BPNUMBER__&MKM_MID=__DELIVERNAME__&cid=__CID____SEGMENTCODE__&bpid=__BPNUMBER__&apn=com.samsung.ecomm&al=samsungestore%3A%2F%2Fgototab%23tab%3D4%23subtabid%3DMobile_Offers%23offerCID%3DearlyAccess%23segmentName%3DholidayReserve%23utm_source%3Dsamsung%23utm_medium%3Demail%23utm_campaign%3Dholiday_deals_t3_11172020%23marsLinkCategory%3D__MARSTRACKING__%23MKM_RID%3D__BPNUMBER__%23MKM_MID%3D__DELIVERNAME__%23cid%3D__CID____SEGMENTCODE__%23bpid%3D__BPNUMBER__&afl=https%3A%2F%2Fwww.samsung.com%2Fus%2Fshop%2Fall-deals%2Fcell-phone-deals%2F%3FofferCID%3DearlyAccess%26utm_source%3Dsamsung%26utm_medium%3Demail%26utm_campaign%3Dholiday_deals_t3_11172020%26marsLinkCategory%3D__MARSTRACKING__%26MKM_RID%3D__BPNUMBER__%26MKM_MID%3D__DELIVERNAME__%26cid%3D__CID____SEGMENTCODE__%26bpid%3D__BPNUMBER__&efr=1 | BH9: =CCModuleCopy!$I$3 -> NULL | BI9: =CCModuleCopy!$J$3 -> NULL | BJ9: =CCModuleCopy!$K$3 -> NULL | BK9: CC TV & ACCESSORIES | BL9: =CCModuleCopy!$B$7 -> HE_HeadImage_Shop_TVs_500xV.jpg | BM9: =CCModuleCopy!$C$7 -> Get up to $3000 off select 8K, 4K and Lifestyle TVs | BN9: =CCModuleCopy!$D$7 -> NULL | BO9: =CCModuleCopy!$E$7 -> Discover the mind-blowing, true-to-live resolution of QLED technology and create your ultimate home theater today. Save up to $3000 on 8K TVs, up to $1800 on select 4K TVs, up to $1300 on Lifestyle TVs and up to $400 on select soundbars and more. Plus, buy and try select Lifestyle TVs, soundbars and The Premiere Projector with our new 100-day, risk-free trial. | BP9: =CCModuleCopy!$F$7 -> Shop all | BQ9: =CCModuleCopy!$G$7 -> https://www.samsung.com/us/shop/all-deals/tv-and-home-theater-deals/ | BR9: =CCModuleCopy!$H$7 -> https://shopsamsung.page.link?link=https%3A%2F%2Fwww.samsung.com%2Fus%2Fshop%2Fall-deals%2Ftv-and-home-theater-deals%2F%3FofferCID%3DearlyAccess%26utm_source%3Dsamsung%26utm_medium%3Demail%26utm_campaign%3Dholiday_deals_t3_11172020%26marsLinkCategory%3D__MARSTRACKING__%26MKM_RID%3D__BPNUMBER__%26MKM_MID%3D__DELIVERNAME__%26cid%3D__CID____SEGMENTCODE__%26bpid%3D__BPNUMBER__%26iosparam%3Dsamsungestore%25253A%25252F%25252Fgototab%252523tab%25253D4%252523subtabid%25253DTV_Home_Theater_Offers%252523offerCID%25253DearlyAccess%252523segmentName%25253DholidayReserve%252523utm_source%25253Dsamsung%252523utm_medium%25253Demail%252523utm_campaign%25253Dholiday_deals_t3_11172020%252523marsLinkCategory%25253D__MARSTRACKING__%252523MKM_RID%25253D__BPNUMBER__%252523MKM_MID%25253D__DELIVERNAME__%252523cid%25253D__CID____SEGMENTCODE__%252523bpid%25253D__BPNUMBER__&utm_source=samsung&utm_medium=email&utm_campaign=holiday_deals_t3_11172020&marsLinkCategory=__MARSTRACKING__&MKM_RID=__BPNUMBER__&MKM_MID=__DELIVERNAME__&cid=__CID____SEGMENTCODE__&bpid=__BPNUMBER__&apn=com.samsung.ecomm&al=samsungestore%3A%2F%2Fgototab%23tab%3D4%23subtabid%3DTV_Home_Theater_Offers%23offerCID%3DearlyAccess%23segmentName%3DholidayReserve%23utm_source%3Dsamsung%23utm_medium%3Demail%23utm_campaign%3Dholiday_deals_t3_11172020%23marsLinkCategory%3D__MARSTRACKING__%23MKM_RID%3D__BPNUMBER__%23MKM_MID%3D__DELIVERNAME__%23cid%3D__CID____SEGMENTCODE__%23bpid%3D__BPNUMBER__&afl=https%3A%2F%2Fwww.samsung.com%2Fus%2Fshop%2Fall-deals%2Ftv-and-home-theater-deals%2F%3FofferCID%3DearlyAccess%26utm_source%3Dsamsung%26utm_medium%3Demail%26utm_campaign%3Dholiday_deals_t3_11172020%26marsLinkCategory%3D__MARSTRACKING__%26MKM_RID%3D__BPNUMBER__%26MKM_MID%3D__DELIVERNAME__%26cid%3D__CID____SEGMENTCODE__%26bpid%3D__BPNUMBER__&isi=1274679179&ibi=com.samsung.ShopSamsung&ius=samsungestore&ifl=https%3A%2F%2Fwww.samsung.com%2Fus%2Fshop%2Fall-deals%2Ftv-and-home-theater-deals%2F%3FofferCID%3DearlyAccess%26utm_source%3Dsamsung%26utm_medium%3Demail%26utm_campaign%3Dholiday_deals_t3_11172020%26marsLinkCategory%3D__MARSTRACKING__%26MKM_RID%3D__BPNUMBER__%26MKM_MID%3D__DELIVERNAME__%26cid%3D__CID____SEGMENTCODE__%26bpid%3D__BPNUMBER__&efr=1 | BS9: =CCModuleCopy!$I$7 -> NULL | BT9: =CCModuleCopy!$J$7 -> NULL | BU9: =CCModuleCopy!$K$7 -> NULL | BV9: CC TABLET | BW9: =CCModuleCopy!$B$15 -> Tablet-HeadImage-500xV.jpg | BX9: =CCModuleCopy!$C$15 -> Save up to $150 on select tablets | BY9: =CCModuleCopy!$D$15 -> NULL | BZ9: =CCModuleCopy!$E$15 -> Empower how you create, learn, game and more with our powerful line of tablets. Shop offers on must-have products from the new Galaxy Tab S7+ to the Galaxy Tab S6 Lite. | CA9: =CCModuleCopy!$F$15 -> Shop all | CB9: =CCModuleCopy!$G$15 -> https://www.samsung.com/us/shop/all-deals/tablets-laptops-computers-deals/ | CC9: =CCModuleCopy!$H$15 -> https://shopsamsung.page.link?link=https%3A%2F%2Fwww.samsung.com%2Fus%2Fshop%2Fall-deals%2Ftablets-laptops-computers-deals%2F%3FofferCID%3DearlyAccess%26utm_source%3Dsamsung%26utm_medium%3Demail%26utm_campaign%3Dholiday_deals_rev_11182020%26marsLinkCategory%3D__MARSTRACKING__%26MKM_RID%3D__BPNUMBER__%26MKM_MID%3D__DELIVERNAME__%26cid%3D__CID____SEGMENTCODE__%26bpid%3D__BPNUMBER__%26iosparam%3Dsamsungestore%25253A%25252F%25252Fgototab%252523tab%25253D4%252523subtabid%25253DTablets%252526Computing_Offers%252523offerCID%25253DearlyAccess%252523utm_source%25253Dsamsung%252523utm_medium%25253Demail%252523utm_campaign%25253Dholiday_deals_rev_11182020%252523marsLinkCategory%25253D__MARSTRACKING__%252523MKM_RID%25253D__BPNUMBER__%252523MKM_MID%25253D__DELIVERNAME__%252523cid%25253D__CID____SEGMENTCODE__%252523bpid%25253D__BPNUMBER__&utm_source=samsung&utm_medium=email&utm_campaign=holiday_deals_rev_11182020&marsLinkCategory=__MARSTRACKING__&MKM_RID=__BPNUMBER__&MKM_MID=__DELIVERNAME__&cid=__CID____SEGMENTCODE__&bpid=__BPNUMBER__&apn=com.samsung.ecomm&al=samsungestore%3A%2F%2Fgototab%23tab%3D4%23subtabid%3DTablets%26Computing_Offers%23offerCID%3DearlyAccess%23utm_source%3Dsamsung%23utm_medium%3Demail%23utm_campaign%3Dholiday_deals_rev_11182020%23marsLinkCategory%3D__MARSTRACKING__%23MKM_RID%3D__BPNUMBER__%23MKM_MID%3D__DELIVERNAME__%23cid%3D__CID____SEGMENTCODE__%23bpid%3D__BPNUMBER__&afl=https%3A%2F%2Fwww.samsung.com%2Fus%2Fshop%2Fall-deals%2Ftablets-laptops-computers-deals%2F%3FofferCID%3DearlyAccess%26utm_source%3Dsamsung%26utm_medium%3Demail%26utm_campaign%3Dholiday_deals_rev_11182020%26marsLinkCategory%3D__MARSTRACKING__%26MKM_RID%3D__BPNUMBER__%26MKM_MID%3D__DELIVERNAME__%26cid%3D__CID____SEGMENTCODE__%26bpid%3D__BPNUMBER__&isi=1274679179&ibi=com.samsung.ShopSamsung&ius=samsungestore&ifl=https%3A%2F%2Fwww.samsung.com%2Fus%2Fshop%2Fall-deals%2Ftablets-laptops-computers-deals%2F%3FofferCID%3DearlyAccess%26utm_source%3Dsamsung%26utm_medium%3Demail%26utm_campaign%3Dholiday_deals_rev_11182020%26marsLinkCategory%3D__MARSTRACKING__%26MKM_RID%3D__BPNUMBER__%26MKM_MID%3D__DELIVERNAME__%26cid%3D__CID____SEGMENTCODE__%26bpid%3D__BPNUMBER__&efr=1 | CD9: =CCModuleCopy!$I$15 -> NULL | CE9: =CCModuleCopy!$J$15 -> NULL | CF9: =CCModuleCopy!$K$15 -> NULL | CG9: CC COMPUTER | CH9: =CCModuleCopy!$B$13 -> CE_HeadImage_Computing_500xV.jpg | CI9: =CCModuleCopy!$C$13 -> Get up to 60% off memory cards, SSD, monitors and more | CJ9: =CCModuleCopy!$D$13 -> NULL | CK9: =CCModuleCopy!$E$13 -> Expand the way you play, store and create and get up to 30% off monitors, up to 60% off memory cards, up to 35% off SSD and more. Work and game smarter, not harder with these must-have computing offers. | CL9: =CCModuleCopy!$F$13 -> Shop all | CM9: =CCModuleCopy!$G$13 -> https://www.samsung.com/us/shop/all-deals/tablets-laptops-computers-deals/ | CN9: =CCModuleCopy!$H$13 -> https://shopsamsung.page.link?link=https%3A%2F%2Fwww.samsung.com%2Fus%2Fshop%2Fall-deals%2Flaptop-and-computer-deals%2F%3FofferCID%3DearlyAccess%26utm_source%3Dsamsung%26utm_medium%3Demail%26utm_campaign%3Dholiday_deals_t3_11172020%26marsLinkCategory%3D__MARSTRACKING__%26MKM_RID%3D__BPNUMBER__%26MKM_MID%3D__DELIVERNAME__%26cid%3D__CID____SEGMENTCODE__%26bpid%3D__BPNUMBER__%26iosparam%3Dsamsungestore%25253A%25252F%25252Fgototab%252523tab%25253D4%252523subtabid%25253DComputing_Offers%252523offerCID%25253DearlyAccess%252523segmentName%25253DholidayReserve%252523utm_source%25253Dsamsung%252523utm_medium%25253Demail%252523utm_campaign%25253Dholiday_deals_t3_11172020%252523marsLinkCategory%25253D__MARSTRACKING__%252523MKM_RID%25253D__BPNUMBER__%252523MKM_MID%25253D__DELIVERNAME__%252523cid%25253D__CID____SEGMENTCODE__%252523bpid%25253D__BPNUMBER__&utm_source=samsung&utm_medium=email&utm_campaign=holiday_deals_t3_11172020&marsLinkCategory=__MARSTRACKING__&MKM_RID=__BPNUMBER__&MKM_MID=__DELIVERNAME__&cid=__CID____SEGMENTCODE__&bpid=__BPNUMBER__&apn=com.samsung.ecomm&al=samsungestore%3A%2F%2Fgototab%23tab%3D4%23subtabid%3DComputing_Offers%23offerCID%3DearlyAccess%23segmentName%3DholidayReserve%23utm_source%3Dsamsung%23utm_medium%3Demail%23utm_campaign%3Dholiday_deals_t3_11172020%23marsLinkCategory%3D__MARSTRACKING__%23MKM_RID%3D__BPNUMBER__%23MKM_MID%3D__DELIVERNAME__%23cid%3D__CID____SEGMENTCODE__%23bpid%3D__BPNUMBER__&afl=https%3A%2F%2Fwww.samsung.com%2Fus%2Fshop%2Fall-deals%2Flaptop-and-computer-deals%2F%3FofferCID%3DearlyAccess%26utm_source%3Dsamsung%26utm_medium%3Demail%26utm_campaign%3Dholiday_deals_t3_11172020%26marsLinkCategory%3D__MARSTRACKING__%26MKM_RID%3D__BPNUMBER__%26MKM_MID%3D__DELIVERNAME__%26cid%3D__CID____SEGMENTCODE__%26bpid%3D__BPNUMBER__&isi=1274679179&ibi=com.samsung.ShopSamsung&ius=samsungestore&ifl=https%3A%2F%2Fwww.samsung.com%2Fus%2Fshop%2Fall-deals%2Flaptop-and-computer-deals%2F%3FofferCID%3DearlyAccess%26utm_source%3Dsamsung%26utm_medium%3Demail%26utm_campaign%3Dholiday_deals_t3_11172020%26marsLinkCategory%3D__MARSTRACKING__%26MKM_RID%3D__BPNUMBER__%26MKM_MID%3D__DELIVERNAME__%26cid%3D__CID____SEGMENTCODE__%26bpid%3D__BPNUMBER__&efr=1 | CO9: =CCModuleCopy!$I$13 -> NULL | CP9: =CCModuleCopy!$J$13 -> NULL | CQ9: =CCModuleCopy!$K$13 -> NULL | CR9: CC HA | CS9: =CCModuleCopy!$B$9 -> HA_HeadImage_Shop_HA_500xV.jpg | CT9: =CCModuleCopy!$C$9 -> Save up to 50% on everything you need to upgrade your home and home care | CU9: =CCModuleCopy!$D$9 -> NULL | CV9: =CCModuleCopy!$E$9 -> Get an additional 10% off when you buy 4 or more eligible kitchen appliances. Save even more with early Black Friday prices for select categories.α Plus, shop our time and cost-saving laundry and floor care products, and buy and try a Jet Stick Cordless Vacuum with our new 100-day, risk-free trial. | CW9: =CCModuleCopy!$F$9 -> Shop all | CX9: =CCModuleCopy!$G$9 -> https://www.samsung.com/us/shop/all-deals/home-appliance-and-smart-home-sales/ | CY9: =CCModuleCopy!$H$9 -> https://shopsamsung.page.link?link=https%3A%2F%2Fwww.samsung.com%2Fus%2Fshop%2Fall-deals%2Fhome-appliance-and-smart-home-sales%2F%3FofferCID%3DearlyAccess%26utm_source%3Dsamsung%26utm_medium%3Demail%26utm_campaign%3Dholiday_deals_t3_11172020%26marsLinkCategory%3D__MARSTRACKING__%26MKM_RID%3D__BPNUMBER__%26MKM_MID%3D__DELIVERNAME__%26cid%3D__CID____SEGMENTCODE__%26bpid%3D__BPNUMBER__%26iosparam%3Dsamsungestore%25253A%25252F%25252Fgototab%252523tab%25253D4%252523subtabid%25253DHome_Appliances_SmartHome_Offers%252523offerCID%25253DearlyAccess%252523segmentName%25253DholidayReserve%252523utm_source%25253Dsamsung%252523utm_medium%25253Demail%252523utm_campaign%25253Dholiday_deals_t3_11172020%252523marsLinkCategory%25253D__MARSTRACKING__%252523MKM_RID%25253D__BPNUMBER__%252523MKM_MID%25253D__DELIVERNAME__%252523cid%25253D__CID____SEGMENTCODE__%252523bpid%25253D__BPNUMBER__&utm_source=samsung&utm_medium=email&utm_campaign=holiday_deals_t3_11172020&marsLinkCategory=__MARSTRACKING__&MKM_RID=__BPNUMBER__&MKM_MID=__DELIVERNAME__&cid=__CID____SEGMENTCODE__&bpid=__BPNUMBER__&apn=com.samsung.ecomm&al=samsungestore%3A%2F%2Fgototab%23tab%3D4%23subtabid%3DHome_Appliances_SmartHome_Offers%23offerCID%3DearlyAccess%23segmentName%3DholidayReserve%23utm_source%3Dsamsung%23utm_medium%3Demail%23utm_campaign%3Dholiday_deals_t3_11172020%23marsLinkCategory%3D__MARSTRACKING__%23MKM_RID%3D__BPNUMBER__%23MKM_MID%3D__DELIVERNAME__%23cid%3D__CID____SEGMENTCODE__%23bpid%3D__BPNUMBER__&afl=https%3A%2F%2Fwww.samsung.com%2Fus%2Fshop%2Fall-deals%2Fhome-appliance-and-smart-home-sales%2F%3FofferCID%3DearlyAccess%26utm_source%3Dsamsung%26utm_medium%3Demail%26utm_campaign%3Dholiday_deals_t3_11172020%26marsLinkCategory%3D__MARSTRACKING__%26MKM_RID%3D__BPNUMBER__%26MKM_MID%3D__DELIVERNAME__%26cid%3D__CID____SEGMENTCODE__%26bpid%3D__BPNUMBER__&isi=1274679179&ibi=com.samsung.ShopSamsung&ius=samsungestore&ifl=https%3A%2F%2Fwww.samsung.com%2Fus%2Fshop%2Fall-deals%2Fhome-appliance-and-smart-home-sales%2F%3FofferCID%3DearlyAccess%26utm_source%3Dsamsung%26utm_medium%3Demail%26utm_campaign%3Dholiday_deals_t3_11172020%26marsLinkCategory%3D__MARSTRACKING__%26MKM_RID%3D__BPNUMBER__%26MKM_MID%3D__DELIVERNAME__%26cid%3D__CID____SEGMENTCODE__%26bpid%3D__BPNUMBER__&efr=1 | CZ9: =CCModuleCopy!$I$9 -> NULL | DA9: =CCModuleCopy!$J$9 -> NULL | DB9: =CCModuleCopy!$K$9 -> NULL | DC9: GIFT GUIDE | DD9: =MiscBanners!$H$4 -> Give-wonder-500xV.jpg | DE9: =MiscBanners!$I$4 -> The gift that keeps on giving | DF9: =MiscBanners!$J$4 -> NULL | DG9: =MiscBanners!$K$4 -> Discover even more exclusive offers on your favorite products and unlock the power of smart and savvy gifting. | DH9: =MiscBanners!$L$4 -> Shop now | DI9: =MiscBanners!$M$4 -> https://www.samsung.com/us/gift-ideas/ | DJ9: =MiscBanners!$N$4 -> https://shopsamsung.page.link?link=https%3A%2F%2Fwww.samsung.com%2Fus%2Fgift-ideas%2F%3FofferCID%3DearlyAccess%26utm_source%3Dsamsung%26utm_medium%3Demail%26utm_campaign%3Dholiday_deals_t3_11172020%26marsLinkCategory%3D__MARSTRACKING__%26MKM_RID%3D__BPNUMBER__%26MKM_MID%3D__DELIVERNAME__%26cid%3D__CID____SEGMENTCODE__%26bpid%3D__BPNUMBER__%26iosparam%3Dsamsungestore%25253A%25252F%25252Fopenwebview%252523url%25253Dhttps%25253A%25252F%25252Fwww.samsung.com%25252Fus%25252Fapp%25252Fgift-ideas%25252F%25253FofferCID%25253DearlyAccess%252526segmentName%25253DholidayReserve%252523utm_source%25253Dsamsung%252523utm_medium%25253Demail%252523utm_campaign%25253Dholiday_deals_t3_11172020%252523marsLinkCategory%25253D__MARSTRACKING__%252523MKM_RID%25253D__BPNUMBER__%252523MKM_MID%25253D__DELIVERNAME__%252523cid%25253D__CID____SEGMENTCODE__%252523bpid%25253D__BPNUMBER__&utm_source=samsung&utm_medium=email&utm_campaign=holiday_deals_t3_11172020&marsLinkCategory=__MARSTRACKING__&MKM_RID=__BPNUMBER__&MKM_MID=__DELIVERNAME__&cid=__CID____SEGMENTCODE__&bpid=__BPNUMBER__&apn=com.samsung.ecomm&al=samsungestore%3A%2F%2Fopenwebview%23url%3Dhttps%3A%2F%2Fwww.samsung.com%2Fus%2Fapp%2Fgift-ideas%2F%3FofferCID%3DearlyAccess%26segmentName%3DholidayReserve%23utm_source%3Dsamsung%23utm_medium%3Demail%23utm_campaign%3Dholiday_deals_t3_11172020%23marsLinkCategory%3D__MARSTRACKING__%23MKM_RID%3D__BPNUMBER__%23MKM_MID%3D__DELIVERNAME__%23cid%3D__CID____SEGMENTCODE__%23bpid%3D__BPNUMBER__&afl=https%3A%2F%2Fwww.samsung.com%2Fus%2Fgift-ideas%2F%3FofferCID%3DearlyAccess%26utm_source%3Dsamsung%26utm_medium%3Demail%26utm_campaign%3Dholiday_deals_t3_11172020%26marsLinkCategory%3D__MARSTRACKING__%26MKM_RID%3D__BPNUMBER__%26MKM_MID%3D__DELIVERNAME__%26cid%3D__CID____SEGMENTCODE__%26bpid%3D__BPNUMBER__&isi=1274679179&ibi=com.samsung.ShopSamsung&ius=samsungestore&ifl=https%3A%2F%2Fwww.samsung.com%2Fus%2Fgift-ideas%2F%3FofferCID%3DearlyAccess%26utm_source%3Dsamsung%26utm_medium%3Demail%26utm_campaign%3Dholiday_deals_t3_11172020%26marsLinkCategory%3D__MARSTRACKING__%26MKM_RID%3D__BPNUMBER__%26MKM_MID%3D__DELIVERNAME__%26cid%3D__CID____SEGMENTCODE__%26bpid%3D__BPNUMBER__&efr=1 | DK9: =MiscBanners!$O$4 -> NULL | DL9: =MiscBanners!$P$4 -> NULL | DM9: =MiscBanners!$Q$4 -> NULL | DN9: FOOTER | DY9: TC1 | DZ9: NULL | EA9: NULL | EB9: NULL | EC9: §18+ & 50 US/DC only. By 11/29/2020 11:59 PM EST, purchase a qualifying device on device installment plan, 2-year contract plan, lease or outright purchase at full retail price (“Qualifying Purchase”), & receive a Samsung Credit of $100 (“Gift”) instant credit from Samsung for use towards an eligible purchase including select wearables, tablets, PC’s and accessories when you purchase qualifying smartphone (“Qualifying Purchase”) before 01/15/21 at 11:59 PM EST. You must make a Qualifying Purchase on Samsung.com or the Shop Samsung App to receive an instant credit which may be applied instantly or deferred to a future eligible purchase. Gift valid for use on eligible purchases from 11/10/20- 01/15/21 or while supplies last, and is a one-time use certificate; when first used, any value not used is lost. Gift is non-transferrable and limited to 1 instant credit per registered customer. Samsung Credits are valid only at www.Samsung.com or in the App for use towards an eligible purchase. Void where prohibited or restricted by law. Additional restrictions apply. Offer subject to additional terms here. Samsung reserves the right to modify or discontinue offer at any time by posting notice on the app or website | ED9: NULL | EE9: https://www.samsung.com/us/ | EF9: 0 | EG9: NULL | EH9: NULL | EI9: NULL | EJ9: TC2 | EK9: NULL | EL9: NULL | EM9: NULL | EN9: †18+ & 50 US/DC only. By 11/29/2020 11:59 PM EST, purchase a qualifying device on device installment plan, 2-year contract plan, lease or outright purchase at full retail price (“Qualifying Purchase”), & receive a Samsung Credit of $30 (“Gift”) instant credit from Samsung for use towards an eligible purchase including select wearables, tablets, PC’s and accessories when you purchase qualifying smartphone (“Qualifying Purchase”) before 01/15/21 at 11:59 PM EST. You must make a Qualifying Purchase on Samsung.com or the Shop Samsung App to receive an instant credit which may be applied instantly or deferred to a future eligible purchase. Gift valid for use on eligible purchases from 11/10/20- 01/15/21 or while supplies last, and is a one-time use certificate; when first used, any value not used is lost. Gift is non-transferrable and limited to 1 instant credit per registered customer. Samsung Credits are valid only at www.Samsung.com or in the App for use towards an eligible purchase. Void where prohibited or restricted by law. Additional restrictions apply. Offer subject to additional terms here. Samsung reserves the right to modify or discontinue offer at any time by posting notice on the app or website | EO9: NULL | EP9: https://www.samsung.com/us/ | EQ9: 0 | ER9: NULL | ES9: NULL | ET9: NULL | EU9: TC3 | EV9: NULL | EW9: NULL | EX9: NULL | EY9: ‡18+ & 50 US/DC only. Between 10/26/20 at 12:01 AM EST and 11/18/20 at 11:59 PM EST (“Registration Period”), register for the Samsung Holiday instant credit promotion to receive a $20 instant credit from Samsung for use towards an eligible purchase including select wearables, tablets, PC’s and accessories when you purchase qualifying smartphone (“Qualifying Purchase”) before 01/15/21 at 11:59 PM EST. You must make a Qualifying Purchase on Samsung.com or the Shop Samsung App to receive an instant credit which may be applied instantly or deferred to a future eligible purchase. Gift valid for use on eligible purchases from 11/10/20- 01/15/21 or while supplies last, and is a one-time use certificate; when first used, any value not used is lost. Gift is non-transferrable and limited to 1 instant credit per registered customer. Samsung Credits are valid only at www.Samsung.com or in the App for use towards an eligible purchase. Void where prohibited or restricted by law. Additional restrictions apply. Offer subject to additional terms here. Samsung reserves the right to modify or discontinue offer at any time by posting notice on the app or website. | EZ9: NULL | FA9: https://www.samsung.com/us/ | FB9: 0 | FC9: NULL | FD9: NULL | FE9: NULL | FF9: TC4 | FG9: NULL | FH9: NULL | FI9: NULL | FJ9: αMust be an eligible legal resident of the 50 US/DC & at least 18 years old to participate. Purchase at least 4 eligible Samsung Home Appliance products in the same transaction (Refrigerators, Ranges, Countertop Microwaves, Over-the-Range Microwave Ovens, Dishwashers, Wall Ovens, Cooktops, or Range Hoods) (“a Qualifying Purchase”) between 11/04/20 and 12/02/20 on Samsung.com, and you will receive a 10% instant rebate off of the pre-tax purchase price of your Qualifying Purchase (“Gift”). Purchases must include products from different product categories. If more than 4 eligible products are purchased, the additional products purchased are eligible for the discount as long as the eligibility requirements listed above and below are met. Eligible categories are Refrigerators, Ranges, Countertop Microwaves, Over-the-Range Microwave Ovens, Dishwashers, Wall Ovens, Cooktops, or Range Hoods. Samsung Chef Collection, Washers, Dryers, Pedestals, Vacuums, Air Purifiers, AirDresser, Wine Cooler, and all accessories are not eligible. Quantities limited; offer valid while supplies last. One claim per household. This Offer and instant rebate Gift redemption applies to Samsung.com only. Offer cannot be combined with other Samsung offers, rebates, programs, or promotions unless otherwise stated. | FK9: NULL | FL9: 0 | FM9: 0 | FN9: NULL | FO9: NULL | FP9: NULL
A10: CC | B10: CE_COMPUTER | C10: X | D10: X | E10: Reserver | G10: Cyber Monday is on. | H10: Act fast to save on showstopping gifts while supplies last. | I10: EPP Banner | J10: NULL | K10: NULL | L10: NULL | M10: NULL | N10: NULL | O10: NULL | P10: NULL | Q10: NULL | R10: NULL | S10: Hero & Countdown Timer Image | T10: ='Dynamic Banners'!$L$4 -> Cyber-monday-1.png | U10: ='Dynamic Banners'!$M$4 -> The clock is ticking away for Cyber Monday | V10: NULL | W10: ='Dynamic Banners'!$N$4 -> Shop amazing offers on showstopping products while supplies last. | X10: NULL | Y10: =[1]MiscBanners!$B$4 -> https://www.samsung.com/us/shop/all-deals/ | Z10: =[1]MiscBanners!$C$4 -> https://shopsamsung.page.link?link=https%3A%2F%2Fwww.samsung.com%2Fus%2Fshop%2Fall-deals%2F%3FofferCID%3DearlyAccess%26utm_source%3Dsamsung%26utm_medium%3Demail%26utm_campaign%3Dholiday_deals_t3_11172020%26marsLinkCategory%3D__MARSTRACKING__%26MKM_RID%3D__BPNUMBER__%26MKM_MID%3D__DELIVERNAME__%26cid%3D__CID____SEGMENTCODE__%26bpid%3D__BPNUMBER__%26iosparam%3Dsamsungestore%25253A%25252F%25252Fgototab%252523tab%25253D4%252523offerCID%25253DearlyAccess%252523utm_source%25253Dsamsung%252523utm_medium%25253Demail%252523utm_campaign%25253Dholiday_deals_t3_11172020%252523marsLinkCategory%25253D__MARSTRACKING__%252523MKM_RID%25253D__BPNUMBER__%252523MKM_MID%25253D__DELIVERNAME__%252523cid%25253D__CID____SEGMENTCODE__%252523bpid%25253D__BPNUMBER__&utm_source=samsung&utm_medium=email&utm_campaign=holiday_deals_t3_11172020&marsLinkCategory=__MARSTRACKING__&MKM_RID=__BPNUMBER__&MKM_MID=__DELIVERNAME__&cid=__CID____SEGMENTCODE__&bpid=__BPNUMBER__&apn=com.samsung.ecomm&al=samsungestore%3A%2F%2Fgototab%23tab%3D4%23offerCID%3DearlyAccess%23utm_source%3Dsamsung%23utm_medium%3Demail%23utm_campaign%3Dholiday_deals_t3_11172020%23marsLinkCategory%3D__MARSTRACKING__%23MKM_RID%3D__BPNUMBER__%23MKM_MID%3D__DELIVERNAME__%23cid%3D__CID____SEGMENTCODE__%23bpid%3D__BPNUMBER__&afl=https%3A%2F%2Fwww.samsung.com%2Fus%2Fshop%2Fall-deals%2F%3FofferCID%3DearlyAccess%26utm_source%3Dsamsung%26utm_medium%3Demail%26utm_campaign%3Dholiday_deals_t3_11172020%26marsLinkCategory%3D__MARSTRACKING__%26MKM_RID%3D__BPNUMBER__%26MKM_MID%3D__DELIVERNAME__%26cid%3D__CID____SEGMENTCODE__%26bpid%3D__BPNUMBER__&isi=1274679179&ibi=com.samsung.ShopSamsung&ius=samsungestore&ifl=https%3A%2F%2Fwww.samsung.com%2Fus%2Fshop%2Fall-deals%2F%3FofferCID%3DearlyAccess%26utm_source%3Dsamsung%26utm_medium%3Demail%26utm_campaign%3Dholiday_deals_t3_11172020%26marsLinkCategory%3D__MARSTRACKING__%26MKM_RID%3D__BPNUMBER__%26MKM_MID%3D__DELIVERNAME__%26cid%3D__CID____SEGMENTCODE__%26bpid%3D__BPNUMBER__&efr=1 | AA10: NULL | AB10: NULL | AC10: NULL | AD10: Hero & Countdown Timer Copy | AE10: NULL | AF10: NULL | AG10: While supplies last. | AH10: Today is your day to shop some of our greatest offers of the year. | AI10: NULL | AJ10: =[1]MiscBanners!$B$4 -> https://www.samsung.com/us/shop/all-deals/ | AK10: =[1]MiscBanners!$C$4 -> https://shopsamsung.page.link?link=https%3A%2F%2Fwww.samsung.com%2Fus%2Fshop%2Fall-deals%2F%3FofferCID%3DearlyAccess%26utm_source%3Dsamsung%26utm_medium%3Demail%26utm_campaign%3Dholiday_deals_t3_11172020%26marsLinkCategory%3D__MARSTRACKING__%26MKM_RID%3D__BPNUMBER__%26MKM_MID%3D__DELIVERNAME__%26cid%3D__CID____SEGMENTCODE__%26bpid%3D__BPNUMBER__%26iosparam%3Dsamsungestore%25253A%25252F%25252Fgototab%252523tab%25253D4%252523offerCID%25253DearlyAccess%252523utm_source%25253Dsamsung%252523utm_medium%25253Demail%252523utm_campaign%25253Dholiday_deals_t3_11172020%252523marsLinkCategory%25253D__MARSTRACKING__%252523MKM_RID%25253D__BPNUMBER__%252523MKM_MID%25253D__DELIVERNAME__%252523cid%25253D__CID____SEGMENTCODE__%252523bpid%25253D__BPNUMBER__&utm_source=samsung&utm_medium=email&utm_campaign=holiday_deals_t3_11172020&marsLinkCategory=__MARSTRACKING__&MKM_RID=__BPNUMBER__&MKM_MID=__DELIVERNAME__&cid=__CID____SEGMENTCODE__&bpid=__BPNUMBER__&apn=com.samsung.ecomm&al=samsungestore%3A%2F%2Fgototab%23tab%3D4%23offerCID%3DearlyAccess%23utm_source%3Dsamsung%23utm_medium%3Demail%23utm_campaign%3Dholiday_deals_t3_11172020%23marsLinkCategory%3D__MARSTRACKING__%23MKM_RID%3D__BPNUMBER__%23MKM_MID%3D__DELIVERNAME__%23cid%3D__CID____SEGMENTCODE__%23bpid%3D__BPNUMBER__&afl=https%3A%2F%2Fwww.samsung.com%2Fus%2Fshop%2Fall-deals%2F%3FofferCID%3DearlyAccess%26utm_source%3Dsamsung%26utm_medium%3Demail%26utm_campaign%3Dholiday_deals_t3_11172020%26marsLinkCategory%3D__MARSTRACKING__%26MKM_RID%3D__BPNUMBER__%26MKM_MID%3D__DELIVERNAME__%26cid%3D__CID____SEGMENTCODE__%26bpid%3D__BPNUMBER__&isi=1274679179&ibi=com.samsung.ShopSamsung&ius=samsungestore&ifl=https%3A%2F%2Fwww.samsung.com%2Fus%2Fshop%2Fall-deals%2F%3FofferCID%3DearlyAccess%26utm_source%3Dsamsung%26utm_medium%3Demail%26utm_campaign%3Dholiday_deals_t3_11172020%26marsLinkCategory%3D__MARSTRACKING__%26MKM_RID%3D__BPNUMBER__%26MKM_MID%3D__DELIVERNAME__%26cid%3D__CID____SEGMENTCODE__%26bpid%3D__BPNUMBER__&efr=1 | AL10: NULL | AM10: NULL | AN10: NULL | AO10: CC COMPUTER | AP10: =CCModuleCopy!$B$13 -> CE_HeadImage_Computing_500xV.jpg | AQ10: =CCModuleCopy!$C$13 -> Get up to 60% off memory cards, SSD, monitors and more | AR10: =CCModuleCopy!$D$13 -> NULL | AS10: =CCModuleCopy!$E$13 -> Expand the way you play, store and create and get up to 30% off monitors, up to 60% off memory cards, up to 35% off SSD and more. Work and game smarter, not harder with these must-have computing offers. | AT10: =CCModuleCopy!$F$13 -> Shop all | AU10: =CCModuleCopy!$G$13 -> https://www.samsung.com/us/shop/all-deals/tablets-laptops-computers-deals/ | AV10: =CCModuleCopy!$H$13 -> https://shopsamsung.page.link?link=https%3A%2F%2Fwww.samsung.com%2Fus%2Fshop%2Fall-deals%2Flaptop-and-computer-deals%2F%3FofferCID%3DearlyAccess%26utm_source%3Dsamsung%26utm_medium%3Demail%26utm_campaign%3Dholiday_deals_t3_11172020%26marsLinkCategory%3D__MARSTRACKING__%26MKM_RID%3D__BPNUMBER__%26MKM_MID%3D__DELIVERNAME__%26cid%3D__CID____SEGMENTCODE__%26bpid%3D__BPNUMBER__%26iosparam%3Dsamsungestore%25253A%25252F%25252Fgototab%252523tab%25253D4%252523subtabid%25253DComputing_Offers%252523offerCID%25253DearlyAccess%252523segmentName%25253DholidayReserve%252523utm_source%25253Dsamsung%252523utm_medium%25253Demail%252523utm_campaign%25253Dholiday_deals_t3_11172020%252523marsLinkCategory%25253D__MARSTRACKING__%252523MKM_RID%25253D__BPNUMBER__%252523MKM_MID%25253D__DELIVERNAME__%252523cid%25253D__CID____SEGMENTCODE__%252523bpid%25253D__BPNUMBER__&utm_source=samsung&utm_medium=email&utm_campaign=holiday_deals_t3_11172020&marsLinkCategory=__MARSTRACKING__&MKM_RID=__BPNUMBER__&MKM_MID=__DELIVERNAME__&cid=__CID____SEGMENTCODE__&bpid=__BPNUMBER__&apn=com.samsung.ecomm&al=samsungestore%3A%2F%2Fgototab%23tab%3D4%23subtabid%3DComputing_Offers%23offerCID%3DearlyAccess%23segmentName%3DholidayReserve%23utm_source%3Dsamsung%23utm_medium%3Demail%23utm_campaign%3Dholiday_deals_t3_11172020%23marsLinkCategory%3D__MARSTRACKING__%23MKM_RID%3D__BPNUMBER__%23MKM_MID%3D__DELIVERNAME__%23cid%3D__CID____SEGMENTCODE__%23bpid%3D__BPNUMBER__&afl=https%3A%2F%2Fwww.samsung.com%2Fus%2Fshop%2Fall-deals%2Flaptop-and-computer-deals%2F%3FofferCID%3DearlyAccess%26utm_source%3Dsamsung%26utm_medium%3Demail%26utm_campaign%3Dholiday_deals_t3_11172020%26marsLinkCategory%3D__MARSTRACKING__%26MKM_RID%3D__BPNUMBER__%26MKM_MID%3D__DELIVERNAME__%26cid%3D__CID____SEGMENTCODE__%26bpid%3D__BPNUMBER__&isi=1274679179&ibi=com.samsung.ShopSamsung&ius=samsungestore&ifl=https%3A%2F%2Fwww.samsung.com%2Fus%2Fshop%2Fall-deals%2Flaptop-and-computer-deals%2F%3FofferCID%3DearlyAccess%26utm_source%3Dsamsung%26utm_medium%3Demail%26utm_campaign%3Dholiday_deals_t3_11172020%26marsLinkCategory%3D__MARSTRACKING__%26MKM_RID%3D__BPNUMBER__%26MKM_MID%3D__DELIVERNAME__%26cid%3D__CID____SEGMENTCODE__%26bpid%3D__BPNUMBER__&efr=1 | AW10: =CCModuleCopy!$I$13 -> NULL | AX10: =CCModuleCopy!$J$13 -> NULL | AY10: =CCModuleCopy!$K$13 -> NULL | AZ10: CC MOBILE RESERVER | BA10: =CCModuleCopy!$B$3 -> IM_HeadImage_Shop_Phones_500xV.jpg | BB10: =CCModuleCopy!$C$3 -> Save up to $1000 instantly on the latest and greatest Galaxy smartphones | BC10: =CCModuleCopy!$D$3 -> NULL | BD10: =CCModuleCopy!$E$3 -> Whether you're here to improve the way you work or power up the way you play, shop some of our best offers of the year on Galaxy Note20 5G, S20 FE 5G, Z Fold2 5G and select A series devices. Plus, get $50 or more instant credit toward accessories with any smartphone purchase to complete your Galaxy Ecosystem.‡† | BE10: =CCModuleCopy!$F$3 -> Shop all | BF10: =CCModuleCopy!$G$3 -> https://www.samsung.com/us/shop/all-deals/cell-phone-deals/ | BG10: =CCModuleCopy!$H$3 -> https://shopsamsung.page.link?link=https%3A%2F%2Fwww.samsung.com%2Fus%2Fshop%2Fall-deals%2Fcell-phone-deals%2F%3FofferCID%3DearlyAccess%26utm_source%3Dsamsung%26utm_medium%3Demail%26utm_campaign%3Dholiday_deals_t3_11172020%26marsLinkCategory%3D__MARSTRACKING__%26MKM_RID%3D__BPNUMBER__%26MKM_MID%3D__DELIVERNAME__%26cid%3D__CID____SEGMENTCODE__%26bpid%3D__BPNUMBER__&utm_source=samsung&utm_medium=email&utm_campaign=holiday_deals_t3_11172020&marsLinkCategory=__MARSTRACKING__&MKM_RID=__BPNUMBER__&MKM_MID=__DELIVERNAME__&cid=__CID____SEGMENTCODE__&bpid=__BPNUMBER__&apn=com.samsung.ecomm&al=samsungestore%3A%2F%2Fgototab%23tab%3D4%23subtabid%3DMobile_Offers%23offerCID%3DearlyAccess%23segmentName%3DholidayReserve%23utm_source%3Dsamsung%23utm_medium%3Demail%23utm_campaign%3Dholiday_deals_t3_11172020%23marsLinkCategory%3D__MARSTRACKING__%23MKM_RID%3D__BPNUMBER__%23MKM_MID%3D__DELIVERNAME__%23cid%3D__CID____SEGMENTCODE__%23bpid%3D__BPNUMBER__&afl=https%3A%2F%2Fwww.samsung.com%2Fus%2Fshop%2Fall-deals%2Fcell-phone-deals%2F%3FofferCID%3DearlyAccess%26utm_source%3Dsamsung%26utm_medium%3Demail%26utm_campaign%3Dholiday_deals_t3_11172020%26marsLinkCategory%3D__MARSTRACKING__%26MKM_RID%3D__BPNUMBER__%26MKM_MID%3D__DELIVERNAME__%26cid%3D__CID____SEGMENTCODE__%26bpid%3D__BPNUMBER__&efr=1 | BH10: =CCModuleCopy!$I$3 -> NULL | BI10: =CCModuleCopy!$J$3 -> NULL | BJ10: =CCModuleCopy!$K$3 -> NULL | BK10: CC TV & ACCESSORIES | BL10: =CCModuleCopy!$B$7 -> HE_HeadImage_Shop_TVs_500xV.jpg | BM10: =CCModuleCopy!$C$7 -> Get up to $3000 off select 8K, 4K and Lifestyle TVs | BN10: =CCModuleCopy!$D$7 -> NULL | BO10: =CCModuleCopy!$E$7 -> Discover the mind-blowing, true-to-live resolution of QLED technology and create your ultimate home theater today. Save up to $3000 on 8K TVs, up to $1800 on select 4K TVs, up to $1300 on Lifestyle TVs and up to $400 on select soundbars and more. Plus, buy and try select Lifestyle TVs, soundbars and The Premiere Projector with our new 100-day, risk-free trial. | BP10: =CCModuleCopy!$F$7 -> Shop all | BQ10: =CCModuleCopy!$G$7 -> https://www.samsung.com/us/shop/all-deals/tv-and-home-theater-deals/ | BR10: =CCModuleCopy!$H$7 -> https://shopsamsung.page.link?link=https%3A%2F%2Fwww.samsung.com%2Fus%2Fshop%2Fall-deals%2Ftv-and-home-theater-deals%2F%3FofferCID%3DearlyAccess%26utm_source%3Dsamsung%26utm_medium%3Demail%26utm_campaign%3Dholiday_deals_t3_11172020%26marsLinkCategory%3D__MARSTRACKING__%26MKM_RID%3D__BPNUMBER__%26MKM_MID%3D__DELIVERNAME__%26cid%3D__CID____SEGMENTCODE__%26bpid%3D__BPNUMBER__%26iosparam%3Dsamsungestore%25253A%25252F%25252Fgototab%252523tab%25253D4%252523subtabid%25253DTV_Home_Theater_Offers%252523offerCID%25253DearlyAccess%252523segmentName%25253DholidayReserve%252523utm_source%25253Dsamsung%252523utm_medium%25253Demail%252523utm_campaign%25253Dholiday_deals_t3_11172020%252523marsLinkCategory%25253D__MARSTRACKING__%252523MKM_RID%25253D__BPNUMBER__%252523MKM_MID%25253D__DELIVERNAME__%252523cid%25253D__CID____SEGMENTCODE__%252523bpid%25253D__BPNUMBER__&utm_source=samsung&utm_medium=email&utm_campaign=holiday_deals_t3_11172020&marsLinkCategory=__MARSTRACKING__&MKM_RID=__BPNUMBER__&MKM_MID=__DELIVERNAME__&cid=__CID____SEGMENTCODE__&bpid=__BPNUMBER__&apn=com.samsung.ecomm&al=samsungestore%3A%2F%2Fgototab%23tab%3D4%23subtabid%3DTV_Home_Theater_Offers%23offerCID%3DearlyAccess%23segmentName%3DholidayReserve%23utm_source%3Dsamsung%23utm_medium%3Demail%23utm_campaign%3Dholiday_deals_t3_11172020%23marsLinkCategory%3D__MARSTRACKING__%23MKM_RID%3D__BPNUMBER__%23MKM_MID%3D__DELIVERNAME__%23cid%3D__CID____SEGMENTCODE__%23bpid%3D__BPNUMBER__&afl=https%3A%2F%2Fwww.samsung.com%2Fus%2Fshop%2Fall-deals%2Ftv-and-home-theater-deals%2F%3FofferCID%3DearlyAccess%26utm_source%3Dsamsung%26utm_medium%3Demail%26utm_campaign%3Dholiday_deals_t3_11172020%26marsLinkCategory%3D__MARSTRACKING__%26MKM_RID%3D__BPNUMBER__%26MKM_MID%3D__DELIVERNAME__%26cid%3D__CID____SEGMENTCODE__%26bpid%3D__BPNUMBER__&isi=1274679179&ibi=com.samsung.ShopSamsung&ius=samsungestore&ifl=https%3A%2F%2Fwww.samsung.com%2Fus%2Fshop%2Fall-deals%2Ftv-and-home-theater-deals%2F%3FofferCID%3DearlyAccess%26utm_source%3Dsamsung%26utm_medium%3Demail%26utm_campaign%3Dholiday_deals_t3_11172020%26marsLinkCategory%3D__MARSTRACKING__%26MKM_RID%3D__BPNUMBER__%26MKM_MID%3D__DELIVERNAME__%26cid%3D__CID____SEGMENTCODE__%26bpid%3D__BPNUMBER__&efr=1 | BS10: =CCModuleCopy!$I$7 -> NULL | BT10: =CCModuleCopy!$J$7 -> NULL | BU10: =CCModuleCopy!$K$7 -> NULL | BV10: CC TABLET | BW10: =CCModuleCopy!$B$15 -> Tablet-HeadImage-500xV.jpg | BX10: =CCModuleCopy!$C$15 -> Save up to $150 on select tablets | BY10: =CCModuleCopy!$D$15 -> NULL | BZ10: =CCModuleCopy!$E$15 -> Empower how you create, learn, game and more with our powerful line of tablets. Shop offers on must-have products from the new Galaxy Tab S7+ to the Galaxy Tab S6 Lite. | CA10: =CCModuleCopy!$F$15 -> Shop all | CB10: =CCModuleCopy!$G$15 -> https://www.samsung.com/us/shop/all-deals/tablets-laptops-computers-deals/ | CC10: =CCModuleCopy!$H$15 -> https://shopsamsung.page.link?link=https%3A%2F%2Fwww.samsung.com%2Fus%2Fshop%2Fall-deals%2Ftablets-laptops-computers-deals%2F%3FofferCID%3DearlyAccess%26utm_source%3Dsamsung%26utm_medium%3Demail%26utm_campaign%3Dholiday_deals_rev_11182020%26marsLinkCategory%3D__MARSTRACKING__%26MKM_RID%3D__BPNUMBER__%26MKM_MID%3D__DELIVERNAME__%26cid%3D__CID____SEGMENTCODE__%26bpid%3D__BPNUMBER__%26iosparam%3Dsamsungestore%25253A%25252F%25252Fgototab%252523tab%25253D4%252523subtabid%25253DTablets%252526Computing_Offers%252523offerCID%25253DearlyAccess%252523utm_source%25253Dsamsung%252523utm_medium%25253Demail%252523utm_campaign%25253Dholiday_deals_rev_11182020%252523marsLinkCategory%25253D__MARSTRACKING__%252523MKM_RID%25253D__BPNUMBER__%252523MKM_MID%25253D__DELIVERNAME__%252523cid%25253D__CID____SEGMENTCODE__%252523bpid%25253D__BPNUMBER__&utm_source=samsung&utm_medium=email&utm_campaign=holiday_deals_rev_11182020&marsLinkCategory=__MARSTRACKING__&MKM_RID=__BPNUMBER__&MKM_MID=__DELIVERNAME__&cid=__CID____SEGMENTCODE__&bpid=__BPNUMBER__&apn=com.samsung.ecomm&al=samsungestore%3A%2F%2Fgototab%23tab%3D4%23subtabid%3DTablets%26Computing_Offers%23offerCID%3DearlyAccess%23utm_source%3Dsamsung%23utm_medium%3Demail%23utm_campaign%3Dholiday_deals_rev_11182020%23marsLinkCategory%3D__MARSTRACKING__%23MKM_RID%3D__BPNUMBER__%23MKM_MID%3D__DELIVERNAME__%23cid%3D__CID____SEGMENTCODE__%23bpid%3D__BPNUMBER__&afl=https%3A%2F%2Fwww.samsung.com%2Fus%2Fshop%2Fall-deals%2Ftablets-laptops-computers-deals%2F%3FofferCID%3DearlyAccess%26utm_source%3Dsamsung%26utm_medium%3Demail%26utm_campaign%3Dholiday_deals_rev_11182020%26marsLinkCategory%3D__MARSTRACKING__%26MKM_RID%3D__BPNUMBER__%26MKM_MID%3D__DELIVERNAME__%26cid%3D__CID____SEGMENTCODE__%26bpid%3D__BPNUMBER__&isi=1274679179&ibi=com.samsung.ShopSamsung&ius=samsungestore&ifl=https%3A%2F%2Fwww.samsung.com%2Fus%2Fshop%2Fall-deals%2Ftablets-laptops-computers-deals%2F%3FofferCID%3DearlyAccess%26utm_source%3Dsamsung%26utm_medium%3Demail%26utm_campaign%3Dholiday_deals_rev_11182020%26marsLinkCategory%3D__MARSTRACKING__%26MKM_RID%3D__BPNUMBER__%26MKM_MID%3D__DELIVERNAME__%26cid%3D__CID____SEGMENTCODE__%26bpid%3D__BPNUMBER__&efr=1 | CD10: =CCModuleCopy!$I$15 -> NULL | CE10: =CCModuleCopy!$J$15 -> NULL | CF10: =CCModuleCopy!$K$15 -> NULL | CG10: CC WEAR | CH10: =CCModuleCopy!$B$11 -> ME_HeadImage_Wearables_500xV.jpg | CI10: =CCModuleCopy!$C$11 -> Get up to $100 off select watches and earbuds | CJ10: =CCModuleCopy!$D$11 -> NULL | CK10: =CCModuleCopy!$E$11 -> Treat yourself (or someone special) to Galaxy Watch3 Titanium, Watch3, Buds+ and more, suited for every lifestyle and every holiday shopping budget. Plus, now you can flex your fashion muscles with the new Samsung Design Studio. Create a Galaxy Watch as unique as you, today. | CL10: =CCModuleCopy!$F$11 -> Shop all | CM10: =CCModuleCopy!$G$11 -> https://www.samsung.com/us/shop/all-deals/watches-audio-accessories-deals/ | CN10: =CCModuleCopy!$H$11 -> https://shopsamsung.page.link?link=https%3A%2F%2Fwww.samsung.com%2Fus%2Fshop%2Fall-deals%2Ftablets-wearables-cell-phone-accessories-deals%2F%3FofferCID%3DearlyAccess%26utm_source%3Dsamsung%26utm_medium%3Demail%26utm_campaign%3Dholiday_deals_t3_11172020%26marsLinkCategory%3D__MARSTRACKING__%26MKM_RID%3D__BPNUMBER__%26MKM_MID%3D__DELIVERNAME__%26cid%3D__CID____SEGMENTCODE__%26bpid%3D__BPNUMBER__&utm_source=samsung&utm_medium=email&utm_campaign=holiday_deals_t3_11172020&marsLinkCategory=__MARSTRACKING__&MKM_RID=__BPNUMBER__&MKM_MID=__DELIVERNAME__&cid=__CID____SEGMENTCODE__&bpid=__BPNUMBER__&apn=com.samsung.ecomm&al=samsungestore%3A%2F%2Fgototab%23tab%3D4%23subtabid%3DTablets_Wearables_Offers%23offerCID%3DearlyAccess%23utm_source%3Dsamsung%23utm_medium%3Demail%23utm_campaign%3Dholiday_deals_t3_11172020%23marsLinkCategory%3D__MARSTRACKING__%23MKM_RID%3D__BPNUMBER__%23MKM_MID%3D__DELIVERNAME__%23cid%3D__CID____SEGMENTCODE__%23bpid%3D__BPNUMBER__&afl=https%3A%2F%2Fwww.samsung.com%2Fus%2Fshop%2Fall-deals%2Ftablets-wearables-cell-phone-accessories-deals%2F%3FofferCID%3DearlyAccess%26utm_source%3Dsamsung%26utm_medium%3Demail%26utm_campaign%3Dholiday_deals_t3_11172020%26marsLinkCategory%3D__MARSTRACKING__%26MKM_RID%3D__BPNUMBER__%26MKM_MID%3D__DELIVERNAME__%26cid%3D__CID____SEGMENTCODE__%26bpid%3D__BPNUMBER__&efr=1 | CO10: =CCModuleCopy!$I$11 -> NULL | CP10: =CCModuleCopy!$J$11 -> NULL | CQ10: =CCModuleCopy!$K$11 -> NULL | CR10: CC HA | CS10: =CCModuleCopy!$B$9 -> HA_HeadImage_Shop_HA_500xV.jpg | CT10: =CCModuleCopy!$C$9 -> Save up to 50% on everything you need to upgrade your home and home care | CU10: =CCModuleCopy!$D$9 -> NULL | CV10: =CCModuleCopy!$E$9 -> Get an additional 10% off when you buy 4 or more eligible kitchen appliances. Save even more with early Black Friday prices for select categories.α Plus, shop our time and cost-saving laundry and floor care products, and buy and try a Jet Stick Cordless Vacuum with our new 100-day, risk-free trial. | CW10: =CCModuleCopy!$F$9 -> Shop all | CX10: =CCModuleCopy!$G$9 -> https://www.samsung.com/us/shop/all-deals/home-appliance-and-smart-home-sales/ | CY10: =CCModuleCopy!$H$9 -> https://shopsamsung.page.link?link=https%3A%2F%2Fwww.samsung.com%2Fus%2Fshop%2Fall-deals%2Fhome-appliance-and-smart-home-sales%2F%3FofferCID%3DearlyAccess%26utm_source%3Dsamsung%26utm_medium%3Demail%26utm_campaign%3Dholiday_deals_t3_11172020%26marsLinkCategory%3D__MARSTRACKING__%26MKM_RID%3D__BPNUMBER__%26MKM_MID%3D__DELIVERNAME__%26cid%3D__CID____SEGMENTCODE__%26bpid%3D__BPNUMBER__%26iosparam%3Dsamsungestore%25253A%25252F%25252Fgototab%252523tab%25253D4%252523subtabid%25253DHome_Appliances_SmartHome_Offers%252523offerCID%25253DearlyAccess%252523segmentName%25253DholidayReserve%252523utm_source%25253Dsamsung%252523utm_medium%25253Demail%252523utm_campaign%25253Dholiday_deals_t3_11172020%252523marsLinkCategory%25253D__MARSTRACKING__%252523MKM_RID%25253D__BPNUMBER__%252523MKM_MID%25253D__DELIVERNAME__%252523cid%25253D__CID____SEGMENTCODE__%252523bpid%25253D__BPNUMBER__&utm_source=samsung&utm_medium=email&utm_campaign=holiday_deals_t3_11172020&marsLinkCategory=__MARSTRACKING__&MKM_RID=__BPNUMBER__&MKM_MID=__DELIVERNAME__&cid=__CID____SEGMENTCODE__&bpid=__BPNUMBER__&apn=com.samsung.ecomm&al=samsungestore%3A%2F%2Fgototab%23tab%3D4%23subtabid%3DHome_Appliances_SmartHome_Offers%23offerCID%3DearlyAccess%23segmentName%3DholidayReserve%23utm_source%3Dsamsung%23utm_medium%3Demail%23utm_campaign%3Dholiday_deals_t3_11172020%23marsLinkCategory%3D__MARSTRACKING__%23MKM_RID%3D__BPNUMBER__%23MKM_MID%3D__DELIVERNAME__%23cid%3D__CID____SEGMENTCODE__%23bpid%3D__BPNUMBER__&afl=https%3A%2F%2Fwww.samsung.com%2Fus%2Fshop%2Fall-deals%2Fhome-appliance-and-smart-home-sales%2F%3FofferCID%3DearlyAccess%26utm_source%3Dsamsung%26utm_medium%3Demail%26utm_campaign%3Dholiday_deals_t3_11172020%26marsLinkCategory%3D__MARSTRACKING__%26MKM_RID%3D__BPNUMBER__%26MKM_MID%3D__DELIVERNAME__%26cid%3D__CID____SEGMENTCODE__%26bpid%3D__BPNUMBER__&isi=1274679179&ibi=com.samsung.ShopSamsung&ius=samsungestore&ifl=https%3A%2F%2Fwww.samsung.com%2Fus%2Fshop%2Fall-deals%2Fhome-appliance-and-smart-home-sales%2F%3FofferCID%3DearlyAccess%26utm_source%3Dsamsung%26utm_medium%3Demail%26utm_campaign%3Dholiday_deals_t3_11172020%26marsLinkCategory%3D__MARSTRACKING__%26MKM_RID%3D__BPNUMBER__%26MKM_MID%3D__DELIVERNAME__%26cid%3D__CID____SEGMENTCODE__%26bpid%3D__BPNUMBER__&efr=1 | CZ10: =CCModuleCopy!$I$9 -> NULL | DA10: =CCModuleCopy!$J$9 -> NULL | DB10: =CCModuleCopy!$K$9 -> NULL | DC10: GIFT GUIDE | DD10: =MiscBanners!$H$4 -> Give-wonder-500xV.jpg | DE10: =MiscBanners!$I$4 -> The gift that keeps on giving | DF10: =MiscBanners!$J$4 -> NULL | DG10: =MiscBanners!$K$4 -> Discover even more exclusive offers on your favorite products and unlock the power of smart and savvy gifting. | DH10: =MiscBanners!$L$4 -> Shop now | DI10: =MiscBanners!$M$4 -> https://www.samsung.com/us/gift-ideas/ | DJ10: =MiscBanners!$N$4 -> https://shopsamsung.page.link?link=https%3A%2F%2Fwww.samsung.com%2Fus%2Fgift-ideas%2F%3FofferCID%3DearlyAccess%26utm_source%3Dsamsung%26utm_medium%3Demail%26utm_campaign%3Dholiday_deals_t3_11172020%26marsLinkCategory%3D__MARSTRACKING__%26MKM_RID%3D__BPNUMBER__%26MKM_MID%3D__DELIVERNAME__%26cid%3D__CID____SEGMENTCODE__%26bpid%3D__BPNUMBER__%26iosparam%3Dsamsungestore%25253A%25252F%25252Fopenwebview%252523url%25253Dhttps%25253A%25252F%25252Fwww.samsung.com%25252Fus%25252Fapp%25252Fgift-ideas%25252F%25253FofferCID%25253DearlyAccess%252526segmentName%25253DholidayReserve%252523utm_source%25253Dsamsung%252523utm_medium%25253Demail%252523utm_campaign%25253Dholiday_deals_t3_11172020%252523marsLinkCategory%25253D__MARSTRACKING__%252523MKM_RID%25253D__BPNUMBER__%252523MKM_MID%25253D__DELIVERNAME__%252523cid%25253D__CID____SEGMENTCODE__%252523bpid%25253D__BPNUMBER__&utm_source=samsung&utm_medium=email&utm_campaign=holiday_deals_t3_11172020&marsLinkCategory=__MARSTRACKING__&MKM_RID=__BPNUMBER__&MKM_MID=__DELIVERNAME__&cid=__CID____SEGMENTCODE__&bpid=__BPNUMBER__&apn=com.samsung.ecomm&al=samsungestore%3A%2F%2Fopenwebview%23url%3Dhttps%3A%2F%2Fwww.samsung.com%2Fus%2Fapp%2Fgift-ideas%2F%3FofferCID%3DearlyAccess%26segmentName%3DholidayReserve%23utm_source%3Dsamsung%23utm_medium%3Demail%23utm_campaign%3Dholiday_deals_t3_11172020%23marsLinkCategory%3D__MARSTRACKING__%23MKM_RID%3D__BPNUMBER__%23MKM_MID%3D__DELIVERNAME__%23cid%3D__CID____SEGMENTCODE__%23bpid%3D__BPNUMBER__&afl=https%3A%2F%2Fwww.samsung.com%2Fus%2Fgift-ideas%2F%3FofferCID%3DearlyAccess%26utm_source%3Dsamsung%26utm_medium%3Demail%26utm_campaign%3Dholiday_deals_t3_11172020%26marsLinkCategory%3D__MARSTRACKING__%26MKM_RID%3D__BPNUMBER__%26MKM_MID%3D__DELIVERNAME__%26cid%3D__CID____SEGMENTCODE__%26bpid%3D__BPNUMBER__&isi=1274679179&ibi=com.samsung.ShopSamsung&ius=samsungestore&ifl=https%3A%2F%2Fwww.samsung.com%2Fus%2Fgift-ideas%2F%3FofferCID%3DearlyAccess%26utm_source%3Dsamsung%26utm_medium%3Demail%26utm_campaign%3Dholiday_deals_t3_11172020%26marsLinkCategory%3D__MARSTRACKING__%26MKM_RID%3D__BPNUMBER__%26MKM_MID%3D__DELIVERNAME__%26cid%3D__CID____SEGMENTCODE__%26bpid%3D__BPNUMBER__&efr=1 | DK10: =MiscBanners!$O$4 -> NULL | DL10: =MiscBanners!$P$4 -> NULL | DM10: =MiscBanners!$Q$4 -> NULL | DN10: FOOTER | DY10: TC1 | DZ10: NULL | EA10: NULL | EB10: NULL | EC10: §18+ & 50 US/DC only. By 11/29/2020 11:59 PM EST, purchase a qualifying device on device installment plan, 2-year contract plan, lease or outright purchase at full retail price (“Qualifying Purchase”), & receive a Samsung Credit of $100 (“Gift”) instant credit from Samsung for use towards an eligible purchase including select wearables, tablets, PC’s and accessories when you purchase qualifying smartphone (“Qualifying Purchase”) before 01/15/21 at 11:59 PM EST. You must make a Qualifying Purchase on Samsung.com or the Shop Samsung App to receive an instant credit which may be applied instantly or deferred to a future eligible purchase. Gift valid for use on eligible purchases from 11/10/20- 01/15/21 or while supplies last, and is a one-time use certificate; when first used, any value not used is lost. Gift is non-transferrable and limited to 1 instant credit per registered customer. Samsung Credits are valid only at www.Samsung.com or in the App for use towards an eligible purchase. Void where prohibited or restricted by law. Additional restrictions apply. Offer subject to additional terms here. Samsung reserves the right to modify or discontinue offer at any time by posting notice on the app or website | ED10: NULL | EE10: https://www.samsung.com/us/ | EF10: 0 | EG10: NULL | EH10: NULL | EI10: NULL | EJ10: TC2 | EK10: NULL | EL10: NULL | EM10: NULL | EN10: †18+ & 50 US/DC only. By 11/29/2020 11:59 PM EST, purchase a qualifying device on device installment plan, 2-year contract plan, lease or outright purchase at full retail price (“Qualifying Purchase”), & receive a Samsung Credit of $30 (“Gift”) instant credit from Samsung for use towards an eligible purchase including select wearables, tablets, PC’s and accessories when you purchase qualifying smartphone (“Qualifying Purchase”) before 01/15/21 at 11:59 PM EST. You must make a Qualifying Purchase on Samsung.com or the Shop Samsung App to receive an instant credit which may be applied instantly or deferred to a future eligible purchase. Gift valid for use on eligible purchases from 11/10/20- 01/15/21 or while supplies last, and is a one-time use certificate; when first used, any value not used is lost. Gift is non-transferrable and limited to 1 instant credit per registered customer. Samsung Credits are valid only at www.Samsung.com or in the App for use towards an eligible purchase. Void where prohibited or restricted by law. Additional restrictions apply. Offer subject to additional terms here. Samsung reserves the right to modify or discontinue offer at any time by posting notice on the app or website | EO10: NULL | EP10: https://www.samsung.com/us/ | EQ10: 0 | ER10: NULL | ES10: NULL | ET10: NULL | EU10: TC3 | EV10: NULL | EW10: NULL | EX10: NULL | EY10: ‡18+ & 50 US/DC only. Between 10/26/20 at 12:01 AM EST and 11/18/20 at 11:59 PM EST (“Registration Period”), register for the Samsung Holiday instant credit promotion to receive a $20 instant credit from Samsung for use towards an eligible purchase including select wearables, tablets, PC’s and accessories when you purchase qualifying smartphone (“Qualifying Purchase”) before 01/15/21 at 11:59 PM EST. You must make a Qualifying Purchase on Samsung.com or the Shop Samsung App to receive an instant credit which may be applied instantly or deferred to a future eligible purchase. Gift valid for use on eligible purchases from 11/10/20- 01/15/21 or while supplies last, and is a one-time use certificate; when first used, any value not used is lost. Gift is non-transferrable and limited to 1 instant credit per registered customer. Samsung Credits are valid only at www.Samsung.com or in the App for use towards an eligible purchase. Void where prohibited or restricted by law. Additional restrictions apply. Offer subject to additional terms here. Samsung reserves the right to modify or discontinue offer at any time by posting notice on the app or website. | EZ10: NULL | FA10: https://www.samsung.com/us/ | FB10: 0 | FC10: NULL | FD10: NULL | FE10: NULL | FF10: TC4 | FG10: NULL | FH10: NULL | FI10: NULL | FJ10: αMust be an eligible legal resident of the 50 US/DC & at least 18 years old to participate. Purchase at least 4 eligible Samsung Home Appliance products in the same transaction (Refrigerators, Ranges, Countertop Microwaves, Over-the-Range Microwave Ovens, Dishwashers, Wall Ovens, Cooktops, or Range Hoods) (“a Qualifying Purchase”) between 11/04/20 and 12/02/20 on Samsung.com, and you will receive a 10% instant rebate off of the pre-tax purchase price of your Qualifying Purchase (“Gift”). Purchases must include products from different product categories. If more than 4 eligible products are purchased, the additional products purchased are eligible for the discount as long as the eligibility requirements listed above and below are met. Eligible categories are Refrigerators, Ranges, Countertop Microwaves, Over-the-Range Microwave Ovens, Dishwashers, Wall Ovens, Cooktops, or Range Hoods. Samsung Chef Collection, Washers, Dryers, Pedestals, Vacuums, Air Purifiers, AirDresser, Wine Cooler, and all accessories are not eligible. Quantities limited; offer valid while supplies last. One claim per household. This Offer and instant rebate Gift redemption applies to Samsung.com only. Offer cannot be combined with other Samsung offers, rebates, programs, or promotions unless otherwise stated. | FK10: NULL | FL10: 0 | FM10: 0 | FN10: NULL | FO10: NULL | FP10: NULL
